Workbook

Sheet Dashboard
A1: GRAUWASSER · Bewertungsdashboard
A2: Dashboard | B2: Eingaben | C2: Profile | D2: Kalender | E2: Methodik
A3: Wissenschaftlicher Excel-Prototyp · makrofrei · Eingaben blau · Ampelschwellen vorläufig · keine Freigabe
A4: Projekt | C4: =Eingaben!$B$5 -> OGS mit Sporthalle – RECHENBEISPIEL | I4: ="Zeitraum: "&Eingaben!$B$11&" Jahre | Bilanz "&Eingaben!$B$10 -> Zeitraum: 20 Jahre | Bilanz 2026
A5: Gebäudetyp | C5: =Eingaben!$B$6 -> Offene Ganztagsschule mit Sporthalle | I5: =Berechnung!$B$41 -> Modellergebnis mit Beispieldaten
A7: Grauwasseranfall | D7: Betriebswasserbedarf | G7: Nutzbar / Trinkwasser gespart | J7: Trinkwassereinsparquote
A8: =IF(Berechnung!$B$5>0,"Eingaben prüfen",Berechnung!$B$6) -> 742.2 | D8: =IF(Berechnung!$B$5>0,"Eingaben prüfen",Berechnung!$B$9) -> 1018.7 | G8: =IF(Berechnung!$B$5>0,"Eingaben prüfen",Berechnung!$B$10) -> 555.38976 | J8: =IF(Berechnung!$B$5>0,"Eingaben prüfen",Berechnung!$B$22) -> 0.22050651
A11: Gesamtinvestition | D11: Betriebskosten Jahr 1 | G11: Vermiedene Kosten Jahr 1 | J11: Netto-Cashflow Jahr 1
A12: =IF(Berechnung!$B$5>0,"Eingaben prüfen",Berechnung!$B$13) -> 25000 | D12: =IF(Berechnung!$B$5>0,"Eingaben prüfen",Berechnung!$B$16) -> 781.527 | G12: =IF(Berechnung!$B$5>0,"Eingaben prüfen",Berechnung!$B$17) -> 1388.4744 | J12: =IF(Berechnung!$B$5>0,"Eingaben prüfen",Berechnung!$B$18) -> 606.94739
A15: Statische Amortisation | D15: Dynamische Amortisation | G15: Kapitalwert | J15: Deckungsgrad
A16: =IF(Berechnung!$B$5>0,"Eingaben prüfen",Berechnung!$B$19) -> 41.189731 | D16: =IF(Berechnung!$B$5>0,"Eingaben prüfen",Berechnung!$B$21) -> Im Zeitraum nicht erreicht | G16: =IF(Berechnung!$B$5>0,"Eingaben prüfen",Berechnung!$B$20) -> -17797.873 | J16: =IF(Berechnung!$B$5>0,"Eingaben prüfen",Berechnung!$B$23) -> 0.54519462
A19: Ökonomie | E19: Ressourcen | I19: Gesamtbewertung
A20: =Berechnung!$B$31 -> Rot | E20: =Berechnung!$B$32 -> Grün | I20: =Berechnung!$B$33 -> Rot
A21: =IF(Berechnung!$B$5>0,"Bewertung gesperrt: "&Berechnung!$B$5&" Pflichtfehler; Blatt Prüfungen öffnen.","Ökonomie: Kapitalwert "&TEXT(Berechnung!$B$20,"#,##0.00")&" €; Kriterium NPV/Nettoinvestition, Grün ab "&TEXT(Schwellenwerte!B5,"0.0%")&", Gelb ab "&TEXT(Schwellenwerte!B6,"0.0%")&". Ohne Nettoinvestition entscheidet Vorzeichen des NPV.") -> Ökonomie: Kapitalwert -17,797.87 €; Kriterium NPV/Nettoinvestition, Grün ab 0.0%, Gelb ab -20.0%. Ohne Nettoinvestition entscheidet Vorzeichen des NPV.
A22: =IF(Berechnung!$B$5>0,"Ressourcenbewertung gesperrt.","Ressourcen: Einsparquote "&TEXT(Berechnung!$B$22,"0.0%")&"; Grün ab "&TEXT(Schwellenwerte!B9,"0.0%")&", Gelb ab "&TEXT(Schwellenwerte!B10,"0.0%")&". Ohne Einsparung Rot. Keine vollständige Umweltbilanz.") -> Ressourcen: Einsparquote 22.1%; Grün ab 15.0%, Gelb ab 5.0%. Ohne Einsparung Rot. Keine vollständige Umweltbilanz.
A23: ="Gesamt = schlechteste Kategorie einschließlich Nachweisstatus. "&Berechnung!$B$34&". Statische Amortisation nur innerhalb Horizont interpretieren; dynamische Stabilität: "&Berechnung!$B$37&"." -> Gesamt = schlechteste Kategorie einschließlich Nachweisstatus. PRÜFBEDARF: Nachweise ungeklärt. Statische Amortisation nur innerhalb Horizont interpretieren; dynamische Stabilität: Keine positive Rückgewinnung.
A24: =Berechnung!$B$40 -> BEISPIELDATEN · PRÜFBEDARF: Nachweise ungeklärt · Statische Amortisation außerhalb Horizont. · Schwellen vorläufig; Tagesprofil und Quellen projektbezogen validieren.
P46: Wasserbilanz | Q46: m³/a
P47: Rohgrauwasser | Q47: =IF(Berechnung!$B$5=0,Berechnung!$B$6,0) -> 742.2
P48: Aufbereitet | Q48: =IF(Berechnung!$B$5=0,Berechnung!$B$8,0) -> 634.581
P49: Wiederverwendung | Q49: =IF(Berechnung!$B$5=0,Berechnung!$B$10,0) -> 555.38976
P50: Betriebsbedarf | Q50: =IF(Berechnung!$B$5=0,Berechnung!$B$9,0) -> 1018.7
P51: Nachspeisung | Q51: =IF(Berechnung!$B$5=0,Berechnung!$B$11,0) -> 463.31024
P54: Jahr | Q54: Cashflow € | R54: Kumuliert diskontiert €
P55: =IFERROR(MIN(Zahlungen!A7,Eingaben!$B$11),0) -> 0 | Q55: =IF(Berechnung!$B$5=0,INDEX(Zahlungen!$G$7:$G$57,P55+1),0) -> -25000 | R55: =IF(Berechnung!$B$5=0,INDEX(Zahlungen!$J$7:$J$57,P55+1),0) -> -25000
P56: =IFERROR(MIN(Zahlungen!A8,Eingaben!$B$11),0) -> 1 | Q56: =IF(Berechnung!$B$5=0,INDEX(Zahlungen!$G$7:$G$57,P56+1),0) -> 606.94739 | R56: =IF(Berechnung!$B$5=0,INDEX(Zahlungen!$J$7:$J$57,P56+1),0) -> -24410.731
P57: =IFERROR(MIN(Zahlungen!A9,Eingaben!$B$11),0) -> 2 | Q57: =IF(Berechnung!$B$5=0,INDEX(Zahlungen!$G$7:$G$57,P57+1),0) -> 619.08634 | R57: =IF(Berechnung!$B$5=0,INDEX(Zahlungen!$J$7:$J$57,P57+1),0) -> -23827.182
P58: =IFERROR(MIN(Zahlungen!A10,Eingaben!$B$11),0) -> 3 | Q58: =IF(Berechnung!$B$5=0,INDEX(Zahlungen!$G$7:$G$57,P58+1),0) -> 631.46807 | R58: =IF(Berechnung!$B$5=0,INDEX(Zahlungen!$J$7:$J$57,P58+1),0) -> -23249.3
P59: =IFERROR(MIN(Zahlungen!A11,Eingaben!$B$11),0) -> 4 | Q59: =IF(Berechnung!$B$5=0,INDEX(Zahlungen!$G$7:$G$57,P59+1),0) -> 644.09743 | R59: =IF(Berechnung!$B$5=0,INDEX(Zahlungen!$J$7:$J$57,P59+1),0) -> -22677.027
P60: =IFERROR(MIN(Zahlungen!A12,Eingaben!$B$11),0) -> 5 | Q60: =IF(Berechnung!$B$5=0,INDEX(Zahlungen!$G$7:$G$57,P60+1),0) -> 656.97938 | R60: =IF(Berechnung!$B$5=0,INDEX(Zahlungen!$J$7:$J$57,P60+1),0) -> -22110.311
P61: =IFERROR(MIN(Zahlungen!A13,Eingaben!$B$11),0) -> 6 | Q61: =IF(Berechnung!$B$5=0,INDEX(Zahlungen!$G$7:$G$57,P61+1),0) -> 670.11897 | R61: =IF(Berechnung!$B$5=0,INDEX(Zahlungen!$J$7:$J$57,P61+1),0) -> -21549.097
A62: Anleitung → Eingaben → Profile → Kalender → Nachweise → Dashboard → Szenarien. Tabellen rechts liefern Diagrammdaten. | P62: =IFERROR(MIN(Zahlungen!A14,Eingaben!$B$11),0) -> 7 | Q62: =IF(Berechnung!$B$5=0,INDEX(Zahlungen!$G$7:$G$57,P62+1),0) -> 683.52134 | R62: =IF(Berechnung!$B$5=0,INDEX(Zahlungen!$J$7:$J$57,P62+1),0) -> -20993.332
P63: =IFERROR(MIN(Zahlungen!A15,Eingaben!$B$11),0) -> 8 | Q63: =IF(Berechnung!$B$5=0,INDEX(Zahlungen!$G$7:$G$57,P63+1),0) -> 697.19177 | R63: =IF(Berechnung!$B$5=0,INDEX(Zahlungen!$J$7:$J$57,P63+1),0) -> -20442.962
P64: =IFERROR(MIN(Zahlungen!A16,Eingaben!$B$11),0) -> 9 | Q64: =IF(Berechnung!$B$5=0,INDEX(Zahlungen!$G$7:$G$57,P64+1),0) -> 711.13561 | R64: =IF(Berechnung!$B$5=0,INDEX(Zahlungen!$J$7:$J$57,P64+1),0) -> -19897.936
P65: =IFERROR(MIN(Zahlungen!A17,Eingaben!$B$11),0) -> 10 | Q65: =IF(Berechnung!$B$5=0,INDEX(Zahlungen!$G$7:$G$57,P65+1),0) -> -4055.012 | R65: =IF(Berechnung!$B$5=0,INDEX(Zahlungen!$J$7:$J$57,P65+1),0) -> -22915.246
P66: =IFERROR(MIN(Zahlungen!A18,Eingaben!$B$11),0) -> 11 | Q66: =IF(Berechnung!$B$5=0,INDEX(Zahlungen!$G$7:$G$57,P66+1),0) -> 739.86549 | R66: =IF(Berechnung!$B$5=0,INDEX(Zahlungen!$J$7:$J$57,P66+1),0) -> -22380.751
P67: =IFERROR(MIN(Zahlungen!A19,Eingaben!$B$11),0) -> 12 | Q67: =IF(Berechnung!$B$5=0,INDEX(Zahlungen!$G$7:$G$57,P67+1),0) -> 754.6628 | R67: =IF(Berechnung!$B$5=0,INDEX(Zahlungen!$J$7:$J$57,P67+1),0) -> -21851.446
P68: =IFERROR(MIN(Zahlungen!A20,Eingaben!$B$11),0) -> 13 | Q68: =IF(Berechnung!$B$5=0,INDEX(Zahlungen!$G$7:$G$57,P68+1),0) -> 769.75605 | R68: =IF(Berechnung!$B$5=0,INDEX(Zahlungen!$J$7:$J$57,P68+1),0) -> -21327.279
P69: =IFERROR(MIN(Zahlungen!A21,Eingaben!$B$11),0) -> 14 | Q69: =IF(Berechnung!$B$5=0,INDEX(Zahlungen!$G$7:$G$57,P69+1),0) -> 785.15117 | R69: =IF(Berechnung!$B$5=0,INDEX(Zahlungen!$J$7:$J$57,P69+1),0) -> -20808.202
P70: =IFERROR(MIN(Zahlungen!A22,Eingaben!$B$11),0) -> 15 | Q70: =IF(Berechnung!$B$5=0,INDEX(Zahlungen!$G$7:$G$57,P70+1),0) -> 800.8542 | R70: =IF(Berechnung!$B$5=0,INDEX(Zahlungen!$J$7:$J$57,P70+1),0) -> -20294.164
P71: =IFERROR(MIN(Zahlungen!A23,Eingaben!$B$11),0) -> 16 | Q71: =IF(Berechnung!$B$5=0,INDEX(Zahlungen!$G$7:$G$57,P71+1),0) -> 816.87128 | R71: =IF(Berechnung!$B$5=0,INDEX(Zahlungen!$J$7:$J$57,P71+1),0) -> -19785.117
P72: =IFERROR(MIN(Zahlungen!A24,Eingaben!$B$11),0) -> 17 | Q72: =IF(Berechnung!$B$5=0,INDEX(Zahlungen!$G$7:$G$57,P72+1),0) -> 833.2087 | R72: =IF(Berechnung!$B$5=0,INDEX(Zahlungen!$J$7:$J$57,P72+1),0) -> -19281.012
P73: =IFERROR(MIN(Zahlungen!A25,Eingaben!$B$11),0) -> 18 | Q73: =IF(Berechnung!$B$5=0,INDEX(Zahlungen!$G$7:$G$57,P73+1),0) -> 849.87288 | R73: =IF(Berechnung!$B$5=0,INDEX(Zahlungen!$J$7:$J$57,P73+1),0) -> -18781.801
P74: =IFERROR(MIN(Zahlungen!A26,Eingaben!$B$11),0) -> 19 | Q74: =IF(Berechnung!$B$5=0,INDEX(Zahlungen!$G$7:$G$57,P74+1),0) -> 866.87034 | R74: =IF(Berechnung!$B$5=0,INDEX(Zahlungen!$J$7:$J$57,P74+1),0) -> -18287.437
... P105: =IFERROR(MIN(Zahlungen!A57,Eingaben!$B$11),0) -> 20 | Q105: =IF(Berechnung!$B$5=0,INDEX(Zahlungen!$G$7:$G$57,P105+1),0) -> 884.20774 | R105: =IF(Berechnung!$B$5=0,INDEX(Zahlungen!$J$7:$J$57,P105+1),0) -> -17797.873

Sheet Eingaben
A1: Projekt & Anlage
A2: Dashboard | B2: Eingaben | C2: Profile | D2: Kalender | E2: Methodik
A3: Blaue Felder bearbeiten · RECHENBEISPIEL, nicht vermessene Projektwerte
A4: 01 Projekt
A5: Projektname | B5: OGS mit Sporthalle – RECHENBEISPIEL | C5: – | D5: Bezeichnung für Dashboard und Dokumentation.
A6: Gebäudetyp | B6: Offene Ganztagsschule mit Sporthalle | C6: – | D6: Nutzergruppen separat in Nutzungsprofile erfassen.
A7: Standort | B7: Beispielstandort – keine realen Projektdaten | C7: – | D7: Gebührenbescheid und tatsächlichen Ferienkalender prüfen.
A8: Geplante Anlage | B8: Modellanlage – Herstellerdaten ergänzen | C8: – | D8: Kapazität, Energie und Verluste mit Hersteller-/Messdaten belegen.
A9: Nutzer im Referenzprojekt | B9: 300 | C9: Personen | D9: Informative Bezugsgröße; Profile dürfen Teil-/Fremdnutzer abbilden.
A10: Bilanzjahr | B10: 2026 | C10: Jahr | D10: Bei Jahreswechsel Kalenderflaggen kontrollieren; keine automatische Ferienerkennung.
A11: Betrachtungszeitraum | B11: 20 | C11: Jahre | D11: 1–50; Kalenderjahr wird für alle Betriebsjahre wiederholt.
A12: Sonstiger Trinkwasserbedarf | B12: 1500 | C12: m³/a | D12: Baseline außerhalb erfasster Betriebswassernutzungen; keine Doppelzählung.
A14: 02 Anlage, Speicher & Nachweise
A15: Aufbereitungsausbeute | B15: 0.9 | C15: % | D15: Aufbereitet / verarbeitet. Kein garantierter Herstellerwert.
A16: Betriebsverfügbarkeit | B16: 0.95 | C16: % | D16: Pauschaler Tagesfaktor auf min(Rohwasser, Kapazität); kein Ausfallkalender.
A17: Rohwasser-Aufbereitungskapazität | B17: 5 | C17: m³/d | D17: Maximale verarbeitbare Rohwassermenge je Tag vor Verfügbarkeitsfaktor.
A18: Nutzbares Speichervolumen | B18: 2 | C18: m³ | D18: Modell: frischer Tagesrest für genau den Folgetag; alte Reste werden verworfen.
A19: Direkt nutzbarer Tagesanteil | B19: 0.7 | C19: % | D19: Vereinfachte zeitliche Übereinstimmung; mit Stundenprofilen validieren.
A20: Verlust bei Tagesübertrag | B20: 0.02 | C20: % | D20: Volumetrischer Verlust, keine hygienische Inaktivierungsrate.
A21: Hygienische Nachweise | B21: Ungeklärt | C21: Status | D21: Ungeklärt begrenzt Gesamtergebnis auf Gelb; Nicht erfüllt ergibt Rot.
A22: Technische Nachweise | B22: Ungeklärt | C22: Status | D22: Trennung, Nachspeisung, Betrieb und Auslegung projektbezogen prüfen.
A23: Rechtliche Zulässigkeit | B23: Ungeklärt | C23: Status | D23: Behördliche / Betreiberanforderungen separat nachweisen.
A24: Nachweise / Aktenverweise | B24: Projektbezogene Nachweise fehlen; kein Freigabenachweis. | C24: – | D24: Status ist Selbstauskunft; dieses Tool prüft keine Nachweisdokumente.
A26: 03 Wirtschaftlichkeit
A27: Planungskosten | B27: 3000 | C27: € | D27: Einheitlicher Preisstand und Brutto-/Nettobezug für alle Kosten.
A28: Anlagenkosten | B28: 15000 | C28: € | D28: Beschaffung; keine Montage doppelt erfassen.
A29: Montagekosten | B29: 5000 | C29: € | D29: Einbau inklusive erforderlicher Leitungen erfassen.
A30: Sonstige Investitionskosten | B30: 2000 | C30: € | D30: Zusatzleistungen ohne Doppelzählung.
A31: Fördermittel bei Investition | B31: 0 | C31: € | D31: Jahr 0; höchstens Gesamtinvestition. In Varianten begrenzt auf Bruttoinvestition.
A32: Wartungskosten erstes Jahr | B32: 450 | C32: €/a | D32: Wiederkehrende Kosten; Preisentwicklung separat.
A33: Spezifische Aufbereitungsenergie | B33: 1 | C33: kWh/m³ | D33: Bezug: verarbeitetes Rohwasser, auch bei später ungenutztem Wasser.
A34: Strompreis erstes Jahr | B34: 0.3 | C34: €/kWh | D34: Projektbezogener Tarif.
A35: Sonstige Betriebskosten erstes Jahr | B35: 120 | C35: €/a | D35: Labor, Verbrauchsmaterial, Betreiberaufwand etc.
A36: Vermiedener Trinkwasserpreis | B36: 2.5 | C36: €/m³ | D36: Nur mengenabhängig vermeidbarer Anteil; Grundgebühren ausschließen.
A37: Abwassergebühr | B37: 2.2 | C37: €/m³ | D37: Keine automatische Einsparung; Gebührenregelung projektspezifisch.
A38: Anerkannter Abwasser-Einsparanteil | B38: 0 | C38: % | D38: Standard 0 %. Positiver Wert erfordert dokumentierte Gebührenentlastung.
... A46: Abwassergebührensteigerung | B46: 0.02 | C46: %/a | D46: Nur auf bestätigten mengenabhängigen Einsparanteil angewandt.
A47: Beleg der Gebührenentlastung | B47: Keine bestätigte Gebührenentlastung; Ansatz 0 %. | C47: – | D47: Bei positiver Anerkennung voreingestellten Text durch konkreten Beleg ersetzen.
A48: Datenstatus | B48: Beispieldaten | C48: Status | D48: Beispieldaten sind keine Entscheidungsgrundlage für das reale Projekt.

Sheet Nutzungsprofile
A1: Nutzergruppen & Mengen
A2: Dashboard | B2: Eingaben | C2: Profile | D2: Kalender | E2: Methodik
A3: Tage sind Jahres-Nutzungstage je Profil; Verteilung auf aktive Kalendertage der Gruppe. Quellen fachlich separat freigeben.
A5: Quelle / Nutzung | B5: Kalendergruppe | C5: Nutzer | D5: Nutzungen je Tag | E5: Liter je Nutzung | F5: Tage pro Jahr | G5: Jahresmenge m³ | H5: Aktive Kalendertage | I5: Prüfung | J5: Hinweise / Quelle
A6: Duschen Sporthalle | B6: Halle | C6: 120 | D6: 0.6 | E6: 25 | F6: 280 | G6: =IFERROR(C6*D6*E6*F6/1000,0) -> 504 | H6: =IF(B6="Schulbetrieb",SUM(Kalender!$C$5:$C$370),IF(B6="Halle",SUM(Kalender!$D$5:$D$370),IF(B6="Individuell",SUM(Kalender!$E$5:$E$370),0))) -> 280 | I6: =IFERROR(IF(AND(LEN(TRIM(A6))>0,OR(B6="Schulbetrieb",B6="Halle",B6="Individuell"),COUNT(C6:F6)=4,C6>=0,C6<=1000000,D6>=0,D6<=100,E6>=0,E6<=1000,F6>=0,F6<=366,MOD(F6,1)=0,OR(G6=0,F6<=H6)),"OK","FEHLER"),"FEHLER") -> OK | J6: Fiktiver Rechenansatz; Messung / Planungsnachweis ergänzen.
A7: Handwaschbecken Schule | B7: Schulbetrieb | C7: 300 | D7: 3 | E7: 1 | F7: 190 | G7: =IFERROR(C7*D7*E7*F7/1000,0) -> 171 | H7: =IF(B7="Schulbetrieb",SUM(Kalender!$C$5:$C$370),IF(B7="Halle",SUM(Kalender!$D$5:$D$370),IF(B7="Individuell",SUM(Kalender!$E$5:$E$370),0))) -> 190 | I7: =IFERROR(IF(AND(LEN(TRIM(A7))>0,OR(B7="Schulbetrieb",B7="Halle",B7="Individuell"),COUNT(C7:F7)=4,C7>=0,C7<=1000000,D7>=0,D7<=100,E7>=0,E7<=1000,F7>=0,F7<=366,MOD(F7,1)=0,OR(G7=0,F7<=H7)),"OK","FEHLER"),"FEHLER") -> OK | J7: Fiktiver Rechenansatz; Messung / Planungsnachweis ergänzen.
A8: Handwaschbecken Halle | B8: Halle | C8: 120 | D8: 2 | E8: 1 | F8: 280 | G8: =IFERROR(C8*D8*E8*F8/1000,0) -> 67.2 | H8: =IF(B8="Schulbetrieb",SUM(Kalender!$C$5:$C$370),IF(B8="Halle",SUM(Kalender!$D$5:$D$370),IF(B8="Individuell",SUM(Kalender!$E$5:$E$370),0))) -> 280 | I8: =IFERROR(IF(AND(LEN(TRIM(A8))>0,OR(B8="Schulbetrieb",B8="Halle",B8="Individuell"),COUNT(C8:F8)=4,C8>=0,C8<=1000000,D8>=0,D8<=100,E8>=0,E8<=1000,F8>=0,F8<=366,MOD(F8,1)=0,OR(G8=0,F8<=H8)),"OK","FEHLER"),"FEHLER") -> OK | J8: Fiktiver Rechenansatz; Messung / Planungsnachweis ergänzen.
A9: Weitere zulässige Quelle 1 | B9: Individuell | C9: 0 | D9: 0 | E9: 0 | F9: 0 | G9: =IFERROR(C9*D9*E9*F9/1000,0) -> 0 | H9: =IF(B9="Schulbetrieb",SUM(Kalender!$C$5:$C$370),IF(B9="Halle",SUM(Kalender!$D$5:$D$370),IF(B9="Individuell",SUM(Kalender!$E$5:$E$370),0))) -> 0 | I9: =IFERROR(IF(AND(LEN(TRIM(A9))>0,OR(B9="Schulbetrieb",B9="Halle",B9="Individuell"),COUNT(C9:F9)=4,C9>=0,C9<=1000000,D9>=0,D9<=100,E9>=0,E9<=1000,F9>=0,F9<=366,MOD(F9,1)=0,OR(G9=0,F9<=H9)),"OK","FEHLER"),"FEHLER") -> OK | J9: Fiktiver Rechenansatz; Messung / Planungsnachweis ergänzen.
A10: Weitere zulässige Quelle 2 | B10: Individuell | C10: 0 | D10: 0 | E10: 0 | F10: 0 | G10: =IFERROR(C10*D10*E10*F10/1000,0) -> 0 | H10: =IF(B10="Schulbetrieb",SUM(Kalender!$C$5:$C$370),IF(B10="Halle",SUM(Kalender!$D$5:$D$370),IF(B10="Individuell",SUM(Kalender!$E$5:$E$370),0))) -> 0 | I10: =IFERROR(IF(AND(LEN(TRIM(A10))>0,OR(B10="Schulbetrieb",B10="Halle",B10="Individuell"),COUNT(C10:F10)=4,C10>=0,C10<=1000000,D10>=0,D10<=100,E10>=0,E10<=1000,F10>=0,F10<=366,MOD(F10,1)=0,OR(G10=0,F10<=H10)),"OK","FEHLER"),"FEHLER") -> OK | J10: Fiktiver Rechenansatz; Messung / Planungsnachweis ergänzen.
A11: Weitere zulässige Quelle 3 | B11: Individuell | C11: 0 | D11: 0 | E11: 0 | F11: 0 | G11: =IFERROR(C11*D11*E11*F11/1000,0) -> 0 | H11: =IF(B11="Schulbetrieb",SUM(Kalender!$C$5:$C$370),IF(B11="Halle",SUM(Kalender!$D$5:$D$370),IF(B11="Individuell",SUM(Kalender!$E$5:$E$370),0))) -> 0 | I11: =IFERROR(IF(AND(LEN(TRIM(A11))>0,OR(B11="Schulbetrieb",B11="Halle",B11="Individuell"),COUNT(C11:F11)=4,C11>=0,C11<=1000000,D11>=0,D11<=100,E11>=0,E11<=1000,F11>=0,F11<=366,MOD(F11,1)=0,OR(G11=0,F11<=H11)),"OK","FEHLER"),"FEHLER") -> OK | J11: Fiktiver Rechenansatz; Messung / Planungsnachweis ergänzen.
A13: Grauwasserquellen: Küchenabwasser und belastete Quellen nicht ungeprüft als zulässig ansetzen.
A16: Quelle / Nutzung | B16: Kalendergruppe | C16: Nutzer | D16: Nutzungen je Tag | E16: Liter je Nutzung | F16: Tage pro Jahr | G16: Jahresmenge m³ | H16: Aktive Kalendertage | I16: Prüfung | J16: Hinweise / Quelle
A17: WC Schule | B17: Schulbetrieb | C17: 300 | D17: 3 | E17: 4.5 | F17: 190 | G17: =IFERROR(C17*D17*E17*F17/1000,0) -> 769.5 | H17: =IF(B17="Schulbetrieb",SUM(Kalender!$C$5:$C$370),IF(B17="Halle",SUM(Kalender!$D$5:$D$370),IF(B17="Individuell",SUM(Kalender!$E$5:$E$370),0))) -> 190 | I17: =IFERROR(IF(AND(LEN(TRIM(A17))>0,OR(B17="Schulbetrieb",B17="Halle",B17="Individuell"),COUNT(C17:F17)=4,C17>=0,C17<=1000000,D17>=0,D17<=100,E17>=0,E17<=1000,F17>=0,F17<=366,MOD(F17,1)=0,OR(G17=0,F17<=H17)),"OK","FEHLER"),"FEHLER") -> OK | J17: Fiktiver Rechenansatz; Messung / Planungsnachweis ergänzen.
A18: WC Halle | B18: Halle | C18: 120 | D18: 1.5 | E18: 4.5 | F18: 280 | G18: =IFERROR(C18*D18*E18*F18/1000,0) -> 226.8 | H18: =IF(B18="Schulbetrieb",SUM(Kalender!$C$5:$C$370),IF(B18="Halle",SUM(Kalender!$D$5:$D$370),IF(B18="Individuell",SUM(Kalender!$E$5:$E$370),0))) -> 280 | I18: =IFERROR(IF(AND(LEN(TRIM(A18))>0,OR(B18="Schulbetrieb",B18="Halle",B18="Individuell"),COUNT(C18:F18)=4,C18>=0,C18<=1000000,D18>=0,D18<=100,E18>=0,E18<=1000,F18>=0,F18<=366,MOD(F18,1)=0,OR(G18=0,F18<=H18)),"OK","FEHLER"),"FEHLER") -> OK | J18: Fiktiver Rechenansatz; Messung / Planungsnachweis ergänzen.
A19: Urinale Halle | B19: Halle | C19: 80 | D19: 1 | E19: 1 | F19: 280 | G19: =IFERROR(C19*D19*E19*F19/1000,0) -> 22.4 | H19: =IF(B19="Schulbetrieb",SUM(Kalender!$C$5:$C$370),IF(B19="Halle",SUM(Kalender!$D$5:$D$370),IF(B19="Individuell",SUM(Kalender!$E$5:$E$370),0))) -> 280 | I19: =IFERROR(IF(AND(LEN(TRIM(A19))>0,OR(B19="Schulbetrieb",B19="Halle",B19="Individuell"),COUNT(C19:F19)=4,C19>=0,C19<=1000000,D19>=0,D19<=100,E19>=0,E19<=1000,F19>=0,F19<=366,MOD(F19,1)=0,OR(G19=0,F19<=H19)),"OK","FEHLER"),"FEHLER") -> OK | J19: Fiktiver Rechenansatz; Messung / Planungsnachweis ergänzen.
A20: Weitere zulässige Nutzung 1 | B20: Individuell | C20: 0 | D20: 0 | E20: 0 | F20: 0 | G20: =IFERROR(C20*D20*E20*F20/1000,0) -> 0 | H20: =IF(B20="Schulbetrieb",SUM(Kalender!$C$5:$C$370),IF(B20="Halle",SUM(Kalender!$D$5:$D$370),IF(B20="Individuell",SUM(Kalender!$E$5:$E$370),0))) -> 0 | I20: =IFERROR(IF(AND(LEN(TRIM(A20))>0,OR(B20="Schulbetrieb",B20="Halle",B20="Individuell"),COUNT(C20:F20)=4,C20>=0,C20<=1000000,D20>=0,D20<=100,E20>=0,E20<=1000,F20>=0,F20<=366,MOD(F20,1)=0,OR(G20=0,F20<=H20)),"OK","FEHLER"),"FEHLER") -> OK | J20: Fiktiver Rechenansatz; Messung / Planungsnachweis ergänzen.
A21: Weitere zulässige Nutzung 2 | B21: Individuell | C21: 0 | D21: 0 | E21: 0 | F21: 0 | G21: =IFERROR(C21*D21*E21*F21/1000,0) -> 0 | H21: =IF(B21="Schulbetrieb",SUM(Kalender!$C$5:$C$370),IF(B21="Halle",SUM(Kalender!$D$5:$D$370),IF(B21="Individuell",SUM(Kalender!$E$5:$E$370),0))) -> 0 | I21: =IFERROR(IF(AND(LEN(TRIM(A21))>0,OR(B21="Schulbetrieb",B21="Halle",B21="Individuell"),COUNT(C21:F21)=4,C21>=0,C21<=1000000,D21>=0,D21<=100,E21>=0,E21<=1000,F21>=0,F21<=366,MOD(F21,1)=0,OR(G21=0,F21<=H21)),"OK","FEHLER"),"FEHLER") -> OK | J21: Fiktiver Rechenansatz; Messung / Planungsnachweis ergänzen.
A22: Weitere zulässige Nutzung 3 | B22: Individuell | C22: 0 | D22: 0 | E22: 0 | F22: 0 | G22: =IFERROR(C22*D22*E22*F22/1000,0) -> 0 | H22: =IF(B22="Schulbetrieb",SUM(Kalender!$C$5:$C$370),IF(B22="Halle",SUM(Kalender!$D$5:$D$370),IF(B22="Individuell",SUM(Kalender!$E$5:$E$370),0))) -> 0 | I22: =IFERROR(IF(AND(LEN(TRIM(A22))>0,OR(B22="Schulbetrieb",B22="Halle",B22="Individuell"),COUNT(C22:F22)=4,C22>=0,C22<=1000000,D22>=0,D22<=100,E22>=0,E22<=1000,F22>=0,F22<=366,MOD(F22,1)=0,OR(G22=0,F22<=H22)),"OK","FEHLER"),"FEHLER") -> OK | J22: Fiktiver Rechenansatz; Messung / Planungsnachweis ergänzen.
A24: Tagesverteilung = Jahresmenge / aktive Gruppentage. Weniger Profiltage reduzieren die Tagesintensität gleichmäßig.
A25: Schule und Halle dürfen verschiedene Nutzerzahlen / Tage haben. Anzahl im Projektkopf ist nur informativ.
A26: Nutzungstage größer als aktive Gruppentage bei positivem Volumen sind ungültig. Kalender entsprechend ergänzen.

Sheet Kalender
A1: Tageskalender
A2: Dashboard | B2: Eingaben | C2: Profile | D2: Kalender | E2: Methodik
A3: 0 = inaktiv · 1 = aktiv. Fiktiv: 190 Schul-, 280 Hallentage; Ferien/Feiertage selbst abgleichen. Hallentage enthalten Wochenenden.
A4: Datum | B4: Wochentag | C4: Schulbetrieb 0/1 | D4: Halle 0/1 | E4: Individuell 0/1 | F4: Notiz / Datengrundlage | G4: Prüfung
A5: =IFERROR(IF(YEAR(DATE(Eingaben!$B$10,1,1)+0)=Eingaben!$B$10,DATE(Eingaben!$B$10,1,1)+0,""),"") -> 46023 | B5: =IF(A5="","",CHOOSE(WEEKDAY(A5,2),"Mo","Di","Mi","Do","Fr","Sa","So")) -> Do | C5: 1 | D5: 1 | E5: 0 | F5: Fiktives Kalenderprofil – zu ersetzen | G5: =IFERROR(IF(AND(COUNT(C5:E5)=3,OR(C5=0,C5=1),OR(D5=0,D5=1),OR(E5=0,E5=1),OR(A5<>"",SUM(C5:E5)=0)),"OK","FEHLER"),"FEHLER") -> OK
A6: =IFERROR(IF(YEAR(DATE(Eingaben!$B$10,1,1)+1)=Eingaben!$B$10,DATE(Eingaben!$B$10,1,1)+1,""),"") -> 46024 | B6: =IF(A6="","",CHOOSE(WEEKDAY(A6,2),"Mo","Di","Mi","Do","Fr","Sa","So")) -> Fr | C6: 1 | D6: 1 | E6: 0 | G6: =IFERROR(IF(AND(COUNT(C6:E6)=3,OR(C6=0,C6=1),OR(D6=0,D6=1),OR(E6=0,E6=1),OR(A6<>"",SUM(C6:E6)=0)),"OK","FEHLER"),"FEHLER") -> OK
A7: =IFERROR(IF(YEAR(DATE(Eingaben!$B$10,1,1)+2)=Eingaben!$B$10,DATE(Eingaben!$B$10,1,1)+2,""),"") -> 46025 | B7: =IF(A7="","",CHOOSE(WEEKDAY(A7,2),"Mo","Di","Mi","Do","Fr","Sa","So")) -> Sa | C7: 0 | D7: 1 | E7: 0 | G7: =IFERROR(IF(AND(COUNT(C7:E7)=3,OR(C7=0,C7=1),OR(D7=0,D7=1),OR(E7=0,E7=1),OR(A7<>"",SUM(C7:E7)=0)),"OK","FEHLER"),"FEHLER") -> OK
A8: =IFERROR(IF(YEAR(DATE(Eingaben!$B$10,1,1)+3)=Eingaben!$B$10,DATE(Eingaben!$B$10,1,1)+3,""),"") -> 46026 | B8: =IF(A8="","",CHOOSE(WEEKDAY(A8,2),"Mo","Di","Mi","Do","Fr","Sa","So")) -> So | C8: 0 | D8: 1 | E8: 0 | G8: =IFERROR(IF(AND(COUNT(C8:E8)=3,OR(C8=0,C8=1),OR(D8=0,D8=1),OR(E8=0,E8=1),OR(A8<>"",SUM(C8:E8)=0)),"OK","FEHLER"),"FEHLER") -> OK
A9: =IFERROR(IF(YEAR(DATE(Eingaben!$B$10,1,1)+4)=Eingaben!$B$10,DATE(Eingaben!$B$10,1,1)+4,""),"") -> 46027 | B9: =IF(A9="","",CHOOSE(WEEKDAY(A9,2),"Mo","Di","Mi","Do","Fr","Sa","So")) -> Mo | C9: 1 | D9: 1 | E9: 0 | G9: =IFERROR(IF(AND(COUNT(C9:E9)=3,OR(C9=0,C9=1),OR(D9=0,D9=1),OR(E9=0,E9=1),OR(A9<>"",SUM(C9:E9)=0)),"OK","FEHLER"),"FEHLER") -> OK
A10: =IFERROR(IF(YEAR(DATE(Eingaben!$B$10,1,1)+5)=Eingaben!$B$10,DATE(Eingaben!$B$10,1,1)+5,""),"") -> 46028 | B10: =IF(A10="","",CHOOSE(WEEKDAY(A10,2),"Mo","Di","Mi","Do","Fr","Sa","So")) -> Di | C10: 1 | D10: 1 | E10: 0 | G10: =IFERROR(IF(AND(COUNT(C10:E10)=3,OR(C10=0,C10=1),OR(D10=0,D10=1),OR(E10=0,E10=1),OR(A10<>"",SUM(C10:E10)=0)),"OK","FEHLER"),"FEHLER") -> OK
A11: =IFERROR(IF(YEAR(DATE(Eingaben!$B$10,1,1)+6)=Eingaben!$B$10,DATE(Eingaben!$B$10,1,1)+6,""),"") -> 46029 | B11: =IF(A11="","",CHOOSE(WEEKDAY(A11,2),"Mo","Di","Mi","Do","Fr","Sa","So")) -> Mi | C11: 1 | D11: 1 | E11: 0 | G11: =IFERROR(IF(AND(COUNT(C11:E11)=3,OR(C11=0,C11=1),OR(D11=0,D11=1),OR(E11=0,E11=1),OR(A11<>"",SUM(C11:E11)=0)),"OK","FEHLER"),"FEHLER") -> OK
A12: =IFERROR(IF(YEAR(DATE(Eingaben!$B$10,1,1)+7)=Eingaben!$B$10,DATE(Eingaben!$B$10,1,1)+7,""),"") -> 46030 | B12: =IF(A12="","",CHOOSE(WEEKDAY(A12,2),"Mo","Di","Mi","Do","Fr","Sa","So")) -> Do | C12: 1 | D12: 1 | E12: 0 | G12: =IFERROR(IF(AND(COUNT(C12:E12)=3,OR(C12=0,C12=1),OR(D12=0,D12=1),OR(E12=0,E12=1),OR(A12<>"",SUM(C12:E12)=0)),"OK","FEHLER"),"FEHLER") -> OK
A13: =IFERROR(IF(YEAR(DATE(Eingaben!$B$10,1,1)+8)=Eingaben!$B$10,DATE(Eingaben!$B$10,1,1)+8,""),"") -> 46031 | B13: =IF(A13="","",CHOOSE(WEEKDAY(A13,2),"Mo","Di","Mi","Do","Fr","Sa","So")) -> Fr | C13: 1 | D13: 1 | E13: 0 | G13: =IFERROR(IF(AND(COUNT(C13:E13)=3,OR(C13=0,C13=1),OR(D13=0,D13=1),OR(E13=0,E13=1),OR(A13<>"",SUM(C13:E13)=0)),"OK","FEHLER"),"FEHLER") -> OK
A14: =IFERROR(IF(YEAR(DATE(Eingaben!$B$10,1,1)+9)=Eingaben!$B$10,DATE(Eingaben!$B$10,1,1)+9,""),"") -> 46032 | B14: =IF(A14="","",CHOOSE(WEEKDAY(A14,2),"Mo","Di","Mi","Do","Fr","Sa","So")) -> Sa | C14: 0 | D14: 1 | E14: 0 | G14: =IFERROR(IF(AND(COUNT(C14:E14)=3,OR(C14=0,C14=1),OR(D14=0,D14=1),OR(E14=0,E14=1),OR(A14<>"",SUM(C14:E14)=0)),"OK","FEHLER"),"FEHLER") -> OK
A15: =IFERROR(IF(YEAR(DATE(Eingaben!$B$10,1,1)+10)=Eingaben!$B$10,DATE(Eingaben!$B$10,1,1)+10,""),"") -> 46033 | B15: =IF(A15="","",CHOOSE(WEEKDAY(A15,2),"Mo","Di","Mi","Do","Fr","Sa","So")) -> So | C15: 0 | D15: 1 | E15: 0 | G15: =IFERROR(IF(AND(COUNT(C15:E15)=3,OR(C15=0,C15=1),OR(D15=0,D15=1),OR(E15=0,E15=1),OR(A15<>"",SUM(C15:E15)=0)),"OK","FEHLER"),"FEHLER") -> OK
A16: =IFERROR(IF(YEAR(DATE(Eingaben!$B$10,1,1)+11)=Eingaben!$B$10,DATE(Eingaben!$B$10,1,1)+11,""),"") -> 46034 | B16: =IF(A16="","",CHOOSE(WEEKDAY(A16,2),"Mo","Di","Mi","Do","Fr","Sa","So")) -> Mo | C16: 1 | D16: 1 | E16: 0 | G16: =IFERROR(IF(AND(COUNT(C16:E16)=3,OR(C16=0,C16=1),OR(D16=0,D16=1),OR(E16=0,E16=1),OR(A16<>"",SUM(C16:E16)=0)),"OK","FEHLER"),"FEHLER") -> OK
A17: =IFERROR(IF(YEAR(DATE(Eingaben!$B$10,1,1)+12)=Eingaben!$B$10,DATE(Eingaben!$B$10,1,1)+12,""),"") -> 46035 | B17: =IF(A17="","",CHOOSE(WEEKDAY(A17,2),"Mo","Di","Mi","Do","Fr","Sa","So")) -> Di | C17: 1 | D17: 1 | E17: 0 | G17: =IFERROR(IF(AND(COUNT(C17:E17)=3,OR(C17=0,C17=1),OR(D17=0,D17=1),OR(E17=0,E17=1),OR(A17<>"",SUM(C17:E17)=0)),"OK","FEHLER"),"FEHLER") -> OK
A18: =IFERROR(IF(YEAR(DATE(Eingaben!$B$10,1,1)+13)=Eingaben!$B$10,DATE(Eingaben!$B$10,1,1)+13,""),"") -> 46036 | B18: =IF(A18="","",CHOOSE(WEEKDAY(A18,2),"Mo","Di","Mi","Do","Fr","Sa","So")) -> Mi | C18: 1 | D18: 1 | E18: 0 | G18: =IFERROR(IF(AND(COUNT(C18:E18)=3,OR(C18=0,C18=1),OR(D18=0,D18=1),OR(E18=0,E18=1),OR(A18<>"",SUM(C18:E18)=0)),"OK","FEHLER"),"FEHLER") -> OK
A19: =IFERROR(IF(YEAR(DATE(Eingaben!$B$10,1,1)+14)=Eingaben!$B$10,DATE(Eingaben!$B$10,1,1)+14,""),"") -> 46037 | B19: =IF(A19="","",CHOOSE(WEEKDAY(A19,2),"Mo","Di","Mi","Do","Fr","Sa","So")) -> Do | C19: 1 | D19: 1 | E19: 0 | G19: =IFERROR(IF(AND(COUNT(C19:E19)=3,OR(C19=0,C19=1),OR(D19=0,D19=1),OR(E19=0,E19=1),OR(A19<>"",SUM(C19:E19)=0)),"OK","FEHLER"),"FEHLER") -> OK
A20: =IFERROR(IF(YEAR(DATE(Eingaben!$B$10,1,1)+15)=Eingaben!$B$10,DATE(Eingaben!$B$10,1,1)+15,""),"") -> 46038 | B20: =IF(A20="","",CHOOSE(WEEKDAY(A20,2),"Mo","Di","Mi","Do","Fr","Sa","So")) -> Fr | C20: 1 | D20: 1 | E20: 0 | G20: =IFERROR(IF(AND(COUNT(C20:E20)=3,OR(C20=0,C20=1),OR(D20=0,D20=1),OR(E20=0,E20=1),OR(A20<>"",SUM(C20:E20)=0)),"OK","FEHLER"),"FEHLER") -> OK
A21: =IFERROR(IF(YEAR(DATE(Eingaben!$B$10,1,1)+16)=Eingaben!$B$10,DATE(Eingaben!$B$10,1,1)+16,""),"") -> 46039 | B21: =IF(A21="","",CHOOSE(WEEKDAY(A21,2),"Mo","Di","Mi","Do","Fr","Sa","So")) -> Sa | C21: 0 | D21: 1 | E21: 0 | G21: =IFERROR(IF(AND(COUNT(C21:E21)=3,OR(C21=0,C21=1),OR(D21=0,D21=1),OR(E21=0,E21=1),OR(A21<>"",SUM(C21:E21)=0)),"OK","FEHLER"),"FEHLER") -> OK
A22: =IFERROR(IF(YEAR(DATE(Eingaben!$B$10,1,1)+17)=Eingaben!$B$10,DATE(Eingaben!$B$10,1,1)+17,""),"") -> 46040 | B22: =IF(A22="","",CHOOSE(WEEKDAY(A22,2),"Mo","Di","Mi","Do","Fr","Sa","So")) -> So | C22: 0 | D22: 1 | E22: 0 | G22: =IFERROR(IF(AND(COUNT(C22:E22)=3,OR(C22=0,C22=1),OR(D22=0,D22=1),OR(E22=0,E22=1),OR(A22<>"",SUM(C22:E22)=0)),"OK","FEHLER"),"FEHLER") -> OK
A23: =IFERROR(IF(YEAR(DATE(Eingaben!$B$10,1,1)+18)=Eingaben!$B$10,DATE(Eingaben!$B$10,1,1)+18,""),"") -> 46041 | B23: =IF(A23="","",CHOOSE(WEEKDAY(A23,2),"Mo","Di","Mi","Do","Fr","Sa","So")) -> Mo | C23: 1 | D23: 1 | E23: 0 | G23: =IFERROR(IF(AND(COUNT(C23:E23)=3,OR(C23=0,C23=1),OR(D23=0,D23=1),OR(E23=0,E23=1),OR(A23<>"",SUM(C23:E23)=0)),"OK","FEHLER"),"FEHLER") -> OK
A24: =IFERROR(IF(YEAR(DATE(Eingaben!$B$10,1,1)+19)=Eingaben!$B$10,DATE(Eingaben!$B$10,1,1)+19,""),"") -> 46042 | B24: =IF(A24="","",CHOOSE(WEEKDAY(A24,2),"Mo","Di","Mi","Do","Fr","Sa","So")) -> Di | C24: 1 | D24: 1 | E24: 0 | G24: =IFERROR(IF(AND(COUNT(C24:E24)=3,OR(C24=0,C24=1),OR(D24=0,D24=1),OR(E24=0,E24=1),OR(A24<>"",SUM(C24:E24)=0)),"OK","FEHLER"),"FEHLER") -> OK
A25: =IFERROR(IF(YEAR(DATE(Eingaben!$B$10,1,1)+20)=Eingaben!$B$10,DATE(Eingaben!$B$10,1,1)+20,""),"") -> 46043 | B25: =IF(A25="","",CHOOSE(WEEKDAY(A25,2),"Mo","Di","Mi","Do","Fr","Sa","So")) -> Mi | C25: 1 | D25: 1 | E25: 0 | G25: =IFERROR(IF(AND(COUNT(C25:E25)=3,OR(C25=0,C25=1),OR(D25=0,D25=1),OR(E25=0,E25=1),OR(A25<>"",SUM(C25:E25)=0)),"OK","FEHLER"),"FEHLER") -> OK
A26: =IFERROR(IF(YEAR(DATE(Eingaben!$B$10,1,1)+21)=Eingaben!$B$10,DATE(Eingaben!$B$10,1,1)+21,""),"") -> 46044 | B26: =IF(A26="","",CHOOSE(WEEKDAY(A26,2),"Mo","Di","Mi","Do","Fr","Sa","So")) -> Do | C26: 1 | D26: 1 | E26: 0 | G26: =IFERROR(IF(AND(COUNT(C26:E26)=3,OR(C26=0,C26=1),OR(D26=0,D26=1),OR(E26=0,E26=1),OR(A26<>"",SUM(C26:E26)=0)),"OK","FEHLER"),"FEHLER") -> OK
A27: =IFERROR(IF(YEAR(DATE(Eingaben!$B$10,1,1)+22)=Eingaben!$B$10,DATE(Eingaben!$B$10,1,1)+22,""),"") -> 46045 | B27: =IF(A27="","",CHOOSE(WEEKDAY(A27,2),"Mo","Di","Mi","Do","Fr","Sa","So")) -> Fr | C27: 1 | D27: 1 | E27: 0 | G27: =IFERROR(IF(AND(COUNT(C27:E27)=3,OR(C27=0,C27=1),OR(D27=0,D27=1),OR(E27=0,E27=1),OR(A27<>"",SUM(C27:E27)=0)),"OK","FEHLER"),"FEHLER") -> OK
A28: =IFERROR(IF(YEAR(DATE(Eingaben!$B$10,1,1)+23)=Eingaben!$B$10,DATE(Eingaben!$B$10,1,1)+23,""),"") -> 46046 | B28: =IF(A28="","",CHOOSE(WEEKDAY(A28,2),"Mo","Di","Mi","Do","Fr","Sa","So")) -> Sa | C28: 0 | D28: 1 | E28: 0 | G28: =IFERROR(IF(AND(COUNT(C28:E28)=3,OR(C28=0,C28=1),OR(D28=0,D28=1),OR(E28=0,E28=1),OR(A28<>"",SUM(C28:E28)=0)),"OK","FEHLER"),"FEHLER") -> OK
A29: =IFERROR(IF(YEAR(DATE(Eingaben!$B$10,1,1)+24)=Eingaben!$B$10,DATE(Eingaben!$B$10,1,1)+24,""),"") -> 46047 | B29: =IF(A29="","",CHOOSE(WEEKDAY(A29,2),"Mo","Di","Mi","Do","Fr","Sa","So")) -> So | C29: 0 | D29: 1 | E29: 0 | G29: =IFERROR(IF(AND(COUNT(C29:E29)=3,OR(C29=0,C29=1),OR(D29=0,D29=1),OR(E29=0,E29=1),OR(A29<>"",SUM(C29:E29)=0)),"OK","FEHLER"),"FEHLER") -> OK
A30: =IFERROR(IF(YEAR(DATE(Eingaben!$B$10,1,1)+25)=Eingaben!$B$10,DATE(Eingaben!$B$10,1,1)+25,""),"") -> 46048 | B30: =IF(A30="","",CHOOSE(WEEKDAY(A30,2),"Mo","Di","Mi","Do","Fr","Sa","So")) -> Mo | C30: 1 | D30: 1 | E30: 0 | G30: =IFERROR(IF(AND(COUNT(C30:E30)=3,OR(C30=0,C30=1),OR(D30=0,D30=1),OR(E30=0,E30=1),OR(A30<>"",SUM(C30:E30)=0)),"OK","FEHLER"),"FEHLER") -> OK
A31: =IFERROR(IF(YEAR(DATE(Eingaben!$B$10,1,1)+26)=Eingaben!$B$10,DATE(Eingaben!$B$10,1,1)+26,""),"") -> 46049 | B31: =IF(A31="","",CHOOSE(WEEKDAY(A31,2),"Mo","Di","Mi","Do","Fr","Sa","So")) -> Di | C31: 1 | D31: 1 | E31: 0 | G31: =IFERROR(IF(AND(COUNT(C31:E31)=3,OR(C31=0,C31=1),OR(D31=0,D31=1),OR(E31=0,E31=1),OR(A31<>"",SUM(C31:E31)=0)),"OK","FEHLER"),"FEHLER") -> OK
A32: =IFERROR(IF(YEAR(DATE(Eingaben!$B$10,1,1)+27)=Eingaben!$B$10,DATE(Eingaben!$B$10,1,1)+27,""),"") -> 46050 | B32: =IF(A32="","",CHOOSE(WEEKDAY(A32,2),"Mo","Di","Mi","Do","Fr","Sa","So")) -> Mi | C32: 1 | D32: 1 | E32: 0 | G32: =IFERROR(IF(AND(COUNT(C32:E32)=3,OR(C32=0,C32=1),OR(D32=0,D32=1),OR(E32=0,E32=1),OR(A32<>"",SUM(C32:E32)=0)),"OK","FEHLER"),"FEHLER") -> OK
A33: =IFERROR(IF(YEAR(DATE(Eingaben!$B$10,1,1)+28)=Eingaben!$B$10,DATE(Eingaben!$B$10,1,1)+28,""),"") -> 46051 | B33: =IF(A33="","",CHOOSE(WEEKDAY(A33,2),"Mo","Di","Mi","Do","Fr","Sa","So")) -> Do | C33: 1 | D33: 1 | E33: 0 | G33: =IFERROR(IF(AND(COUNT(C33:E33)=3,OR(C33=0,C33=1),OR(D33=0,D33=1),OR(E33=0,E33=1),OR(A33<>"",SUM(C33:E33)=0)),"OK","FEHLER"),"FEHLER") -> OK
A34: =IFERROR(IF(YEAR(DATE(Eingaben!$B$10,1,1)+29)=Eingaben!$B$10,DATE(Eingaben!$B$10,1,1)+29,""),"") -> 46052 | B34: =IF(A34="","",CHOOSE(WEEKDAY(A34,2),"Mo","Di","Mi","Do","Fr","Sa","So")) -> Fr | C34: 1 | D34: 1 | E34: 0 | G34: =IFERROR(IF(AND(COUNT(C34:E34)=3,OR(C34=0,C34=1),OR(D34=0,D34=1),OR(E34=0,E34=1),OR(A34<>"",SUM(C34:E34)=0)),"OK","FEHLER"),"FEHLER") -> OK
A35: =IFERROR(IF(YEAR(DATE(Eingaben!$B$10,1,1)+30)=Eingaben!$B$10,DATE(Eingaben!$B$10,1,1)+30,""),"") -> 46053 | B35: =IF(A35="","",CHOOSE(WEEKDAY(A35,2),"Mo","Di","Mi","Do","Fr","Sa","So")) -> Sa | C35: 0 | D35: 1 | E35: 0 | G35: =IFERROR(IF(AND(COUNT(C35:E35)=3,OR(C35=0,C35=1),OR(D35=0,D35=1),OR(E35=0,E35=1),OR(A35<>"",SUM(C35:E35)=0)),"OK","FEHLER"),"FEHLER") -> OK
A36: =IFERROR(IF(YEAR(DATE(Eingaben!$B$10,1,1)+31)=Eingaben!$B$10,DATE(Eingaben!$B$10,1,1)+31,""),"") -> 46054 | B36: =IF(A36="","",CHOOSE(WEEKDAY(A36,2),"Mo","Di","Mi","Do","Fr","Sa","So")) -> So | C36: 0 | D36: 1 | E36: 0 | G36: =IFERROR(IF(AND(COUNT(C36:E36)=3,OR(C36=0,C36=1),OR(D36=0,D36=1),OR(E36=0,E36=1),OR(A36<>"",SUM(C36:E36)=0)),"OK","FEHLER"),"FEHLER") -> OK
A37: =IFERROR(IF(YEAR(DATE(Eingaben!$B$10,1,1)+32)=Eingaben!$B$10,DATE(Eingaben!$B$10,1,1)+32,""),"") -> 46055 | B37: =IF(A37="","",CHOOSE(WEEKDAY(A37,2),"Mo","Di","Mi","Do","Fr","Sa","So")) -> Mo | C37: 1 | D37: 1 | E37: 0 | G37: =IFERROR(IF(AND(COUNT(C37:E37)=3,OR(C37=0,C37=1),OR(D37=0,D37=1),OR(E37=0,E37=1),OR(A37<>"",SUM(C37:E37)=0)),"OK","FEHLER"),"FEHLER") -> OK
A38: =IFERROR(IF(YEAR(DATE(Eingaben!$B$10,1,1)+33)=Eingaben!$B$10,DATE(Eingaben!$B$10,1,1)+33,""),"") -> 46056 | B38: =IF(A38="","",CHOOSE(WEEKDAY(A38,2),"Mo","Di","Mi","Do","Fr","Sa","So")) -> Di | C38: 1 | D38: 1 | E38: 0 | G38: =IFERROR(IF(AND(COUNT(C38:E38)=3,OR(C38=0,C38=1),OR(D38=0,D38=1),OR(E38=0,E38=1),OR(A38<>"",SUM(C38:E38)=0)),"OK","FEHLER"),"FEHLER") -> OK
A39: =IFERROR(IF(YEAR(DATE(Eingaben!$B$10,1,1)+34)=Eingaben!$B$10,DATE(Eingaben!$B$10,1,1)+34,""),"") -> 46057 | B39: =IF(A39="","",CHOOSE(WEEKDAY(A39,2),"Mo","Di","Mi","Do","Fr","Sa","So")) -> Mi | C39: 1 | D39: 1 | E39: 0 | G39: =IFERROR(IF(AND(COUNT(C39:E39)=3,OR(C39=0,C39=1),OR(D39=0,D39=1),OR(E39=0,E39=1),OR(A39<>"",SUM(C39:E39)=0)),"OK","FEHLER"),"FEHLER") -> OK
A40: =IFERROR(IF(YEAR(DATE(Eingaben!$B$10,1,1)+35)=Eingaben!$B$10,DATE(Eingaben!$B$10,1,1)+35,""),"") -> 46058 | B40: =IF(A40="","",CHOOSE(WEEKDAY(A40,2),"Mo","Di","Mi","Do","Fr","Sa","So")) -> Do | C40: 1 | D40: 1 | E40: 0 | G40: =IFERROR(IF(AND(COUNT(C40:E40)=3,OR(C40=0,C40=1),OR(D40=0,D40=1),OR(E40=0,E40=1),OR(A40<>"",SUM(C40:E40)=0)),"OK","FEHLER"),"FEHLER") -> OK
A41: =IFERROR(IF(YEAR(DATE(Eingaben!$B$10,1,1)+36)=Eingaben!$B$10,DATE(Eingaben!$B$10,1,1)+36,""),"") -> 46059 | B41: =IF(A41="","",CHOOSE(WEEKDAY(A41,2),"Mo","Di","Mi","Do","Fr","Sa","So")) -> Fr | C41: 1 | D41: 1 | E41: 0 | G41: =IFERROR(IF(AND(COUNT(C41:E41)=3,OR(C41=0,C41=1),OR(D41=0,D41=1),OR(E41=0,E41=1),OR(A41<>"",SUM(C41:E41)=0)),"OK","FEHLER"),"FEHLER") -> OK
A42: =IFERROR(IF(YEAR(DATE(Eingaben!$B$10,1,1)+37)=Eingaben!$B$10,DATE(Eingaben!$B$10,1,1)+37,""),"") -> 46060 | B42: =IF(A42="","",CHOOSE(WEEKDAY(A42,2),"Mo","Di","Mi","Do","Fr","Sa","So")) -> Sa | C42: 0 | D42: 1 | E42: 0 | G42: =IFERROR(IF(AND(COUNT(C42:E42)=3,OR(C42=0,C42=1),OR(D42=0,D42=1),OR(E42=0,E42=1),OR(A42<>"",SUM(C42:E42)=0)),"OK","FEHLER"),"FEHLER") -> OK
A43: =IFERROR(IF(YEAR(DATE(Eingaben!$B$10,1,1)+38)=Eingaben!$B$10,DATE(Eingaben!$B$10,1,1)+38,""),"") -> 46061 | B43: =IF(A43="","",CHOOSE(WEEKDAY(A43,2),"Mo","Di","Mi","Do","Fr","Sa","So")) -> So | C43: 0 | D43: 1 | E43: 0 | G43: =IFERROR(IF(AND(COUNT(C43:E43)=3,OR(C43=0,C43=1),OR(D43=0,D43=1),OR(E43=0,E43=1),OR(A43<>"",SUM(C43:E43)=0)),"OK","FEHLER"),"FEHLER") -> OK
A44: =IFERROR(IF(YEAR(DATE(Eingaben!$B$10,1,1)+39)=Eingaben!$B$10,DATE(Eingaben!$B$10,1,1)+39,""),"") -> 46062 | B44: =IF(A44="","",CHOOSE(WEEKDAY(A44,2),"Mo","Di","Mi","Do","Fr","Sa","So")) -> Mo | C44: 1 | D44: 1 | E44: 0 | G44: =IFERROR(IF(AND(COUNT(C44:E44)=3,OR(C44=0,C44=1),OR(D44=0,D44=1),OR(E44=0,E44=1),OR(A44<>"",SUM(C44:E44)=0)),"OK","FEHLER"),"FEHLER") -> OK
A45: =IFERROR(IF(YEAR(DATE(Eingaben!$B$10,1,1)+40)=Eingaben!$B$10,DATE(Eingaben!$B$10,1,1)+40,""),"") -> 46063 | B45: =IF(A45="","",CHOOSE(WEEKDAY(A45,2),"Mo","Di","Mi","Do","Fr","Sa","So")) -> Di | C45: 1 | D45: 1 | E45: 0 | G45: =IFERROR(IF(AND(COUNT(C45:E45)=3,OR(C45=0,C45=1),OR(D45=0,D45=1),OR(E45=0,E45=1),OR(A45<>"",SUM(C45:E45)=0)),"OK","FEHLER"),"FEHLER") -> OK
A46: =IFERROR(IF(YEAR(DATE(Eingaben!$B$10,1,1)+41)=Eingaben!$B$10,DATE(Eingaben!$B$10,1,1)+41,""),"") -> 46064 | B46: =IF(A46="","",CHOOSE(WEEKDAY(A46,2),"Mo","Di","Mi","Do","Fr","Sa","So")) -> Mi | C46: 1 | D46: 1 | E46: 0 | G46: =IFERROR(IF(AND(COUNT(C46:E46)=3,OR(C46=0,C46=1),OR(D46=0,D46=1),OR(E46=0,E46=1),OR(A46<>"",SUM(C46:E46)=0)),"OK","FEHLER"),"FEHLER") -> OK
A47: =IFERROR(IF(YEAR(DATE(Eingaben!$B$10,1,1)+42)=Eingaben!$B$10,DATE(Eingaben!$B$10,1,1)+42,""),"") -> 46065 | B47: =IF(A47="","",CHOOSE(WEEKDAY(A47,2),"Mo","Di","Mi","Do","Fr","Sa","So")) -> Do | C47: 1 | D47: 1 | E47: 0 | G47: =IFERROR(IF(AND(COUNT(C47:E47)=3,OR(C47=0,C47=1),OR(D47=0,D47=1),OR(E47=0,E47=1),OR(A47<>"",SUM(C47:E47)=0)),"OK","FEHLER"),"FEHLER") -> OK
A48: =IFERROR(IF(YEAR(DATE(Eingaben!$B$10,1,1)+43)=Eingaben!$B$10,DATE(Eingaben!$B$10,1,1)+43,""),"") -> 46066 | B48: =IF(A48="","",CHOOSE(WEEKDAY(A48,2),"Mo","Di","Mi","Do","Fr","Sa","So")) -> Fr | C48: 1 | D48: 1 | E48: 0 | G48: =IFERROR(IF(AND(COUNT(C48:E48)=3,OR(C48=0,C48=1),OR(D48=0,D48=1),OR(E48=0,E48=1),OR(A48<>"",SUM(C48:E48)=0)),"OK","FEHLER"),"FEHLER") -> OK
A49: =IFERROR(IF(YEAR(DATE(Eingaben!$B$10,1,1)+44)=Eingaben!$B$10,DATE(Eingaben!$B$10,1,1)+44,""),"") -> 46067 | B49: =IF(A49="","",CHOOSE(WEEKDAY(A49,2),"Mo","Di","Mi","Do","Fr","Sa","So")) -> Sa | C49: 0 | D49: 1 | E49: 0 | G49: =IFERROR(IF(AND(COUNT(C49:E49)=3,OR(C49=0,C49=1),OR(D49=0,D49=1),OR(E49=0,E49=1),OR(A49<>"",SUM(C49:E49)=0)),"OK","FEHLER"),"FEHLER") -> OK
A50: =IFERROR(IF(YEAR(DATE(Eingaben!$B$10,1,1)+45)=Eingaben!$B$10,DATE(Eingaben!$B$10,1,1)+45,""),"") -> 46068 | B50: =IF(A50="","",CHOOSE(WEEKDAY(A50,2),"Mo","Di","Mi","Do","Fr","Sa","So")) -> So | C50: 0 | D50: 1 | E50: 0 | G50: =IFERROR(IF(AND(COUNT(C50:E50)=3,OR(C50=0,C50=1),OR(D50=0,D50=1),OR(E50=0,E50=1),OR(A50<>"",SUM(C50:E50)=0)),"OK","FEHLER"),"FEHLER") -> OK
A51: =IFERROR(IF(YEAR(DATE(Eingaben!$B$10,1,1)+46)=Eingaben!$B$10,DATE(Eingaben!$B$10,1,1)+46,""),"") -> 46069 | B51: =IF(A51="","",CHOOSE(WEEKDAY(A51,2),"Mo","Di","Mi","Do","Fr","Sa","So")) -> Mo | C51: 1 | D51: 1 | E51: 0 | G51: =IFERROR(IF(AND(COUNT(C51:E51)=3,OR(C51=0,C51=1),OR(D51=0,D51=1),OR(E51=0,E51=1),OR(A51<>"",SUM(C51:E51)=0)),"OK","FEHLER"),"FEHLER") -> OK
A52: =IFERROR(IF(YEAR(DATE(Eingaben!$B$10,1,1)+47)=Eingaben!$B$10,DATE(Eingaben!$B$10,1,1)+47,""),"") -> 46070 | B52: =IF(A52="","",CHOOSE(WEEKDAY(A52,2),"Mo","Di","Mi","Do","Fr","Sa","So")) -> Di | C52: 1 | D52: 1 | E52: 0 | G52: =IFERROR(IF(AND(COUNT(C52:E52)=3,OR(C52=0,C52=1),OR(D52=0,D52=1),OR(E52=0,E52=1),OR(A52<>"",SUM(C52:E52)=0)),"OK","FEHLER"),"FEHLER") -> OK
A53: =IFERROR(IF(YEAR(DATE(Eingaben!$B$10,1,1)+48)=Eingaben!$B$10,DATE(Eingaben!$B$10,1,1)+48,""),"") -> 46071 | B53: =IF(A53="","",CHOOSE(WEEKDAY(A53,2),"Mo","Di","Mi","Do","Fr","Sa","So")) -> Mi | C53: 1 | D53: 1 | E53: 0 | G53: =IFERROR(IF(AND(COUNT(C53:E53)=3,OR(C53=0,C53=1),OR(D53=0,D53=1),OR(E53=0,E53=1),OR(A53<>"",SUM(C53:E53)=0)),"OK","FEHLER"),"FEHLER") -> OK
A54: =IFERROR(IF(YEAR(DATE(Eingaben!$B$10,1,1)+49)=Eingaben!$B$10,DATE(Eingaben!$B$10,1,1)+49,""),"") -> 46072 | B54: =IF(A54="","",CHOOSE(WEEKDAY(A54,2),"Mo","Di","Mi","Do","Fr","Sa","So")) -> Do | C54: 1 | D54: 1 | E54: 0 | G54: =IFERROR(IF(AND(COUNT(C54:E54)=3,OR(C54=0,C54=1),OR(D54=0,D54=1),OR(E54=0,E54=1),OR(A54<>"",SUM(C54:E54)=0)),"OK","FEHLER"),"FEHLER") -> OK
A55: =IFERROR(IF(YEAR(DATE(Eingaben!$B$10,1,1)+50)=Eingaben!$B$10,DATE(Eingaben!$B$10,1,1)+50,""),"") -> 46073 | B55: =IF(A55="","",CHOOSE(WEEKDAY(A55,2),"Mo","Di","Mi","Do","Fr","Sa","So")) -> Fr | C55: 1 | D55: 1 | E55: 0 | G55: =IFERROR(IF(AND(COUNT(C55:E55)=3,OR(C55=0,C55=1),OR(D55=0,D55=1),OR(E55=0,E55=1),OR(A55<>"",SUM(C55:E55)=0)),"OK","FEHLER"),"FEHLER") -> OK
A56: =IFERROR(IF(YEAR(DATE(Eingaben!$B$10,1,1)+51)=Eingaben!$B$10,DATE(Eingaben!$B$10,1,1)+51,""),"") -> 46074 | B56: =IF(A56="","",CHOOSE(WEEKDAY(A56,2),"Mo","Di","Mi","Do","Fr","Sa","So")) -> Sa | C56: 0 | D56: 1 | E56: 0 | G56: =IFERROR(IF(AND(COUNT(C56:E56)=3,OR(C56=0,C56=1),OR(D56=0,D56=1),OR(E56=0,E56=1),OR(A56<>"",SUM(C56:E56)=0)),"OK","FEHLER"),"FEHLER") -> OK
A57: =IFERROR(IF(YEAR(DATE(Eingaben!$B$10,1,1)+52)=Eingaben!$B$10,DATE(Eingaben!$B$10,1,1)+52,""),"") -> 46075 | B57: =IF(A57="","",CHOOSE(WEEKDAY(A57,2),"Mo","Di","Mi","Do","Fr","Sa","So")) -> So | C57: 0 | D57: 1 | E57: 0 | G57: =IFERROR(IF(AND(COUNT(C57:E57)=3,OR(C57=0,C57=1),OR(D57=0,D57=1),OR(E57=0,E57=1),OR(A57<>"",SUM(C57:E57)=0)),"OK","FEHLER"),"FEHLER") -> OK
A58: =IFERROR(IF(YEAR(DATE(Eingaben!$B$10,1,1)+53)=Eingaben!$B$10,DATE(Eingaben!$B$10,1,1)+53,""),"") -> 46076 | B58: =IF(A58="","",CHOOSE(WEEKDAY(A58,2),"Mo","Di","Mi","Do","Fr","Sa","So")) -> Mo | C58: 1 | D58: 1 | E58: 0 | G58: =IFERROR(IF(AND(COUNT(C58:E58)=3,OR(C58=0,C58=1),OR(D58=0,D58=1),OR(E58=0,E58=1),OR(A58<>"",SUM(C58:E58)=0)),"OK","FEHLER"),"FEHLER") -> OK
A59: =IFERROR(IF(YEAR(DATE(Eingaben!$B$10,1,1)+54)=Eingaben!$B$10,DATE(Eingaben!$B$10,1,1)+54,""),"") -> 46077 | B59: =IF(A59="","",CHOOSE(WEEKDAY(A59,2),"Mo","Di","Mi","Do","Fr","Sa","So")) -> Di | C59: 1 | D59: 1 | E59: 0 | G59: =IFERROR(IF(AND(COUNT(C59:E59)=3,OR(C59=0,C59=1),OR(D59=0,D59=1),OR(E59=0,E59=1),OR(A59<>"",SUM(C59:E59)=0)),"OK","FEHLER"),"FEHLER") -> OK
A60: =IFERROR(IF(YEAR(DATE(Eingaben!$B$10,1,1)+55)=Eingaben!$B$10,DATE(Eingaben!$B$10,1,1)+55,""),"") -> 46078 | B60: =IF(A60="","",CHOOSE(WEEKDAY(A60,2),"Mo","Di","Mi","Do","Fr","Sa","So")) -> Mi | C60: 1 | D60: 1 | E60: 0 | G60: =IFERROR(IF(AND(COUNT(C60:E60)=3,OR(C60=0,C60=1),OR(D60=0,D60=1),OR(E60=0,E60=1),OR(A60<>"",SUM(C60:E60)=0)),"OK","FEHLER"),"FEHLER") -> OK
A61: =IFERROR(IF(YEAR(DATE(Eingaben!$B$10,1,1)+56)=Eingaben!$B$10,DATE(Eingaben!$B$10,1,1)+56,""),"") -> 46079 | B61: =IF(A61="","",CHOOSE(WEEKDAY(A61,2),"Mo","Di","Mi","Do","Fr","Sa","So")) -> Do | C61: 1 | D61: 1 | E61: 0 | G61: =IFERROR(IF(AND(COUNT(C61:E61)=3,OR(C61=0,C61=1),OR(D61=0,D61=1),OR(E61=0,E61=1),OR(A61<>"",SUM(C61:E61)=0)),"OK","FEHLER"),"FEHLER") -> OK
A62: =IFERROR(IF(YEAR(DATE(Eingaben!$B$10,1,1)+57)=Eingaben!$B$10,DATE(Eingaben!$B$10,1,1)+57,""),"") -> 46080 | B62: =IF(A62="","",CHOOSE(WEEKDAY(A62,2),"Mo","Di","Mi","Do","Fr","Sa","So")) -> Fr | C62: 1 | D62: 1 | E62: 0 | G62: =IFERROR(IF(AND(COUNT(C62:E62)=3,OR(C62=0,C62=1),OR(D62=0,D62=1),OR(E62=0,E62=1),OR(A62<>"",SUM(C62:E62)=0)),"OK","FEHLER"),"FEHLER") -> OK
A63: =IFERROR(IF(YEAR(DATE(Eingaben!$B$10,1,1)+58)=Eingaben!$B$10,DATE(Eingaben!$B$10,1,1)+58,""),"") -> 46081 | B63: =IF(A63="","",CHOOSE(WEEKDAY(A63,2),"Mo","Di","Mi","Do","Fr","Sa","So")) -> Sa | C63: 0 | D63: 1 | E63: 0 | G63: =IFERROR(IF(AND(COUNT(C63:E63)=3,OR(C63=0,C63=1),OR(D63=0,D63=1),OR(E63=0,E63=1),OR(A63<>"",SUM(C63:E63)=0)),"OK","FEHLER"),"FEHLER") -> OK
A64: =IFERROR(IF(YEAR(DATE(Eingaben!$B$10,1,1)+59)=Eingaben!$B$10,DATE(Eingaben!$B$10,1,1)+59,""),"") -> 46082 | B64: =IF(A64="","",CHOOSE(WEEKDAY(A64,2),"Mo","Di","Mi","Do","Fr","Sa","So")) -> So | C64: 0 | D64: 1 | E64: 0 | G64: =IFERROR(IF(AND(COUNT(C64:E64)=3,OR(C64=0,C64=1),OR(D64=0,D64=1),OR(E64=0,E64=1),OR(A64<>"",SUM(C64:E64)=0)),"OK","FEHLER"),"FEHLER") -> OK
A65: =IFERROR(IF(YEAR(DATE(Eingaben!$B$10,1,1)+60)=Eingaben!$B$10,DATE(Eingaben!$B$10,1,1)+60,""),"") -> 46083 | B65: =IF(A65="","",CHOOSE(WEEKDAY(A65,2),"Mo","Di","Mi","Do","Fr","Sa","So")) -> Mo | C65: 1 | D65: 1 | E65: 0 | G65: =IFERROR(IF(AND(COUNT(C65:E65)=3,OR(C65=0,C65=1),OR(D65=0,D65=1),OR(E65=0,E65=1),OR(A65<>"",SUM(C65:E65)=0)),"OK","FEHLER"),"FEHLER") -> OK
A66: =IFERROR(IF(YEAR(DATE(Eingaben!$B$10,1,1)+61)=Eingaben!$B$10,DATE(Eingaben!$B$10,1,1)+61,""),"") -> 46084 | B66: =IF(A66="","",CHOOSE(WEEKDAY(A66,2),"Mo","Di","Mi","Do","Fr","Sa","So")) -> Di | C66: 1 | D66: 1 | E66: 0 | G66: =IFERROR(IF(AND(COUNT(C66:E66)=3,OR(C66=0,C66=1),OR(D66=0,D66=1),OR(E66=0,E66=1),OR(A66<>"",SUM(C66:E66)=0)),"OK","FEHLER"),"FEHLER") -> OK
A67: =IFERROR(IF(YEAR(DATE(Eingaben!$B$10,1,1)+62)=Eingaben!$B$10,DATE(Eingaben!$B$10,1,1)+62,""),"") -> 46085 | B67: =IF(A67="","",CHOOSE(WEEKDAY(A67,2),"Mo","Di","Mi","Do","Fr","Sa","So")) -> Mi | C67: 1 | D67: 1 | E67: 0 | G67: =IFERROR(IF(AND(COUNT(C67:E67)=3,OR(C67=0,C67=1),OR(D67=0,D67=1),OR(E67=0,E67=1),OR(A67<>"",SUM(C67:E67)=0)),"OK","FEHLER"),"FEHLER") -> OK
A68: =IFERROR(IF(YEAR(DATE(Eingaben!$B$10,1,1)+63)=Eingaben!$B$10,DATE(Eingaben!$B$10,1,1)+63,""),"") -> 46086 | B68: =IF(A68="","",CHOOSE(WEEKDAY(A68,2),"Mo","Di","Mi","Do","Fr","Sa","So")) -> Do | C68: 1 | D68: 1 | E68: 0 | G68: =IFERROR(IF(AND(COUNT(C68:E68)=3,OR(C68=0,C68=1),OR(D68=0,D68=1),OR(E68=0,E68=1),OR(A68<>"",SUM(C68:E68)=0)),"OK","FEHLER"),"FEHLER") -> OK
A69: =IFERROR(IF(YEAR(DATE(Eingaben!$B$10,1,1)+64)=Eingaben!$B$10,DATE(Eingaben!$B$10,1,1)+64,""),"") -> 46087 | B69: =IF(A69="","",CHOOSE(WEEKDAY(A69,2),"Mo","Di","Mi","Do","Fr","Sa","So")) -> Fr | C69: 1 | D69: 1 | E69: 0 | G69: =IFERROR(IF(AND(COUNT(C69:E69)=3,OR(C69=0,C69=1),OR(D69=0,D69=1),OR(E69=0,E69=1),OR(A69<>"",SUM(C69:E69)=0)),"OK","FEHLER"),"FEHLER") -> OK
A70: =IFERROR(IF(YEAR(DATE(Eingaben!$B$10,1,1)+65)=Eingaben!$B$10,DATE(Eingaben!$B$10,1,1)+65,""),"") -> 46088 | B70: =IF(A70="","",CHOOSE(WEEKDAY(A70,2),"Mo","Di","Mi","Do","Fr","Sa","So")) -> Sa | C70: 0 | D70: 1 | E70: 0 | G70: =IFERROR(IF(AND(COUNT(C70:E70)=3,OR(C70=0,C70=1),OR(D70=0,D70=1),OR(E70=0,E70=1),OR(A70<>"",SUM(C70:E70)=0)),"OK","FEHLER"),"FEHLER") -> OK
A71: =IFERROR(IF(YEAR(DATE(Eingaben!$B$10,1,1)+66)=Eingaben!$B$10,DATE(Eingaben!$B$10,1,1)+66,""),"") -> 46089 | B71: =IF(A71="","",CHOOSE(WEEKDAY(A71,2),"Mo","Di","Mi","Do","Fr","Sa","So")) -> So | C71: 0 | D71: 1 | E71: 0 | G71: =IFERROR(IF(AND(COUNT(C71:E71)=3,OR(C71=0,C71=1),OR(D71=0,D71=1),OR(E71=0,E71=1),OR(A71<>"",SUM(C71:E71)=0)),"OK","FEHLER"),"FEHLER") -> OK
A72: =IFERROR(IF(YEAR(DATE(Eingaben!$B$10,1,1)+67)=Eingaben!$B$10,DATE(Eingaben!$B$10,1,1)+67,""),"") -> 46090 | B72: =IF(A72="","",CHOOSE(WEEKDAY(A72,2),"Mo","Di","Mi","Do","Fr","Sa","So")) -> Mo | C72: 1 | D72: 1 | E72: 0 | G72: =IFERROR(IF(AND(COUNT(C72:E72)=3,OR(C72=0,C72=1),OR(D72=0,D72=1),OR(E72=0,E72=1),OR(A72<>"",SUM(C72:E72)=0)),"OK","FEHLER"),"FEHLER") -> OK
A73: =IFERROR(IF(YEAR(DATE(Eingaben!$B$10,1,1)+68)=Eingaben!$B$10,DATE(Eingaben!$B$10,1,1)+68,""),"") -> 46091 | B73: =IF(A73="","",CHOOSE(WEEKDAY(A73,2),"Mo","Di","Mi","Do","Fr","Sa","So")) -> Di | C73: 1 | D73: 1 | E73: 0 | G73: =IFERROR(IF(AND(COUNT(C73:E73)=3,OR(C73=0,C73=1),OR(D73=0,D73=1),OR(E73=0,E73=1),OR(A73<>"",SUM(C73:E73)=0)),"OK","FEHLER"),"FEHLER") -> OK
A74: =IFERROR(IF(YEAR(DATE(Eingaben!$B$10,1,1)+69)=Eingaben!$B$10,DATE(Eingaben!$B$10,1,1)+69,""),"") -> 46092 | B74: =IF(A74="","",CHOOSE(WEEKDAY(A74,2),"Mo","Di","Mi","Do","Fr","Sa","So")) -> Mi | C74: 1 | D74: 1 | E74: 0 | G74: =IFERROR(IF(AND(COUNT(C74:E74)=3,OR(C74=0,C74=1),OR(D74=0,D74=1),OR(E74=0,E74=1),OR(A74<>"",SUM(C74:E74)=0)),"OK","FEHLER"),"FEHLER") -> OK
A75: =IFERROR(IF(YEAR(DATE(Eingaben!$B$10,1,1)+70)=Eingaben!$B$10,DATE(Eingaben!$B$10,1,1)+70,""),"") -> 46093 | B75: =IF(A75="","",CHOOSE(WEEKDAY(A75,2),"Mo","Di","Mi","Do","Fr","Sa","So")) -> Do | C75: 1 | D75: 1 | E75: 0 | G75: =IFERROR(IF(AND(COUNT(C75:E75)=3,OR(C75=0,C75=1),OR(D75=0,D75=1),OR(E75=0,E75=1),OR(A75<>"",SUM(C75:E75)=0)),"OK","FEHLER"),"FEHLER") -> OK
A76: =IFERROR(IF(YEAR(DATE(Eingaben!$B$10,1,1)+71)=Eingaben!$B$10,DATE(Eingaben!$B$10,1,1)+71,""),"") -> 46094 | B76: =IF(A76="","",CHOOSE(WEEKDAY(A76,2),"Mo","Di","Mi","Do","Fr","Sa","So")) -> Fr | C76: 1 | D76: 1 | E76: 0 | G76: =IFERROR(IF(AND(COUNT(C76:E76)=3,OR(C76=0,C76=1),OR(D76=0,D76=1),OR(E76=0,E76=1),OR(A76<>"",SUM(C76:E76)=0)),"OK","FEHLER"),"FEHLER") -> OK
A77: =IFERROR(IF(YEAR(DATE(Eingaben!$B$10,1,1)+72)=Eingaben!$B$10,DATE(Eingaben!$B$10,1,1)+72,""),"") -> 46095 | B77: =IF(A77="","",CHOOSE(WEEKDAY(A77,2),"Mo","Di","Mi","Do","Fr","Sa","So")) -> Sa | C77: 0 | D77: 1 | E77: 0 | G77: =IFERROR(IF(AND(COUNT(C77:E77)=3,OR(C77=0,C77=1),OR(D77=0,D77=1),OR(E77=0,E77=1),OR(A77<>"",SUM(C77:E77)=0)),"OK","FEHLER"),"FEHLER") -> OK
A78: =IFERROR(IF(YEAR(DATE(Eingaben!$B$10,1,1)+73)=Eingaben!$B$10,DATE(Eingaben!$B$10,1,1)+73,""),"") -> 46096 | B78: =IF(A78="","",CHOOSE(WEEKDAY(A78,2),"Mo","Di","Mi","Do","Fr","Sa","So")) -> So | C78: 0 | D78: 1 | E78: 0 | G78: =IFERROR(IF(AND(COUNT(C78:E78)=3,OR(C78=0,C78=1),OR(D78=0,D78=1),OR(E78=0,E78=1),OR(A78<>"",SUM(C78:E78)=0)),"OK","FEHLER"),"FEHLER") -> OK
A79: =IFERROR(IF(YEAR(DATE(Eingaben!$B$10,1,1)+74)=Eingaben!$B$10,DATE(Eingaben!$B$10,1,1)+74,""),"") -> 46097 | B79: =IF(A79="","",CHOOSE(WEEKDAY(A79,2),"Mo","Di","Mi","Do","Fr","Sa","So")) -> Mo | C79: 1 | D79: 1 | E79: 0 | G79: =IFERROR(IF(AND(COUNT(C79:E79)=3,OR(C79=0,C79=1),OR(D79=0,D79=1),OR(E79=0,E79=1),OR(A79<>"",SUM(C79:E79)=0)),"OK","FEHLER"),"FEHLER") -> OK
A80: =IFERROR(IF(YEAR(DATE(Eingaben!$B$10,1,1)+75)=Eingaben!$B$10,DATE(Eingaben!$B$10,1,1)+75,""),"") -> 46098 | B80: =IF(A80="","",CHOOSE(WEEKDAY(A80,2),"Mo","Di","Mi","Do","Fr","Sa","So")) -> Di | C80: 1 | D80: 1 | E80: 0 | G80: =IFERROR(IF(AND(COUNT(C80:E80)=3,OR(C80=0,C80=1),OR(D80=0,D80=1),OR(E80=0,E80=1),OR(A80<>"",SUM(C80:E80)=0)),"OK","FEHLER"),"FEHLER") -> OK
A81: =IFERROR(IF(YEAR(DATE(Eingaben!$B$10,1,1)+76)=Eingaben!$B$10,DATE(Eingaben!$B$10,1,1)+76,""),"") -> 46099 | B81: =IF(A81="","",CHOOSE(WEEKDAY(A81,2),"Mo","Di","Mi","Do","Fr","Sa","So")) -> Mi | C81: 1 | D81: 1 | E81: 0 | G81: =IFERROR(IF(AND(COUNT(C81:E81)=3,OR(C81=0,C81=1),OR(D81=0,D81=1),OR(E81=0,E81=1),OR(A81<>"",SUM(C81:E81)=0)),"OK","FEHLER"),"FEHLER") -> OK
A82: =IFERROR(IF(YEAR(DATE(Eingaben!$B$10,1,1)+77)=Eingaben!$B$10,DATE(Eingaben!$B$10,1,1)+77,""),"") -> 46100 | B82: =IF(A82="","",CHOOSE(WEEKDAY(A82,2),"Mo","Di","Mi","Do","Fr","Sa","So")) -> Do | C82: 1 | D82: 1 | E82: 0 | G82: =IFERROR(IF(AND(COUNT(C82:E82)=3,OR(C82=0,C82=1),OR(D82=0,D82=1),OR(E82=0,E82=1),OR(A82<>"",SUM(C82:E82)=0)),"OK","FEHLER"),"FEHLER") -> OK
A83: =IFERROR(IF(YEAR(DATE(Eingaben!$B$10,1,1)+78)=Eingaben!$B$10,DATE(Eingaben!$B$10,1,1)+78,""),"") -> 46101 | B83: =IF(A83="","",CHOOSE(WEEKDAY(A83,2),"Mo","Di","Mi","Do","Fr","Sa","So")) -> Fr | C83: 1 | D83: 1 | E83: 0 | G83: =IFERROR(IF(AND(COUNT(C83:E83)=3,OR(C83=0,C83=1),OR(D83=0,D83=1),OR(E83=0,E83=1),OR(A83<>"",SUM(C83:E83)=0)),"OK","FEHLER"),"FEHLER") -> OK
A84: =IFERROR(IF(YEAR(DATE(Eingaben!$B$10,1,1)+79)=Eingaben!$B$10,DATE(Eingaben!$B$10,1,1)+79,""),"") -> 46102 | B84: =IF(A84="","",CHOOSE(WEEKDAY(A84,2),"Mo","Di","Mi","Do","Fr","Sa","So")) -> Sa | C84: 0 | D84: 1 | E84: 0 | G84: =IFERROR(IF(AND(COUNT(C84:E84)=3,OR(C84=0,C84=1),OR(D84=0,D84=1),OR(E84=0,E84=1),OR(A84<>"",SUM(C84:E84)=0)),"OK","FEHLER"),"FEHLER") -> OK
A85: =IFERROR(IF(YEAR(DATE(Eingaben!$B$10,1,1)+80)=Eingaben!$B$10,DATE(Eingaben!$B$10,1,1)+80,""),"") -> 46103 | B85: =IF(A85="","",CHOOSE(WEEKDAY(A85,2),"Mo","Di","Mi","Do","Fr","Sa","So")) -> So | C85: 0 | D85: 1 | E85: 0 | G85: =IFERROR(IF(AND(COUNT(C85:E85)=3,OR(C85=0,C85=1),OR(D85=0,D85=1),OR(E85=0,E85=1),OR(A85<>"",SUM(C85:E85)=0)),"OK","FEHLER"),"FEHLER") -> OK
A86: =IFERROR(IF(YEAR(DATE(Eingaben!$B$10,1,1)+81)=Eingaben!$B$10,DATE(Eingaben!$B$10,1,1)+81,""),"") -> 46104 | B86: =IF(A86="","",CHOOSE(WEEKDAY(A86,2),"Mo","Di","Mi","Do","Fr","Sa","So")) -> Mo | C86: 1 | D86: 1 | E86: 0 | G86: =IFERROR(IF(AND(COUNT(C86:E86)=3,OR(C86=0,C86=1),OR(D86=0,D86=1),OR(E86=0,E86=1),OR(A86<>"",SUM(C86:E86)=0)),"OK","FEHLER"),"FEHLER") -> OK
A87: =IFERROR(IF(YEAR(DATE(Eingaben!$B$10,1,1)+82)=Eingaben!$B$10,DATE(Eingaben!$B$10,1,1)+82,""),"") -> 46105 | B87: =IF(A87="","",CHOOSE(WEEKDAY(A87,2),"Mo","Di","Mi","Do","Fr","Sa","So")) -> Di | C87: 1 | D87: 1 | E87: 0 | G87: =IFERROR(IF(AND(COUNT(C87:E87)=3,OR(C87=0,C87=1),OR(D87=0,D87=1),OR(E87=0,E87=1),OR(A87<>"",SUM(C87:E87)=0)),"OK","FEHLER"),"FEHLER") -> OK
A88: =IFERROR(IF(YEAR(DATE(Eingaben!$B$10,1,1)+83)=Eingaben!$B$10,DATE(Eingaben!$B$10,1,1)+83,""),"") -> 46106 | B88: =IF(A88="","",CHOOSE(WEEKDAY(A88,2),"Mo","Di","Mi","Do","Fr","Sa","So")) -> Mi | C88: 1 | D88: 1 | E88: 0 | G88: =IFERROR(IF(AND(COUNT(C88:E88)=3,OR(C88=0,C88=1),OR(D88=0,D88=1),OR(E88=0,E88=1),OR(A88<>"",SUM(C88:E88)=0)),"OK","FEHLER"),"FEHLER") -> OK
A89: =IFERROR(IF(YEAR(DATE(Eingaben!$B$10,1,1)+84)=Eingaben!$B$10,DATE(Eingaben!$B$10,1,1)+84,""),"") -> 46107 | B89: =IF(A89="","",CHOOSE(WEEKDAY(A89,2),"Mo","Di","Mi","Do","Fr","Sa","So")) -> Do | C89: 1 | D89: 1 | E89: 0 | G89: =IFERROR(IF(AND(COUNT(C89:E89)=3,OR(C89=0,C89=1),OR(D89=0,D89=1),OR(E89=0,E89=1),OR(A89<>"",SUM(C89:E89)=0)),"OK","FEHLER"),"FEHLER") -> OK
A90: =IFERROR(IF(YEAR(DATE(Eingaben!$B$10,1,1)+85)=Eingaben!$B$10,DATE(Eingaben!$B$10,1,1)+85,""),"") -> 46108 | B90: =IF(A90="","",CHOOSE(WEEKDAY(A90,2),"Mo","Di","Mi","Do","Fr","Sa","So")) -> Fr | C90: 1 | D90: 1 | E90: 0 | G90: =IFERROR(IF(AND(COUNT(C90:E90)=3,OR(C90=0,C90=1),OR(D90=0,D90=1),OR(E90=0,E90=1),OR(A90<>"",SUM(C90:E90)=0)),"OK","FEHLER"),"FEHLER") -> OK
A91: =IFERROR(IF(YEAR(DATE(Eingaben!$B$10,1,1)+86)=Eingaben!$B$10,DATE(Eingaben!$B$10,1,1)+86,""),"") -> 46109 | B91: =IF(A91="","",CHOOSE(WEEKDAY(A91,2),"Mo","Di","Mi","Do","Fr","Sa","So")) -> Sa | C91: 0 | D91: 1 | E91: 0 | G91: =IFERROR(IF(AND(COUNT(C91:E91)=3,OR(C91=0,C91=1),OR(D91=0,D91=1),OR(E91=0,E91=1),OR(A91<>"",SUM(C91:E91)=0)),"OK","FEHLER"),"FEHLER") -> OK
A92: =IFERROR(IF(YEAR(DATE(Eingaben!$B$10,1,1)+87)=Eingaben!$B$10,DATE(Eingaben!$B$10,1,1)+87,""),"") -> 46110 | B92: =IF(A92="","",CHOOSE(WEEKDAY(A92,2),"Mo","Di","Mi","Do","Fr","Sa","So")) -> So | C92: 0 | D92: 1 | E92: 0 | G92: =IFERROR(IF(AND(COUNT(C92:E92)=3,OR(C92=0,C92=1),OR(D92=0,D92=1),OR(E92=0,E92=1),OR(A92<>"",SUM(C92:E92)=0)),"OK","FEHLER"),"FEHLER") -> OK
A93: =IFERROR(IF(YEAR(DATE(Eingaben!$B$10,1,1)+88)=Eingaben!$B$10,DATE(Eingaben!$B$10,1,1)+88,""),"") -> 46111 | B93: =IF(A93="","",CHOOSE(WEEKDAY(A93,2),"Mo","Di","Mi","Do","Fr","Sa","So")) -> Mo | C93: 1 | D93: 1 | E93: 0 | G93: =IFERROR(IF(AND(COUNT(C93:E93)=3,OR(C93=0,C93=1),OR(D93=0,D93=1),OR(E93=0,E93=1),OR(A93<>"",SUM(C93:E93)=0)),"OK","FEHLER"),"FEHLER") -> OK
A94: =IFERROR(IF(YEAR(DATE(Eingaben!$B$10,1,1)+89)=Eingaben!$B$10,DATE(Eingaben!$B$10,1,1)+89,""),"") -> 46112 | B94: =IF(A94="","",CHOOSE(WEEKDAY(A94,2),"Mo","Di","Mi","Do","Fr","Sa","So")) -> Di | C94: 1 | D94: 1 | E94: 0 | G94: =IFERROR(IF(AND(COUNT(C94:E94)=3,OR(C94=0,C94=1),OR(D94=0,D94=1),OR(E94=0,E94=1),OR(A94<>"",SUM(C94:E94)=0)),"OK","FEHLER"),"FEHLER") -> OK
A95: =IFERROR(IF(YEAR(DATE(Eingaben!$B$10,1,1)+90)=Eingaben!$B$10,DATE(Eingaben!$B$10,1,1)+90,""),"") -> 46113 | B95: =IF(A95="","",CHOOSE(WEEKDAY(A95,2),"Mo","Di","Mi","Do","Fr","Sa","So")) -> Mi | C95: 1 | D95: 1 | E95: 0 | G95: =IFERROR(IF(AND(COUNT(C95:E95)=3,OR(C95=0,C95=1),OR(D95=0,D95=1),OR(E95=0,E95=1),OR(A95<>"",SUM(C95:E95)=0)),"OK","FEHLER"),"FEHLER") -> OK
A96: =IFERROR(IF(YEAR(DATE(Eingaben!$B$10,1,1)+91)=Eingaben!$B$10,DATE(Eingaben!$B$10,1,1)+91,""),"") -> 46114 | B96: =IF(A96="","",CHOOSE(WEEKDAY(A96,2),"Mo","Di","Mi","Do","Fr","Sa","So")) -> Do | C96: 1 | D96: 1 | E96: 0 | G96: =IFERROR(IF(AND(COUNT(C96:E96)=3,OR(C96=0,C96=1),OR(D96=0,D96=1),OR(E96=0,E96=1),OR(A96<>"",SUM(C96:E96)=0)),"OK","FEHLER"),"FEHLER") -> OK
A97: =IFERROR(IF(YEAR(DATE(Eingaben!$B$10,1,1)+92)=Eingaben!$B$10,DATE(Eingaben!$B$10,1,1)+92,""),"") -> 46115 | B97: =IF(A97="","",CHOOSE(WEEKDAY(A97,2),"Mo","Di","Mi","Do","Fr","Sa","So")) -> Fr | C97: 1 | D97: 1 | E97: 0 | G97: =IFERROR(IF(AND(COUNT(C97:E97)=3,OR(C97=0,C97=1),OR(D97=0,D97=1),OR(E97=0,E97=1),OR(A97<>"",SUM(C97:E97)=0)),"OK","FEHLER"),"FEHLER") -> OK
A98: =IFERROR(IF(YEAR(DATE(Eingaben!$B$10,1,1)+93)=Eingaben!$B$10,DATE(Eingaben!$B$10,1,1)+93,""),"") -> 46116 | B98: =IF(A98="","",CHOOSE(WEEKDAY(A98,2),"Mo","Di","Mi","Do","Fr","Sa","So")) -> Sa | C98: 0 | D98: 1 | E98: 0 | G98: =IFERROR(IF(AND(COUNT(C98:E98)=3,OR(C98=0,C98=1),OR(D98=0,D98=1),OR(E98=0,E98=1),OR(A98<>"",SUM(C98:E98)=0)),"OK","FEHLER"),"FEHLER") -> OK
A99: =IFERROR(IF(YEAR(DATE(Eingaben!$B$10,1,1)+94)=Eingaben!$B$10,DATE(Eingaben!$B$10,1,1)+94,""),"") -> 46117 | B99: =IF(A99="","",CHOOSE(WEEKDAY(A99,2),"Mo","Di","Mi","Do","Fr","Sa","So")) -> So | C99: 0 | D99: 1 | E99: 0 | G99: =IFERROR(IF(AND(COUNT(C99:E99)=3,OR(C99=0,C99=1),OR(D99=0,D99=1),OR(E99=0,E99=1),OR(A99<>"",SUM(C99:E99)=0)),"OK","FEHLER"),"FEHLER") -> OK
A100: =IFERROR(IF(YEAR(DATE(Eingaben!$B$10,1,1)+95)=Eingaben!$B$10,DATE(Eingaben!$B$10,1,1)+95,""),"") -> 46118 | B100: =IF(A100="","",CHOOSE(WEEKDAY(A100,2),"Mo","Di","Mi","Do","Fr","Sa","So")) -> Mo | C100: 1 | D100: 1 | E100: 0 | G100: =IFERROR(IF(AND(COUNT(C100:E100)=3,OR(C100=0,C100=1),OR(D100=0,D100=1),OR(E100=0,E100=1),OR(A100<>"",SUM(C100:E100)=0)),"OK","FEHLER"),"FEHLER") -> OK
...

Sheet Schwellenwerte
A1: Ampelmodell & Schwellen
A2: Dashboard | B2: Eingaben | C2: Profile | D2: Kalender | E2: Methodik
A3: Alle Grenzwerte sind vorläufige Modellannahmen, keine normativen oder empirisch validierten Eignungsgrenzen.
A4: Kriterium | B4: Schwelle | C4: Einheit | D4: Status / Interpretation | E4: Begründung
A5: Ökonomie Grün ab | B5: 0 | C5: NPV / Nettoinvestition | D5: Vorläufig · zu validieren | E5: Grün ab Kapitalwert ≥ 0 bei Basisschwelle 0 %.
A6: Ökonomie Gelb ab | B6: -0.2 | C6: NPV / Nettoinvestition | D6: Vorläufig · zu validieren | E6: Verlust bis 20 % des Kapitaleinsatzes als vorläufiger Prüfbereich.
A9: Ressourcen Grün ab | B9: 0.15 | C9: Anteil Baseline-Trinkwasser | D9: Vorläufig · zu validieren | E9: Vorläufig: 15 % der Baseline aus Betriebsbedarf + sonstigem Bedarf.
A10: Ressourcen Gelb ab | B10: 0.05 | C10: Anteil Baseline-Trinkwasser | D10: Vorläufig · zu validieren | E10: Vorläufig: 5 %; keine Literaturgrenze.
A13: Aggregation: schlechteste Kategorie entscheidet (konservatives Maximum). Keine kompensatorische gewichtete Summe.
A14: Grün / Gelb / Rot entsprechen günstiger / bedingter / ungünstiger Eignung innerhalb dieses Modells.
A15: Nachweise: Nicht erfüllt → Rot; Ungeklärt → mindestens Gelb + Prüfbedarf; alle Nachgewiesen → keine Begrenzung.
A16: Fehlende oder ungültige Pflichtwerte → Nicht bewertbar; kein Ersatz durch Nullwerte im Dashboard.
A17: Keine Wassereinsparung → Ressourcen Rot unabhängig von Schwellen. Kein Bedarf ist kein positiver Nutzen.
A18: Bei Nettoinvestition = 0: NPV ≥ 0 → ökonomisch Grün, NPV < 0 → Rot; Quotient ist nicht definiert.
A19: Technisch/hygienisch/rechtlich sind Nachweisstatus, keine vom Tool erteilte Freigabe. Selbstauskunft dokumentieren.
A20: Gewichtete Bewertung wurde verworfen: Kompensation verdeckt Konflikte, korrelierte KPIs würden doppelt zählen.
A21: Konservative Aggregation macht Zielkonflikte sichtbar; alternative Gewichte erst mit Beteiligten validieren.
A22: Wissenschaftliche Validierung: Schwellen begründen, Expertenreview und Sensitivität durchführen; Nutzertest separat.

Sheet Wasserbilanz
A1: Wasserbilanz · 366 Tageszeilen
A2: Dashboard | B2: Eingaben | C2: Profile | D2: Kalender | E2: Methodik
A3: m³ je Tag · Speicher aus Vortag zuerst nutzen, dann direkte Deckung; alte Reste spätestens am Tagesende verwerfen.
A4: Datum | B4: Schule | C4: Halle | D4: Rohgrauwasser | E4: Betriebsbedarf | F4: Verarbeitet | G4: Aufbereitet | H4: Altbestand nach Verlust | I4: Verbrauch Alt | J4: Direktverbrauch | K4: Endbestand frisch | L4: Wiederverwendung | M4: Nachspeisung | N4: Überschuss frisch | O4: Speicherverlust / Alt | P4: Bilanzrest | Q4: Tank Vortag
A5: =Kalender!A5 -> 46023 | B5: =Kalender!C5 -> 1 | C5: =Kalender!D5 -> 1 | D5: =IF(Prüfungen!$B$4=0,(IFERROR(SUMIF(Nutzungsprofile!$B$6:$B$11,"Schulbetrieb",Nutzungsprofile!$G$6:$G$11)*Kalender!C5/SUM(Kalender!$C$5:$C$370),0)+IFERROR(SUMIF(Nutzungsprofile!$B$6:$B$11,"Halle",Nutzungsprofile!$G$6:$G$11)*Kalender!D5/SUM(Kalender!$D$5:$D$370),0)+IFERROR(SUMIF(Nutzungsprofile!$B$6:$B$11,"Individuell",Nutzungsprofile!$G$6:$G$11)*Kalender!E5/SUM(Kalender!$E$5:$E$370),0)),0) -> 2.94 | E5: =IF(Prüfungen!$B$4=0,(IFERROR(SUMIF(Nutzungsprofile!$B$17:$B$22,"Schulbetrieb",Nutzungsprofile!$G$17:$G$22)*Kalender!C5/SUM(Kalender!$C$5:$C$370),0)+IFERROR(SUMIF(Nutzungsprofile!$B$17:$B$22,"Halle",Nutzungsprofile!$G$17:$G$22)*Kalender!D5/SUM(Kalender!$D$5:$D$370),0)+IFERROR(SUMIF(Nutzungsprofile!$B$17:$B$22,"Individuell",Nutzungsprofile!$G$17:$G$22)*Kalender!E5/SUM(Kalender!$E$5:$E$370),0)),0) -> 4.94 | F5: =IFERROR(MIN(D5,Eingaben!$B$17)*Eingaben!$B$16,0) -> 2.793 | G5: =IFERROR(F5*Eingaben!$B$15,0) -> 2.5137 | H5: =IFERROR(Q5*(1-Eingaben!$B$20),0) -> 0 | I5: =MIN(H5,E5) -> 0 | J5: =IFERROR(MIN(G5*Eingaben!$B$19,MAX(0,E5-I5)),0) -> 1.75959 | K5: =IFERROR(MIN(Eingaben!$B$18,MAX(0,G5-J5)),0) -> 0.75411 | L5: =I5+J5 -> 1.75959 | M5: =MAX(0,E5-L5) -> 3.18041 | N5: =MAX(0,G5-J5-K5) -> 0 | O5: =Q5-I5 -> 0 | P5: =G5+Q5-L5-N5-O5-K5 -> 0 | Q5: =0 -> 0
A6: =Kalender!A6 -> 46024 | B6: =Kalender!C6 -> 1 | C6: =Kalender!D6 -> 1 | D6: =IF(Prüfungen!$B$4=0,(IFERROR(SUMIF(Nutzungsprofile!$B$6:$B$11,"Schulbetrieb",Nutzungsprofile!$G$6:$G$11)*Kalender!C6/SUM(Kalender!$C$5:$C$370),0)+IFERROR(SUMIF(Nutzungsprofile!$B$6:$B$11,"Halle",Nutzungsprofile!$G$6:$G$11)*Kalender!D6/SUM(Kalender!$D$5:$D$370),0)+IFERROR(SUMIF(Nutzungsprofile!$B$6:$B$11,"Individuell",Nutzungsprofile!$G$6:$G$11)*Kalender!E6/SUM(Kalender!$E$5:$E$370),0)),0) -> 2.94 | E6: =IF(Prüfungen!$B$4=0,(IFERROR(SUMIF(Nutzungsprofile!$B$17:$B$22,"Schulbetrieb",Nutzungsprofile!$G$17:$G$22)*Kalender!C6/SUM(Kalender!$C$5:$C$370),0)+IFERROR(SUMIF(Nutzungsprofile!$B$17:$B$22,"Halle",Nutzungsprofile!$G$17:$G$22)*Kalender!D6/SUM(Kalender!$D$5:$D$370),0)+IFERROR(SUMIF(Nutzungsprofile!$B$17:$B$22,"Individuell",Nutzungsprofile!$G$17:$G$22)*Kalender!E6/SUM(Kalender!$E$5:$E$370),0)),0) -> 4.94 | F6: =IFERROR(MIN(D6,Eingaben!$B$17)*Eingaben!$B$16,0) -> 2.793 | G6: =IFERROR(F6*Eingaben!$B$15,0) -> 2.5137 | H6: =IFERROR(Q6*(1-Eingaben!$B$20),0) -> 0.7390278 | I6: =MIN(H6,E6) -> 0.7390278 | J6: =IFERROR(MIN(G6*Eingaben!$B$19,MAX(0,E6-I6)),0) -> 1.75959 | K6: =IFERROR(MIN(Eingaben!$B$18,MAX(0,G6-J6)),0) -> 0.75411 | L6: =I6+J6 -> 2.4986178 | M6: =MAX(0,E6-L6) -> 2.4413822 | N6: =MAX(0,G6-J6-K6) -> 0 | O6: =Q6-I6 -> 0.0150822 | P6: =G6+Q6-L6-N6-O6-K6 -> 0 | Q6: =IF(A6="",0,K5) -> 0.75411
A7: =Kalender!A7 -> 46025 | B7: =Kalender!C7 -> 0 | C7: =Kalender!D7 -> 1 | D7: =IF(Prüfungen!$B$4=0,(IFERROR(SUMIF(Nutzungsprofile!$B$6:$B$11,"Schulbetrieb",Nutzungsprofile!$G$6:$G$11)*Kalender!C7/SUM(Kalender!$C$5:$C$370),0)+IFERROR(SUMIF(Nutzungsprofile!$B$6:$B$11,"Halle",Nutzungsprofile!$G$6:$G$11)*Kalender!D7/SUM(Kalender!$D$5:$D$370),0)+IFERROR(SUMIF(Nutzungsprofile!$B$6:$B$11,"Individuell",Nutzungsprofile!$G$6:$G$11)*Kalender!E7/SUM(Kalender!$E$5:$E$370),0)),0) -> 2.04 | E7: =IF(Prüfungen!$B$4=0,(IFERROR(SUMIF(Nutzungsprofile!$B$17:$B$22,"Schulbetrieb",Nutzungsprofile!$G$17:$G$22)*Kalender!C7/SUM(Kalender!$C$5:$C$370),0)+IFERROR(SUMIF(Nutzungsprofile!$B$17:$B$22,"Halle",Nutzungsprofile!$G$17:$G$22)*Kalender!D7/SUM(Kalender!$D$5:$D$370),0)+IFERROR(SUMIF(Nutzungsprofile!$B$17:$B$22,"Individuell",Nutzungsprofile!$G$17:$G$22)*Kalender!E7/SUM(Kalender!$E$5:$E$370),0)),0) -> 0.89 | F7: =IFERROR(MIN(D7,Eingaben!$B$17)*Eingaben!$B$16,0) -> 1.938 | G7: =IFERROR(F7*Eingaben!$B$15,0) -> 1.7442 | H7: =IFERROR(Q7*(1-Eingaben!$B$20),0) -> 0.7390278 | I7: =MIN(H7,E7) -> 0.7390278 | J7: =IFERROR(MIN(G7*Eingaben!$B$19,MAX(0,E7-I7)),0) -> 0.1509722 | K7: =IFERROR(MIN(Eingaben!$B$18,MAX(0,G7-J7)),0) -> 1.5932278 | L7: =I7+J7 -> 0.89 | M7: =MAX(0,E7-L7) -> 0 | N7: =MAX(0,G7-J7-K7) -> 0 | O7: =Q7-I7 -> 0.0150822 | P7: =G7+Q7-L7-N7-O7-K7 -> 0 | Q7: =IF(A7="",0,K6) -> 0.75411
A8: =Kalender!A8 -> 46026 | B8: =Kalender!C8 -> 0 | C8: =Kalender!D8 -> 1 | D8: =IF(Prüfungen!$B$4=0,(IFERROR(SUMIF(Nutzungsprofile!$B$6:$B$11,"Schulbetrieb",Nutzungsprofile!$G$6:$G$11)*Kalender!C8/SUM(Kalender!$C$5:$C$370),0)+IFERROR(SUMIF(Nutzungsprofile!$B$6:$B$11,"Halle",Nutzungsprofile!$G$6:$G$11)*Kalender!D8/SUM(Kalender!$D$5:$D$370),0)+IFERROR(SUMIF(Nutzungsprofile!$B$6:$B$11,"Individuell",Nutzungsprofile!$G$6:$G$11)*Kalender!E8/SUM(Kalender!$E$5:$E$370),0)),0) -> 2.04 | E8: =IF(Prüfungen!$B$4=0,(IFERROR(SUMIF(Nutzungsprofile!$B$17:$B$22,"Schulbetrieb",Nutzungsprofile!$G$17:$G$22)*Kalender!C8/SUM(Kalender!$C$5:$C$370),0)+IFERROR(SUMIF(Nutzungsprofile!$B$17:$B$22,"Halle",Nutzungsprofile!$G$17:$G$22)*Kalender!D8/SUM(Kalender!$D$5:$D$370),0)+IFERROR(SUMIF(Nutzungsprofile!$B$17:$B$22,"Individuell",Nutzungsprofile!$G$17:$G$22)*Kalender!E8/SUM(Kalender!$E$5:$E$370),0)),0) -> 0.89 | F8: =IFERROR(MIN(D8,Eingaben!$B$17)*Eingaben!$B$16,0) -> 1.938 | G8: =IFERROR(F8*Eingaben!$B$15,0) -> 1.7442 | H8: =IFERROR(Q8*(1-Eingaben!$B$20),0) -> 1.5613632 | I8: =MIN(H8,E8) -> 0.89 | J8: =IFERROR(MIN(G8*Eingaben!$B$19,MAX(0,E8-I8)),0) -> 0 | K8: =IFERROR(MIN(Eingaben!$B$18,MAX(0,G8-J8)),0) -> 1.7442 | L8: =I8+J8 -> 0.89 | M8: =MAX(0,E8-L8) -> 0 | N8: =MAX(0,G8-J8-K8) -> 0 | O8: =Q8-I8 -> 0.7032278 | P8: =G8+Q8-L8-N8-O8-K8 -> 0 | Q8: =IF(A8="",0,K7) -> 1.5932278
A9: =Kalender!A9 -> 46027 | B9: =Kalender!C9 -> 1 | C9: =Kalender!D9 -> 1 | D9: =IF(Prüfungen!$B$4=0,(IFERROR(SUMIF(Nutzungsprofile!$B$6:$B$11,"Schulbetrieb",Nutzungsprofile!$G$6:$G$11)*Kalender!C9/SUM(Kalender!$C$5:$C$370),0)+IFERROR(SUMIF(Nutzungsprofile!$B$6:$B$11,"Halle",Nutzungsprofile!$G$6:$G$11)*Kalender!D9/SUM(Kalender!$D$5:$D$370),0)+IFERROR(SUMIF(Nutzungsprofile!$B$6:$B$11,"Individuell",Nutzungsprofile!$G$6:$G$11)*Kalender!E9/SUM(Kalender!$E$5:$E$370),0)),0) -> 2.94 | E9: =IF(Prüfungen!$B$4=0,(IFERROR(SUMIF(Nutzungsprofile!$B$17:$B$22,"Schulbetrieb",Nutzungsprofile!$G$17:$G$22)*Kalender!C9/SUM(Kalender!$C$5:$C$370),0)+IFERROR(SUMIF(Nutzungsprofile!$B$17:$B$22,"Halle",Nutzungsprofile!$G$17:$G$22)*Kalender!D9/SUM(Kalender!$D$5:$D$370),0)+IFERROR(SUMIF(Nutzungsprofile!$B$17:$B$22,"Individuell",Nutzungsprofile!$G$17:$G$22)*Kalender!E9/SUM(Kalender!$E$5:$E$370),0)),0) -> 4.94 | F9: =IFERROR(MIN(D9,Eingaben!$B$17)*Eingaben!$B$16,0) -> 2.793 | G9: =IFERROR(F9*Eingaben!$B$15,0) -> 2.5137 | H9: =IFERROR(Q9*(1-Eingaben!$B$20),0) -> 1.709316 | I9: =MIN(H9,E9) -> 1.709316 | J9: =IFERROR(MIN(G9*Eingaben!$B$19,MAX(0,E9-I9)),0) -> 1.75959 | K9: =IFERROR(MIN(Eingaben!$B$18,MAX(0,G9-J9)),0) -> 0.75411 | L9: =I9+J9 -> 3.468906 | M9: =MAX(0,E9-L9) -> 1.471094 | N9: =MAX(0,G9-J9-K9) -> 0 | O9: =Q9-I9 -> 0.034884 | P9: =G9+Q9-L9-N9-O9-K9 -> 0 | Q9: =IF(A9="",0,K8) -> 1.7442
A10: =Kalender!A10 -> 46028 | B10: =Kalender!C10 -> 1 | C10: =Kalender!D10 -> 1 | D10: =IF(Prüfungen!$B$4=0,(IFERROR(SUMIF(Nutzungsprofile!$B$6:$B$11,"Schulbetrieb",Nutzungsprofile!$G$6:$G$11)*Kalender!C10/SUM(Kalender!$C$5:$C$370),0)+IFERROR(SUMIF(Nutzungsprofile!$B$6:$B$11,"Halle",Nutzungsprofile!$G$6:$G$11)*Kalender!D10/SUM(Kalender!$D$5:$D$370),0)+IFERROR(SUMIF(Nutzungsprofile!$B$6:$B$11,"Individuell",Nutzungsprofile!$G$6:$G$11)*Kalender!E10/SUM(Kalender!$E$5:$E$370),0)),0) -> 2.94 | E10: =IF(Prüfungen!$B$4=0,(IFERROR(SUMIF(Nutzungsprofile!$B$17:$B$22,"Schulbetrieb",Nutzungsprofile!$G$17:$G$22)*Kalender!C10/SUM(Kalender!$C$5:$C$370),0)+IFERROR(SUMIF(Nutzungsprofile!$B$17:$B$22,"Halle",Nutzungsprofile!$G$17:$G$22)*Kalender!D10/SUM(Kalender!$D$5:$D$370),0)+IFERROR(SUMIF(Nutzungsprofile!$B$17:$B$22,"Individuell",Nutzungsprofile!$G$17:$G$22)*Kalender!E10/SUM(Kalender!$E$5:$E$370),0)),0) -> 4.94 | F10: =IFERROR(MIN(D10,Eingaben!$B$17)*Eingaben!$B$16,0) -> 2.793 | G10: =IFERROR(F10*Eingaben!$B$15,0) -> 2.5137 | H10: =IFERROR(Q10*(1-Eingaben!$B$20),0) -> 0.7390278 | I10: =MIN(H10,E10) -> 0.7390278 | J10: =IFERROR(MIN(G10*Eingaben!$B$19,MAX(0,E10-I10)),0) -> 1.75959 | K10: =IFERROR(MIN(Eingaben!$B$18,MAX(0,G10-J10)),0) -> 0.75411 | L10: =I10+J10 -> 2.4986178 | M10: =MAX(0,E10-L10) -> 2.4413822 | N10: =MAX(0,G10-J10-K10) -> 0 | O10: =Q10-I10 -> 0.0150822 | P10: =G10+Q10-L10-N10-O10-K10 -> 0 | Q10: =IF(A10="",0,K9) -> 0.75411
A11: =Kalender!A11 -> 46029 | B11: =Kalender!C11 -> 1 | C11: =Kalender!D11 -> 1 | D11: =IF(Prüfungen!$B$4=0,(IFERROR(SUMIF(Nutzungsprofile!$B$6:$B$11,"Schulbetrieb",Nutzungsprofile!$G$6:$G$11)*Kalender!C11/SUM(Kalender!$C$5:$C$370),0)+IFERROR(SUMIF(Nutzungsprofile!$B$6:$B$11,"Halle",Nutzungsprofile!$G$6:$G$11)*Kalender!D11/SUM(Kalender!$D$5:$D$370),0)+IFERROR(SUMIF(Nutzungsprofile!$B$6:$B$11,"Individuell",Nutzungsprofile!$G$6:$G$11)*Kalender!E11/SUM(Kalender!$E$5:$E$370),0)),0) -> 2.94 | E11: =IF(Prüfungen!$B$4=0,(IFERROR(SUMIF(Nutzungsprofile!$B$17:$B$22,"Schulbetrieb",Nutzungsprofile!$G$17:$G$22)*Kalender!C11/SUM(Kalender!$C$5:$C$370),0)+IFERROR(SUMIF(Nutzungsprofile!$B$17:$B$22,"Halle",Nutzungsprofile!$G$17:$G$22)*Kalender!D11/SUM(Kalender!$D$5:$D$370),0)+IFERROR(SUMIF(Nutzungsprofile!$B$17:$B$22,"Individuell",Nutzungsprofile!$G$17:$G$22)*Kalender!E11/SUM(Kalender!$E$5:$E$370),0)),0) -> 4.94 | F11: =IFERROR(MIN(D11,Eingaben!$B$17)*Eingaben!$B$16,0) -> 2.793 | G11: =IFERROR(F11*Eingaben!$B$15,0) -> 2.5137 | H11: =IFERROR(Q11*(1-Eingaben!$B$20),0) -> 0.7390278 | I11: =MIN(H11,E11) -> 0.7390278 | J11: =IFERROR(MIN(G11*Eingaben!$B$19,MAX(0,E11-I11)),0) -> 1.75959 | K11: =IFERROR(MIN(Eingaben!$B$18,MAX(0,G11-J11)),0) -> 0.75411 | L11: =I11+J11 -> 2.4986178 | M11: =MAX(0,E11-L11) -> 2.4413822 | N11: =MAX(0,G11-J11-K11) -> 0 | O11: =Q11-I11 -> 0.0150822 | P11: =G11+Q11-L11-N11-O11-K11 -> 0 | Q11: =IF(A11="",0,K10) -> 0.75411
A12: =Kalender!A12 -> 46030 | B12: =Kalender!C12 -> 1 | C12: =Kalender!D12 -> 1 | D12: =IF(Prüfungen!$B$4=0,(IFERROR(SUMIF(Nutzungsprofile!$B$6:$B$11,"Schulbetrieb",Nutzungsprofile!$G$6:$G$11)*Kalender!C12/SUM(Kalender!$C$5:$C$370),0)+IFERROR(SUMIF(Nutzungsprofile!$B$6:$B$11,"Halle",Nutzungsprofile!$G$6:$G$11)*Kalender!D12/SUM(Kalender!$D$5:$D$370),0)+IFERROR(SUMIF(Nutzungsprofile!$B$6:$B$11,"Individuell",Nutzungsprofile!$G$6:$G$11)*Kalender!E12/SUM(Kalender!$E$5:$E$370),0)),0) -> 2.94 | E12: =IF(Prüfungen!$B$4=0,(IFERROR(SUMIF(Nutzungsprofile!$B$17:$B$22,"Schulbetrieb",Nutzungsprofile!$G$17:$G$22)*Kalender!C12/SUM(Kalender!$C$5:$C$370),0)+IFERROR(SUMIF(Nutzungsprofile!$B$17:$B$22,"Halle",Nutzungsprofile!$G$17:$G$22)*Kalender!D12/SUM(Kalender!$D$5:$D$370),0)+IFERROR(SUMIF(Nutzungsprofile!$B$17:$B$22,"Individuell",Nutzungsprofile!$G$17:$G$22)*Kalender!E12/SUM(Kalender!$E$5:$E$370),0)),0) -> 4.94 | F12: =IFERROR(MIN(D12,Eingaben!$B$17)*Eingaben!$B$16,0) -> 2.793 | G12: =IFERROR(F12*Eingaben!$B$15,0) -> 2.5137 | H12: =IFERROR(Q12*(1-Eingaben!$B$20),0) -> 0.7390278 | I12: =MIN(H12,E12) -> 0.7390278 | J12: =IFERROR(MIN(G12*Eingaben!$B$19,MAX(0,E12-I12)),0) -> 1.75959 | K12: =IFERROR(MIN(Eingaben!$B$18,MAX(0,G12-J12)),0) -> 0.75411 | L12: =I12+J12 -> 2.4986178 | M12: =MAX(0,E12-L12) -> 2.4413822 | N12: =MAX(0,G12-J12-K12) -> 0 | O12: =Q12-I12 -> 0.0150822 | P12: =G12+Q12-L12-N12-O12-K12 -> 0 | Q12: =IF(A12="",0,K11) -> 0.75411
A13: =Kalender!A13 -> 46031 | B13: =Kalender!C13 -> 1 | C13: =Kalender!D13 -> 1 | D13: =IF(Prüfungen!$B$4=0,(IFERROR(SUMIF(Nutzungsprofile!$B$6:$B$11,"Schulbetrieb",Nutzungsprofile!$G$6:$G$11)*Kalender!C13/SUM(Kalender!$C$5:$C$370),0)+IFERROR(SUMIF(Nutzungsprofile!$B$6:$B$11,"Halle",Nutzungsprofile!$G$6:$G$11)*Kalender!D13/SUM(Kalender!$D$5:$D$370),0)+IFERROR(SUMIF(Nutzungsprofile!$B$6:$B$11,"Individuell",Nutzungsprofile!$G$6:$G$11)*Kalender!E13/SUM(Kalender!$E$5:$E$370),0)),0) -> 2.94 | E13: =IF(Prüfungen!$B$4=0,(IFERROR(SUMIF(Nutzungsprofile!$B$17:$B$22,"Schulbetrieb",Nutzungsprofile!$G$17:$G$22)*Kalender!C13/SUM(Kalender!$C$5:$C$370),0)+IFERROR(SUMIF(Nutzungsprofile!$B$17:$B$22,"Halle",Nutzungsprofile!$G$17:$G$22)*Kalender!D13/SUM(Kalender!$D$5:$D$370),0)+IFERROR(SUMIF(Nutzungsprofile!$B$17:$B$22,"Individuell",Nutzungsprofile!$G$17:$G$22)*Kalender!E13/SUM(Kalender!$E$5:$E$370),0)),0) -> 4.94 | F13: =IFERROR(MIN(D13,Eingaben!$B$17)*Eingaben!$B$16,0) -> 2.793 | G13: =IFERROR(F13*Eingaben!$B$15,0) -> 2.5137 | H13: =IFERROR(Q13*(1-Eingaben!$B$20),0) -> 0.7390278 | I13: =MIN(H13,E13) -> 0.7390278 | J13: =IFERROR(MIN(G13*Eingaben!$B$19,MAX(0,E13-I13)),0) -> 1.75959 | K13: =IFERROR(MIN(Eingaben!$B$18,MAX(0,G13-J13)),0) -> 0.75411 | L13: =I13+J13 -> 2.4986178 | M13: =MAX(0,E13-L13) -> 2.4413822 | N13: =MAX(0,G13-J13-K13) -> 0 | O13: =Q13-I13 -> 0.0150822 | P13: =G13+Q13-L13-N13-O13-K13 -> 0 | Q13: =IF(A13="",0,K12) -> 0.75411
A14: =Kalender!A14 -> 46032 | B14: =Kalender!C14 -> 0 | C14: =Kalender!D14 -> 1 | D14: =IF(Prüfungen!$B$4=0,(IFERROR(SUMIF(Nutzungsprofile!$B$6:$B$11,"Schulbetrieb",Nutzungsprofile!$G$6:$G$11)*Kalender!C14/SUM(Kalender!$C$5:$C$370),0)+IFERROR(SUMIF(Nutzungsprofile!$B$6:$B$11,"Halle",Nutzungsprofile!$G$6:$G$11)*Kalender!D14/SUM(Kalender!$D$5:$D$370),0)+IFERROR(SUMIF(Nutzungsprofile!$B$6:$B$11,"Individuell",Nutzungsprofile!$G$6:$G$11)*Kalender!E14/SUM(Kalender!$E$5:$E$370),0)),0) -> 2.04 | E14: =IF(Prüfungen!$B$4=0,(IFERROR(SUMIF(Nutzungsprofile!$B$17:$B$22,"Schulbetrieb",Nutzungsprofile!$G$17:$G$22)*Kalender!C14/SUM(Kalender!$C$5:$C$370),0)+IFERROR(SUMIF(Nutzungsprofile!$B$17:$B$22,"Halle",Nutzungsprofile!$G$17:$G$22)*Kalender!D14/SUM(Kalender!$D$5:$D$370),0)+IFERROR(SUMIF(Nutzungsprofile!$B$17:$B$22,"Individuell",Nutzungsprofile!$G$17:$G$22)*Kalender!E14/SUM(Kalender!$E$5:$E$370),0)),0) -> 0.89 | F14: =IFERROR(MIN(D14,Eingaben!$B$17)*Eingaben!$B$16,0) -> 1.938 | G14: =IFERROR(F14*Eingaben!$B$15,0) -> 1.7442 | H14: =IFERROR(Q14*(1-Eingaben!$B$20),0) -> 0.7390278 | I14: =MIN(H14,E14) -> 0.7390278 | J14: =IFERROR(MIN(G14*Eingaben!$B$19,MAX(0,E14-I14)),0) -> 0.1509722 | K14: =IFERROR(MIN(Eingaben!$B$18,MAX(0,G14-J14)),0) -> 1.5932278 | L14: =I14+J14 -> 0.89 | M14: =MAX(0,E14-L14) -> 0 | N14: =MAX(0,G14-J14-K14) -> 0 | O14: =Q14-I14 -> 0.0150822 | P14: =G14+Q14-L14-N14-O14-K14 -> 0 | Q14: =IF(A14="",0,K13) -> 0.75411
A15: =Kalender!A15 -> 46033 | B15: =Kalender!C15 -> 0 | C15: =Kalender!D15 -> 1 | D15: =IF(Prüfungen!$B$4=0,(IFERROR(SUMIF(Nutzungsprofile!$B$6:$B$11,"Schulbetrieb",Nutzungsprofile!$G$6:$G$11)*Kalender!C15/SUM(Kalender!$C$5:$C$370),0)+IFERROR(SUMIF(Nutzungsprofile!$B$6:$B$11,"Halle",Nutzungsprofile!$G$6:$G$11)*Kalender!D15/SUM(Kalender!$D$5:$D$370),0)+IFERROR(SUMIF(Nutzungsprofile!$B$6:$B$11,"Individuell",Nutzungsprofile!$G$6:$G$11)*Kalender!E15/SUM(Kalender!$E$5:$E$370),0)),0) -> 2.04 | E15: =IF(Prüfungen!$B$4=0,(IFERROR(SUMIF(Nutzungsprofile!$B$17:$B$22,"Schulbetrieb",Nutzungsprofile!$G$17:$G$22)*Kalender!C15/SUM(Kalender!$C$5:$C$370),0)+IFERROR(SUMIF(Nutzungsprofile!$B$17:$B$22,"Halle",Nutzungsprofile!$G$17:$G$22)*Kalender!D15/SUM(Kalender!$D$5:$D$370),0)+IFERROR(SUMIF(Nutzungsprofile!$B$17:$B$22,"Individuell",Nutzungsprofile!$G$17:$G$22)*Kalender!E15/SUM(Kalender!$E$5:$E$370),0)),0) -> 0.89 | F15: =IFERROR(MIN(D15,Eingaben!$B$17)*Eingaben!$B$16,0) -> 1.938 | G15: =IFERROR(F15*Eingaben!$B$15,0) -> 1.7442 | H15: =IFERROR(Q15*(1-Eingaben!$B$20),0) -> 1.5613632 | I15: =MIN(H15,E15) -> 0.89 | J15: =IFERROR(MIN(G15*Eingaben!$B$19,MAX(0,E15-I15)),0) -> 0 | K15: =IFERROR(MIN(Eingaben!$B$18,MAX(0,G15-J15)),0) -> 1.7442 | L15: =I15+J15 -> 0.89 | M15: =MAX(0,E15-L15) -> 0 | N15: =MAX(0,G15-J15-K15) -> 0 | O15: =Q15-I15 -> 0.7032278 | P15: =G15+Q15-L15-N15-O15-K15 -> 0 | Q15: =IF(A15="",0,K14) -> 1.5932278
A16: =Kalender!A16 -> 46034 | B16: =Kalender!C16 -> 1 | C16: =Kalender!D16 -> 1 | D16: =IF(Prüfungen!$B$4=0,(IFERROR(SUMIF(Nutzungsprofile!$B$6:$B$11,"Schulbetrieb",Nutzungsprofile!$G$6:$G$11)*Kalender!C16/SUM(Kalender!$C$5:$C$370),0)+IFERROR(SUMIF(Nutzungsprofile!$B$6:$B$11,"Halle",Nutzungsprofile!$G$6:$G$11)*Kalender!D16/SUM(Kalender!$D$5:$D$370),0)+IFERROR(SUMIF(Nutzungsprofile!$B$6:$B$11,"Individuell",Nutzungsprofile!$G$6:$G$11)*Kalender!E16/SUM(Kalender!$E$5:$E$370),0)),0) -> 2.94 | E16: =IF(Prüfungen!$B$4=0,(IFERROR(SUMIF(Nutzungsprofile!$B$17:$B$22,"Schulbetrieb",Nutzungsprofile!$G$17:$G$22)*Kalender!C16/SUM(Kalender!$C$5:$C$370),0)+IFERROR(SUMIF(Nutzungsprofile!$B$17:$B$22,"Halle",Nutzungsprofile!$G$17:$G$22)*Kalender!D16/SUM(Kalender!$D$5:$D$370),0)+IFERROR(SUMIF(Nutzungsprofile!$B$17:$B$22,"Individuell",Nutzungsprofile!$G$17:$G$22)*Kalender!E16/SUM(Kalender!$E$5:$E$370),0)),0) -> 4.94 | F16: =IFERROR(MIN(D16,Eingaben!$B$17)*Eingaben!$B$16,0) -> 2.793 | G16: =IFERROR(F16*Eingaben!$B$15,0) -> 2.5137 | H16: =IFERROR(Q16*(1-Eingaben!$B$20),0) -> 1.709316 | I16: =MIN(H16,E16) -> 1.709316 | J16: =IFERROR(MIN(G16*Eingaben!$B$19,MAX(0,E16-I16)),0) -> 1.75959 | K16: =IFERROR(MIN(Eingaben!$B$18,MAX(0,G16-J16)),0) -> 0.75411 | L16: =I16+J16 -> 3.468906 | M16: =MAX(0,E16-L16) -> 1.471094 | N16: =MAX(0,G16-J16-K16) -> 0 | O16: =Q16-I16 -> 0.034884 | P16: =G16+Q16-L16-N16-O16-K16 -> 0 | Q16: =IF(A16="",0,K15) -> 1.7442
A17: =Kalender!A17 -> 46035 | B17: =Kalender!C17 -> 1 | C17: =Kalender!D17 -> 1 | D17: =IF(Prüfungen!$B$4=0,(IFERROR(SUMIF(Nutzungsprofile!$B$6:$B$11,"Schulbetrieb",Nutzungsprofile!$G$6:$G$11)*Kalender!C17/SUM(Kalender!$C$5:$C$370),0)+IFERROR(SUMIF(Nutzungsprofile!$B$6:$B$11,"Halle",Nutzungsprofile!$G$6:$G$11)*Kalender!D17/SUM(Kalender!$D$5:$D$370),0)+IFERROR(SUMIF(Nutzungsprofile!$B$6:$B$11,"Individuell",Nutzungsprofile!$G$6:$G$11)*Kalender!E17/SUM(Kalender!$E$5:$E$370),0)),0) -> 2.94 | E17: =IF(Prüfungen!$B$4=0,(IFERROR(SUMIF(Nutzungsprofile!$B$17:$B$22,"Schulbetrieb",Nutzungsprofile!$G$17:$G$22)*Kalender!C17/SUM(Kalender!$C$5:$C$370),0)+IFERROR(SUMIF(Nutzungsprofile!$B$17:$B$22,"Halle",Nutzungsprofile!$G$17:$G$22)*Kalender!D17/SUM(Kalender!$D$5:$D$370),0)+IFERROR(SUMIF(Nutzungsprofile!$B$17:$B$22,"Individuell",Nutzungsprofile!$G$17:$G$22)*Kalender!E17/SUM(Kalender!$E$5:$E$370),0)),0) -> 4.94 | F17: =IFERROR(MIN(D17,Eingaben!$B$17)*Eingaben!$B$16,0) -> 2.793 | G17: =IFERROR(F17*Eingaben!$B$15,0) -> 2.5137 | H17: =IFERROR(Q17*(1-Eingaben!$B$20),0) -> 0.7390278 | I17: =MIN(H17,E17) -> 0.7390278 | J17: =IFERROR(MIN(G17*Eingaben!$B$19,MAX(0,E17-I17)),0) -> 1.75959 | K17: =IFERROR(MIN(Eingaben!$B$18,MAX(0,G17-J17)),0) -> 0.75411 | L17: =I17+J17 -> 2.4986178 | M17: =MAX(0,E17-L17) -> 2.4413822 | N17: =MAX(0,G17-J17-K17) -> 0 | O17: =Q17-I17 -> 0.0150822 | P17: =G17+Q17-L17-N17-O17-K17 -> 0 | Q17: =IF(A17="",0,K16) -> 0.75411
... A370: =Kalender!A370 | B370: =Kalender!C370 -> 0 | C370: =Kalender!D370 -> 0 | D370: =IF(Prüfungen!$B$4=0,(IFERROR(SUMIF(Nutzungsprofile!$B$6:$B$11,"Schulbetrieb",Nutzungsprofile!$G$6:$G$11)*Kalender!C370/SUM(Kalender!$C$5:$C$370),0)+IFERROR(SUMIF(Nutzungsprofile!$B$6:$B$11,"Halle",Nutzungsprofile!$G$6:$G$11)*Kalender!D370/SUM(Kalender!$D$5:$D$370),0)+IFERROR(SUMIF(Nutzungsprofile!$B$6:$B$11,"Individuell",Nutzungsprofile!$G$6:$G$11)*Kalender!E370/SUM(Kalender!$E$5:$E$370),0)),0) -> 0 | E370: =IF(Prüfungen!$B$4=0,(IFERROR(SUMIF(Nutzungsprofile!$B$17:$B$22,"Schulbetrieb",Nutzungsprofile!$G$17:$G$22)*Kalender!C370/SUM(Kalender!$C$5:$C$370),0)+IFERROR(SUMIF(Nutzungsprofile!$B$17:$B$22,"Halle",Nutzungsprofile!$G$17:$G$22)*Kalender!D370/SUM(Kalender!$D$5:$D$370),0)+IFERROR(SUMIF(Nutzungsprofile!$B$17:$B$22,"Individuell",Nutzungsprofile!$G$17:$G$22)*Kalender!E370/SUM(Kalender!$E$5:$E$370),0)),0) -> 0 | F370: =IFERROR(MIN(D370,Eingaben!$B$17)*Eingaben!$B$16,0) -> 0 | G370: =IFERROR(F370*Eingaben!$B$15,0) -> 0 | H370: =IFERROR(Q370*(1-Eingaben!$B$20),0) -> 0 | I370: =MIN(H370,E370) -> 0 | J370: =IFERROR(MIN(G370*Eingaben!$B$19,MAX(0,E370-I370)),0) -> 0 | K370: =IFERROR(MIN(Eingaben!$B$18,MAX(0,G370-J370)),0) -> 0 | L370: =I370+J370 -> 0 | M370: =MAX(0,E370-L370) -> 0 | N370: =MAX(0,G370-J370-K370) -> 0 | O370: =Q370-I370 -> 0 | P370: =G370+Q370-L370-N370-O370-K370 -> 0 | Q370: =IF(A370="",0,K369) -> 0

Sheet Zahlungen
A1: Zahlungsreihe & Kapitalwert
A2: Dashboard | B2: Eingaben | C2: Profile | D2: Kalender | E2: Methodik
A3: Nominale Zahlungen am Jahresende; Jahr 0 = Nettoinvestition. Jahreswasserprofil wiederholt sich ohne Wachstum der Nutzerzahl.
A6: Jahr | B6: Einsparmenge m³ | C6: Vermiedene Kosten € | D6: Betriebskosten € | E6: Ersatzinvestition € | F6: Restwert € | G6: Cashflow € | H6: Diskontfaktor | I6: Barwert CF € | J6: Kumuliert diskontiert € | K6: Barwert Kosten € | L6: Barwert Einsparmenge m³ | M6: Erste Rückgewinnung Jahr
A7: 0 | B7: =0 -> 0 | C7: =0 -> 0 | D7: =0 -> 0 | E7: =Berechnung!$B$14 -> 25000 | F7: =0 -> 0 | G7: =-E7 -> -25000 | H7: =1 -> 1 | I7: =G7 -> -25000 | J7: =I7 -> -25000 | K7: =E7 -> 25000 | L7: =0 -> 0 | M7: =""
A8: 1 | B8: =IF(AND(A8<=Eingaben!$B$11,Prüfungen!$B$4=0),Berechnung!$B$10,0) -> 555.38976 | C8: =IFERROR(IF(AND(A8<=Eingaben!$B$11,Prüfungen!$B$4=0),B8*(Eingaben!$B$36*(1+Eingaben!$B$40)^(A8-1)+Eingaben!$B$37*Eingaben!$B$38*(1+Eingaben!$B$46)^(A8-1)),0),0) -> 1388.4744 | D8: =IFERROR(IF(AND(A8<=Eingaben!$B$11,Prüfungen!$B$4=0),(Eingaben!$B$32+Eingaben!$B$35)*(1+Eingaben!$B$41)^(A8-1)+Berechnung!$B$15*Eingaben!$B$34*(1+Eingaben!$B$42)^(A8-1),0),0) -> 781.527 | E8: =IFERROR(IF(AND(AND(A8<=Eingaben!$B$11,Prüfungen!$B$4=0),A8=Eingaben!$B$43),Eingaben!$B$44*(1+Eingaben!$B$41)^(A8-1),0),0) -> 0 | F8: =IFERROR(IF(AND(AND(A8<=Eingaben!$B$11,Prüfungen!$B$4=0),A8=Eingaben!$B$11),Eingaben!$B$45,0),0) -> 0 | G8: =C8-D8-E8+F8 -> 606.94739 | H8: =IFERROR(IF(AND(A8<=Eingaben!$B$11,Prüfungen!$B$4=0),1/(1+Eingaben!$B$39)^A8,0),0) -> 0.97087379 | I8: =G8*H8 -> 589.26931 | J8: =J7+I8 -> -24410.731 | K8: =(D8+E8-F8)*H8 -> 758.76408 | L8: =B8*H8 -> 539.21336 | M8: =IF(AND(AND(A8<=Eingaben!$B$11,Prüfungen!$B$4=0),Berechnung!$B$14>0,J7<0,J8>=0,I8>0),A8-1-J7/I8,"")
A9: 2 | B9: =IF(AND(A9<=Eingaben!$B$11,Prüfungen!$B$4=0),Berechnung!$B$10,0) -> 555.38976 | C9: =IFERROR(IF(AND(A9<=Eingaben!$B$11,Prüfungen!$B$4=0),B9*(Eingaben!$B$36*(1+Eingaben!$B$40)^(A9-1)+Eingaben!$B$37*Eingaben!$B$38*(1+Eingaben!$B$46)^(A9-1)),0),0) -> 1416.2439 | D9: =IFERROR(IF(AND(A9<=Eingaben!$B$11,Prüfungen!$B$4=0),(Eingaben!$B$32+Eingaben!$B$35)*(1+Eingaben!$B$41)^(A9-1)+Berechnung!$B$15*Eingaben!$B$34*(1+Eingaben!$B$42)^(A9-1),0),0) -> 797.15754 | E9: =IFERROR(IF(AND(AND(A9<=Eingaben!$B$11,Prüfungen!$B$4=0),A9=Eingaben!$B$43),Eingaben!$B$44*(1+Eingaben!$B$41)^(A9-1),0),0) -> 0 | F9: =IFERROR(IF(AND(AND(A9<=Eingaben!$B$11,Prüfungen!$B$4=0),A9=Eingaben!$B$11),Eingaben!$B$45,0),0) -> 0 | G9: =C9-D9-E9+F9 -> 619.08634 | H9: =IFERROR(IF(AND(A9<=Eingaben!$B$11,Prüfungen!$B$4=0),1/(1+Eingaben!$B$39)^A9,0),0) -> 0.94259591 | I9: =G9*H9 -> 583.54825 | J9: =J8+I9 -> -23827.182 | K9: =(D9+E9-F9)*H9 -> 751.39744 | L9: =B9*H9 -> 523.50811 | M9: =IF(AND(AND(A9<=Eingaben!$B$11,Prüfungen!$B$4=0),Berechnung!$B$14>0,J8<0,J9>=0,I9>0),A9-1-J8/I9,"")
A10: 3 | B10: =IF(AND(A10<=Eingaben!$B$11,Prüfungen!$B$4=0),Berechnung!$B$10,0) -> 555.38976 | C10: =IFERROR(IF(AND(A10<=Eingaben!$B$11,Prüfungen!$B$4=0),B10*(Eingaben!$B$36*(1+Eingaben!$B$40)^(A10-1)+Eingaben!$B$37*Eingaben!$B$38*(1+Eingaben!$B$46)^(A10-1)),0),0) -> 1444.5688 | D10: =IFERROR(IF(AND(A10<=Eingaben!$B$11,Prüfungen!$B$4=0),(Eingaben!$B$32+Eingaben!$B$35)*(1+Eingaben!$B$41)^(A10-1)+Berechnung!$B$15*Eingaben!$B$34*(1+Eingaben!$B$42)^(A10-1),0),0) -> 813.10069 | E10: =IFERROR(IF(AND(AND(A10<=Eingaben!$B$11,Prüfungen!$B$4=0),A10=Eingaben!$B$43),Eingaben!$B$44*(1+Eingaben!$B$41)^(A10-1),0),0) -> 0 | F10: =IFERROR(IF(AND(AND(A10<=Eingaben!$B$11,Prüfungen!$B$4=0),A10=Eingaben!$B$11),Eingaben!$B$45,0),0) -> 0 | G10: =C10-D10-E10+F10 -> 631.46807 | H10: =IFERROR(IF(AND(A10<=Eingaben!$B$11,Prüfungen!$B$4=0),1/(1+Eingaben!$B$39)^A10,0),0) -> 0.91514166 | I10: =G10*H10 -> 577.88274 | J10: =J9+I10 -> -23249.3 | K10: =(D10+E10-F10)*H10 -> 744.10232 | L10: =B10*H10 -> 508.2603 | M10: =IF(AND(AND(A10<=Eingaben!$B$11,Prüfungen!$B$4=0),Berechnung!$B$14>0,J9<0,J10>=0,I10>0),A10-1-J9/I10,"")
A11: 4 | B11: =IF(AND(A11<=Eingaben!$B$11,Prüfungen!$B$4=0),Berechnung!$B$10,0) -> 555.38976 | C11: =IFERROR(IF(AND(A11<=Eingaben!$B$11,Prüfungen!$B$4=0),B11*(Eingaben!$B$36*(1+Eingaben!$B$40)^(A11-1)+Eingaben!$B$37*Eingaben!$B$38*(1+Eingaben!$B$46)^(A11-1)),0),0) -> 1473.4601 | D11: =IFERROR(IF(AND(A11<=Eingaben!$B$11,Prüfungen!$B$4=0),(Eingaben!$B$32+Eingaben!$B$35)*(1+Eingaben!$B$41)^(A11-1)+Berechnung!$B$15*Eingaben!$B$34*(1+Eingaben!$B$42)^(A11-1),0),0) -> 829.3627 | E11: =IFERROR(IF(AND(AND(A11<=Eingaben!$B$11,Prüfungen!$B$4=0),A11=Eingaben!$B$43),Eingaben!$B$44*(1+Eingaben!$B$41)^(A11-1),0),0) -> 0 | F11: =IFERROR(IF(AND(AND(A11<=Eingaben!$B$11,Prüfungen!$B$4=0),A11=Eingaben!$B$11),Eingaben!$B$45,0),0) -> 0 | G11: =C11-D11-E11+F11 -> 644.09743 | H11: =IFERROR(IF(AND(A11<=Eingaben!$B$11,Prüfungen!$B$4=0),1/(1+Eingaben!$B$39)^A11,0),0) -> 0.88848705 | I11: =G11*H11 -> 572.27222 | J11: =J10+I11 -> -22677.027 | K11: =(D11+E11-F11)*H11 -> 736.87802 | L11: =B11*H11 -> 493.45661 | M11: =IF(AND(AND(A11<=Eingaben!$B$11,Prüfungen!$B$4=0),Berechnung!$B$14>0,J10<0,J11>=0,I11>0),A11-1-J10/I11,"")
A12: 5 | B12: =IF(AND(A12<=Eingaben!$B$11,Prüfungen!$B$4=0),Berechnung!$B$10,0) -> 555.38976 | C12: =IFERROR(IF(AND(A12<=Eingaben!$B$11,Prüfungen!$B$4=0),B12*(Eingaben!$B$36*(1+Eingaben!$B$40)^(A12-1)+Eingaben!$B$37*Eingaben!$B$38*(1+Eingaben!$B$46)^(A12-1)),0),0) -> 1502.9293 | D12: =IFERROR(IF(AND(A12<=Eingaben!$B$11,Prüfungen!$B$4=0),(Eingaben!$B$32+Eingaben!$B$35)*(1+Eingaben!$B$41)^(A12-1)+Berechnung!$B$15*Eingaben!$B$34*(1+Eingaben!$B$42)^(A12-1),0),0) -> 845.94996 | E12: =IFERROR(IF(AND(AND(A12<=Eingaben!$B$11,Prüfungen!$B$4=0),A12=Eingaben!$B$43),Eingaben!$B$44*(1+Eingaben!$B$41)^(A12-1),0),0) -> 0 | F12: =IFERROR(IF(AND(AND(A12<=Eingaben!$B$11,Prüfungen!$B$4=0),A12=Eingaben!$B$11),Eingaben!$B$45,0),0) -> 0 | G12: =C12-D12-E12+F12 -> 656.97938 | H12: =IFERROR(IF(AND(A12<=Eingaben!$B$11,Prüfungen!$B$4=0),1/(1+Eingaben!$B$39)^A12,0),0) -> 0.86260878 | I12: =G12*H12 -> 566.71618 | J12: =J11+I12 -> -22110.311 | K12: =(D12+E12-F12)*H12 -> 729.72387 | L12: =B12*H12 -> 479.08408 | M12: =IF(AND(AND(A12<=Eingaben!$B$11,Prüfungen!$B$4=0),Berechnung!$B$14>0,J11<0,J12>=0,I12>0),A12-1-J11/I12,"")
A13: 6 | B13: =IF(AND(A13<=Eingaben!$B$11,Prüfungen!$B$4=0),Berechnung!$B$10,0) -> 555.38976 | C13: =IFERROR(IF(AND(A13<=Eingaben!$B$11,Prüfungen!$B$4=0),B13*(Eingaben!$B$36*(1+Eingaben!$B$40)^(A13-1)+Eingaben!$B$37*Eingaben!$B$38*(1+Eingaben!$B$46)^(A13-1)),0),0) -> 1532.9879 | D13: =IFERROR(IF(AND(A13<=Eingaben!$B$11,Prüfungen!$B$4=0),(Eingaben!$B$32+Eingaben!$B$35)*(1+Eingaben!$B$41)^(A13-1)+Berechnung!$B$15*Eingaben!$B$34*(1+Eingaben!$B$42)^(A13-1),0),0) -> 862.86896 | E13: =IFERROR(IF(AND(AND(A13<=Eingaben!$B$11,Prüfungen!$B$4=0),A13=Eingaben!$B$43),Eingaben!$B$44*(1+Eingaben!$B$41)^(A13-1),0),0) -> 0 | F13: =IFERROR(IF(AND(AND(A13<=Eingaben!$B$11,Prüfungen!$B$4=0),A13=Eingaben!$B$11),Eingaben!$B$45,0),0) -> 0 | G13: =C13-D13-E13+F13 -> 670.11897 | H13: =IFERROR(IF(AND(A13<=Eingaben!$B$11,Prüfungen!$B$4=0),1/(1+Eingaben!$B$39)^A13,0),0) -> 0.83748426 | I13: =G13*H13 -> 561.21408 | J13: =J12+I13 -> -21549.097 | K13: =(D13+E13-F13)*H13 -> 722.63917 | L13: =B13*H13 -> 465.13018 | M13: =IF(AND(AND(A13<=Eingaben!$B$11,Prüfungen!$B$4=0),Berechnung!$B$14>0,J12<0,J13>=0,I13>0),A13-1-J12/I13,"")
A14: 7 | B14: =IF(AND(A14<=Eingaben!$B$11,Prüfungen!$B$4=0),Berechnung!$B$10,0) -> 555.38976 | C14: =IFERROR(IF(AND(A14<=Eingaben!$B$11,Prüfungen!$B$4=0),B14*(Eingaben!$B$36*(1+Eingaben!$B$40)^(A14-1)+Eingaben!$B$37*Eingaben!$B$38*(1+Eingaben!$B$46)^(A14-1)),0),0) -> 1563.6477 | D14: =IFERROR(IF(AND(A14<=Eingaben!$B$11,Prüfungen!$B$4=0),(Eingaben!$B$32+Eingaben!$B$35)*(1+Eingaben!$B$41)^(A14-1)+Berechnung!$B$15*Eingaben!$B$34*(1+Eingaben!$B$42)^(A14-1),0),0) -> 880.12634 | E14: =IFERROR(IF(AND(AND(A14<=Eingaben!$B$11,Prüfungen!$B$4=0),A14=Eingaben!$B$43),Eingaben!$B$44*(1+Eingaben!$B$41)^(A14-1),0),0) -> 0 | F14: =IFERROR(IF(AND(AND(A14<=Eingaben!$B$11,Prüfungen!$B$4=0),A14=Eingaben!$B$11),Eingaben!$B$45,0),0) -> 0 | G14: =C14-D14-E14+F14 -> 683.52134 | H14: =IFERROR(IF(AND(A14<=Eingaben!$B$11,Prüfungen!$B$4=0),1/(1+Eingaben!$B$39)^A14,0),0) -> 0.81309151 | I14: =G14*H14 -> 555.7654 | J14: =J13+I14 -> -20993.332 | K14: =(D14+E14-F14)*H14 -> 715.62325 | L14: =B14*H14 -> 451.5827 | M14: =IF(AND(AND(A14<=Eingaben!$B$11,Prüfungen!$B$4=0),Berechnung!$B$14>0,J13<0,J14>=0,I14>0),A14-1-J13/I14,"")
A15: 8 | B15: =IF(AND(A15<=Eingaben!$B$11,Prüfungen!$B$4=0),Berechnung!$B$10,0) -> 555.38976 | C15: =IFERROR(IF(AND(A15<=Eingaben!$B$11,Prüfungen!$B$4=0),B15*(Eingaben!$B$36*(1+Eingaben!$B$40)^(A15-1)+Eingaben!$B$37*Eingaben!$B$38*(1+Eingaben!$B$46)^(A15-1)),0),0) -> 1594.9206 | D15: =IFERROR(IF(AND(A15<=Eingaben!$B$11,Prüfungen!$B$4=0),(Eingaben!$B$32+Eingaben!$B$35)*(1+Eingaben!$B$41)^(A15-1)+Berechnung!$B$15*Eingaben!$B$34*(1+Eingaben!$B$42)^(A15-1),0),0) -> 897.72886 | E15: =IFERROR(IF(AND(AND(A15<=Eingaben!$B$11,Prüfungen!$B$4=0),A15=Eingaben!$B$43),Eingaben!$B$44*(1+Eingaben!$B$41)^(A15-1),0),0) -> 0 | F15: =IFERROR(IF(AND(AND(A15<=Eingaben!$B$11,Prüfungen!$B$4=0),A15=Eingaben!$B$11),Eingaben!$B$45,0),0) -> 0 | G15: =C15-D15-E15+F15 -> 697.19177 | H15: =IFERROR(IF(AND(A15<=Eingaben!$B$11,Prüfungen!$B$4=0),1/(1+Eingaben!$B$39)^A15,0),0) -> 0.78940923 | I15: =G15*H15 -> 550.36962 | J15: =J14+I15 -> -20442.962 | K15: =(D15+E15-F15)*H15 -> 708.67545 | L15: =B15*H15 -> 438.4298 | M15: =IF(AND(AND(A15<=Eingaben!$B$11,Prüfungen!$B$4=0),Berechnung!$B$14>0,J14<0,J15>=0,I15>0),A15-1-J14/I15,"")
A16: 9 | B16: =IF(AND(A16<=Eingaben!$B$11,Prüfungen!$B$4=0),Berechnung!$B$10,0) -> 555.38976 | C16: =IFERROR(IF(AND(A16<=Eingaben!$B$11,Prüfungen!$B$4=0),B16*(Eingaben!$B$36*(1+Eingaben!$B$40)^(A16-1)+Eingaben!$B$37*Eingaben!$B$38*(1+Eingaben!$B$46)^(A16-1)),0),0) -> 1626.819 | D16: =IFERROR(IF(AND(A16<=Eingaben!$B$11,Prüfungen!$B$4=0),(Eingaben!$B$32+Eingaben!$B$35)*(1+Eingaben!$B$41)^(A16-1)+Berechnung!$B$15*Eingaben!$B$34*(1+Eingaben!$B$42)^(A16-1),0),0) -> 915.68344 | E16: =IFERROR(IF(AND(AND(A16<=Eingaben!$B$11,Prüfungen!$B$4=0),A16=Eingaben!$B$43),Eingaben!$B$44*(1+Eingaben!$B$41)^(A16-1),0),0) -> 0 | F16: =IFERROR(IF(AND(AND(A16<=Eingaben!$B$11,Prüfungen!$B$4=0),A16=Eingaben!$B$11),Eingaben!$B$45,0),0) -> 0 | G16: =C16-D16-E16+F16 -> 711.13561 | H16: =IFERROR(IF(AND(A16<=Eingaben!$B$11,Prüfungen!$B$4=0),1/(1+Eingaben!$B$39)^A16,0),0) -> 0.76641673 | I16: =G16*H16 -> 545.02623 | J16: =J15+I16 -> -19897.936 | K16: =(D16+E16-F16)*H16 -> 701.79511 | L16: =B16*H16 -> 425.66 | M16: =IF(AND(AND(A16<=Eingaben!$B$11,Prüfungen!$B$4=0),Berechnung!$B$14>0,J15<0,J16>=0,I16>0),A16-1-J15/I16,"")
A17: 10 | B17: =IF(AND(A17<=Eingaben!$B$11,Prüfungen!$B$4=0),Berechnung!$B$10,0) -> 555.38976 | C17: =IFERROR(IF(AND(A17<=Eingaben!$B$11,Prüfungen!$B$4=0),B17*(Eingaben!$B$36*(1+Eingaben!$B$40)^(A17-1)+Eingaben!$B$37*Eingaben!$B$38*(1+Eingaben!$B$46)^(A17-1)),0),0) -> 1659.3554 | D17: =IFERROR(IF(AND(A17<=Eingaben!$B$11,Prüfungen!$B$4=0),(Eingaben!$B$32+Eingaben!$B$35)*(1+Eingaben!$B$41)^(A17-1)+Berechnung!$B$15*Eingaben!$B$34*(1+Eingaben!$B$42)^(A17-1),0),0) -> 933.99711 | E17: =IFERROR(IF(AND(AND(A17<=Eingaben!$B$11,Prüfungen!$B$4=0),A17=Eingaben!$B$43),Eingaben!$B$44*(1+Eingaben!$B$41)^(A17-1),0),0) -> 4780.3703 | F17: =IFERROR(IF(AND(AND(A17<=Eingaben!$B$11,Prüfungen!$B$4=0),A17=Eingaben!$B$11),Eingaben!$B$45,0),0) -> 0 | G17: =C17-D17-E17+F17 -> -4055.012 | H17: =IFERROR(IF(AND(A17<=Eingaben!$B$11,Prüfungen!$B$4=0),1/(1+Eingaben!$B$39)^A17,0),0) -> 0.74409391 | I17: =G17*H17 -> -3017.3097 | J17: =J16+I17 -> -22915.246 | K17: =(D17+E17-F17)*H17 -> 4252.026 | L17: =B17*H17 -> 413.26214 | M17: =IF(AND(AND(A17<=Eingaben!$B$11,Prüfungen!$B$4=0),Berechnung!$B$14>0,J16<0,J17>=0,I17>0),A17-1-J16/I17,"")
A18: 11 | B18: =IF(AND(A18<=Eingaben!$B$11,Prüfungen!$B$4=0),Berechnung!$B$10,0) -> 555.38976 | C18: =IFERROR(IF(AND(A18<=Eingaben!$B$11,Prüfungen!$B$4=0),B18*(Eingaben!$B$36*(1+Eingaben!$B$40)^(A18-1)+Eingaben!$B$37*Eingaben!$B$38*(1+Eingaben!$B$46)^(A18-1)),0),0) -> 1692.5425 | D18: =IFERROR(IF(AND(A18<=Eingaben!$B$11,Prüfungen!$B$4=0),(Eingaben!$B$32+Eingaben!$B$35)*(1+Eingaben!$B$41)^(A18-1)+Berechnung!$B$15*Eingaben!$B$34*(1+Eingaben!$B$42)^(A18-1),0),0) -> 952.67705 | E18: =IFERROR(IF(AND(AND(A18<=Eingaben!$B$11,Prüfungen!$B$4=0),A18=Eingaben!$B$43),Eingaben!$B$44*(1+Eingaben!$B$41)^(A18-1),0),0) -> 0 | F18: =IFERROR(IF(AND(AND(A18<=Eingaben!$B$11,Prüfungen!$B$4=0),A18=Eingaben!$B$11),Eingaben!$B$45,0),0) -> 0 | G18: =C18-D18-E18+F18 -> 739.86549 | H18: =IFERROR(IF(AND(A18<=Eingaben!$B$11,Prüfungen!$B$4=0),1/(1+Eingaben!$B$39)^A18,0),0) -> 0.72242128 | I18: =G18*H18 -> 534.49457 | J18: =J17+I18 -> -22380.751 | K18: =(D18+E18-F18)*H18 -> 688.23417 | L18: =B18*H18 -> 401.22538 | M18: =IF(AND(AND(A18<=Eingaben!$B$11,Prüfungen!$B$4=0),Berechnung!$B$14>0,J17<0,J18>=0,I18>0),A18-1-J17/I18,"")
A19: 12 | B19: =IF(AND(A19<=Eingaben!$B$11,Prüfungen!$B$4=0),Berechnung!$B$10,0) -> 555.38976 | C19: =IFERROR(IF(AND(A19<=Eingaben!$B$11,Prüfungen!$B$4=0),B19*(Eingaben!$B$36*(1+Eingaben!$B$40)^(A19-1)+Eingaben!$B$37*Eingaben!$B$38*(1+Eingaben!$B$46)^(A19-1)),0),0) -> 1726.3934 | D19: =IFERROR(IF(AND(A19<=Eingaben!$B$11,Prüfungen!$B$4=0),(Eingaben!$B$32+Eingaben!$B$35)*(1+Eingaben!$B$41)^(A19-1)+Berechnung!$B$15*Eingaben!$B$34*(1+Eingaben!$B$42)^(A19-1),0),0) -> 971.73059 | E19: =IFERROR(IF(AND(AND(A19<=Eingaben!$B$11,Prüfungen!$B$4=0),A19=Eingaben!$B$43),Eingaben!$B$44*(1+Eingaben!$B$41)^(A19-1),0),0) -> 0 | F19: =IFERROR(IF(AND(AND(A19<=Eingaben!$B$11,Prüfungen!$B$4=0),A19=Eingaben!$B$11),Eingaben!$B$45,0),0) -> 0 | G19: =C19-D19-E19+F19 -> 754.6628 | H19: =IFERROR(IF(AND(A19<=Eingaben!$B$11,Prüfungen!$B$4=0),1/(1+Eingaben!$B$39)^A19,0),0) -> 0.70137988 | I19: =G19*H19 -> 529.3053 | J19: =J18+I19 -> -21851.446 | K19: =(D19+E19-F19)*H19 -> 681.55229 | L19: =B19*H19 -> 389.5392 | M19: =IF(AND(AND(A19<=Eingaben!$B$11,Prüfungen!$B$4=0),Berechnung!$B$14>0,J18<0,J19>=0,I19>0),A19-1-J18/I19,"")
... A57: 50 | B57: =IF(AND(A57<=Eingaben!$B$11,Prüfungen!$B$4=0),Berechnung!$B$10,0) -> 0 | C57: =IFERROR(IF(AND(A57<=Eingaben!$B$11,Prüfungen!$B$4=0),B57*(Eingaben!$B$36*(1+Eingaben!$B$40)^(A57-1)+Eingaben!$B$37*Eingaben!$B$38*(1+Eingaben!$B$46)^(A57-1)),0),0) -> 0 | D57: =IFERROR(IF(AND(A57<=Eingaben!$B$11,Prüfungen!$B$4=0),(Eingaben!$B$32+Eingaben!$B$35)*(1+Eingaben!$B$41)^(A57-1)+Berechnung!$B$15*Eingaben!$B$34*(1+Eingaben!$B$42)^(A57-1),0),0) -> 0 | E57: =IFERROR(IF(AND(AND(A57<=Eingaben!$B$11,Prüfungen!$B$4=0),A57=Eingaben!$B$43),Eingaben!$B$44*(1+Eingaben!$B$41)^(A57-1),0),0) -> 0 | F57: =IFERROR(IF(AND(AND(A57<=Eingaben!$B$11,Prüfungen!$B$4=0),A57=Eingaben!$B$11),Eingaben!$B$45,0),0) -> 0 | G57: =C57-D57-E57+F57 -> 0 | H57: =IFERROR(IF(AND(A57<=Eingaben!$B$11,Prüfungen!$B$4=0),1/(1+Eingaben!$B$39)^A57,0),0) -> 0 | I57: =G57*H57 -> 0 | J57: =J56+I57 -> -17797.873 | K57: =(D57+E57-F57)*H57 -> 0 | L57: =B57*H57 -> 0 | M57: =IF(AND(AND(A57<=Eingaben!$B$11,Prüfungen!$B$4=0),Berechnung!$B$14>0,J56<0,J57>=0,I57>0),A57-1-J56/I57,"")

Sheet Berechnung
A1: Kennzahlen · nachvollziehbarer Rechenkern
A2: Dashboard | B2: Eingaben | C2: Profile | D2: Kalender | E2: Methodik
A3: Ungültige Eingaben werden im Dashboard gesperrt. Technische Hilfswerte sind keine Ergebnisse bei Pflichtfehlern.
A4: Kennzahl | B4: Wert | C4: Einheit | D4: Definition / Bezug
A5: Pflichtfehler | B5: =Prüfungen!B4 -> 0 | C5: Anzahl | D5: Muss 0 sein.
A6: Jährlicher Grauwasseranfall | B6: =SUM(Wasserbilanz!D5:D370) -> 742.2 | C6: m³/a | D6: Rohgrauwasser aller Quellen.
A7: Verarbeitetes Rohgrauwasser | B7: =SUM(Wasserbilanz!F5:F370) -> 705.09 | C7: m³/a | D7: Kapazität und Verfügbarkeit begrenzen Verarbeitung.
A8: Aufbereitete Wassermenge | B8: =SUM(Wasserbilanz!G5:G370) -> 634.581 | C8: m³/a | D8: Verarbeitet × Ausbeute.
A9: Betriebswasserbedarf | B9: =SUM(Wasserbilanz!E5:E370) -> 1018.7 | C9: m³/a | D9: Bedarf aller zulässigen Anwendungen.
A10: Nutzbare Menge / Trinkwassereinsparung | B10: =SUM(Wasserbilanz!L5:L370) -> 555.38976 | C10: m³/a | D10: Altverbrauch + Direktverbrauch; ohne Nachspeisung.
A11: Erforderliche Trinkwassernachspeisung | B11: =SUM(Wasserbilanz!M5:M370) -> 463.31024 | C11: m³/a | D11: Bedarf − Wiederverwendung.
A12: Nicht genutztes aufbereitetes Wasser | B12: =B8-B10 -> 79.191243 | C12: m³/a | D12: Überschuss + Speicherverluste + Endbestand.
A13: Gesamtinvestition | B13: =IFERROR(SUM(Eingaben!B27:B30),0) -> 25000 | C13: € | D13: Planung + Anlage + Montage + Sonstiges.
A14: Nettoinvestition | B14: =IFERROR(MAX(0,B13-Eingaben!$B$31),0) -> 25000 | C14: € | D14: Gesamtinvestition − Förderung.
A15: Jährlicher Strombedarf | B15: =IFERROR(B7*Eingaben!$B$33,0) -> 705.09 | C15: kWh/a | D15: Energie auf verarbeitete Rohmenge, kein LCA-Nachweis.
A16: Betriebskosten Jahr 1 | B16: =IFERROR(Eingaben!$B$32+Eingaben!$B$35+B15*Eingaben!$B$34,0) -> 781.527 | C16: €/a | D16: Wartung, Sonstiges, Energie.
A17: Vermiedene Kosten Jahr 1 | B17: =IFERROR(B10*(Eingaben!$B$36+Eingaben!$B$37*Eingaben!$B$38),0) -> 1388.4744 | C17: €/a | D17: Nur tatsächlich vermiedene variable Gebühren.
A18: Netto-Cashflow Jahr 1 | B18: =B17-B16 -> 606.94739 | C18: €/a | D18: Vor Ersatzinvestition.
A19: Statische Amortisation | B19: =IF(B14=0,"Keine Nettoinvestition",IF(B18<=0,"Nicht erreichbar",B14/B18)) -> 41.189731 | C19: Jahre | D19: Konstante Jahr-1-Nettoeinsparung; ohne Zins/Ersatz.
A20: Kapitalwert | B20: =SUM(Zahlungen!I7:I57) -> -17797.873 | C20: € | D20: Summe aller diskontierten Cashflows incl. Jahr 0.
A21: Erste dynamische Amortisation | B21: =IF(B14=0,"Keine Nettoinvestition",IF(COUNT(Zahlungen!M8:M57)=0,"Im Zeitraum nicht erreicht",MIN(Zahlungen!M8:M57))) -> Im Zeitraum nicht erreicht | C21: Jahre | D21: Erste Rückgewinnung; interpoliert. Stabilität separat prüfen.
A22: Trinkwassereinsparquote | B22: =IFERROR(B10/(B9+Eingaben!$B$12),0) -> 0.22050651 | C22: % | D22: Trinkwasser-Baseline = Betriebsbedarf + sonstiger Bedarf.
A23: Deckungsgrad | B23: =IFERROR(B10/B9,0) -> 0.54519462 | C23: % | D23: Wiederverwendung / Betriebsbedarf.
A24: Grauwassernutzungsgrad | B24: =IFERROR(B10/B6,0) -> 0.74830202 | C24: % | D24: Wiederverwendung / Rohgrauwasseranfall.
A25: Spezifische Lebenszykluskosten | B25: =IF(SUM(Zahlungen!L7:L57)>0,SUM(Zahlungen!K7:K57)/SUM(Zahlungen!L7:L57),"Keine Einsparmenge") -> 5.1327577 | C25: €/m³ | D25: Barwert Kosten / Barwert eingespartes Volumen.
A26: Frischer Überschuss | B26: =SUM(Wasserbilanz!N5:N370) -> 0 | C26: m³/a | D26: Nicht speicherbarer frischer Tagesrest.
A27: Nachweis-Sperre | B27: =IF(OR(Eingaben!$B$21="Nicht erfüllt",Eingaben!$B$22="Nicht erfüllt",Eingaben!$B$23="Nicht erfüllt"),3,IF(OR(Eingaben!$B$21="Ungeklärt",Eingaben!$B$22="Ungeklärt",Eingaben!$B$23="Ungeklärt"),2,1)) -> 2 | C27: 1/2/3 | D27: Maximum mit Kategorien, niemals kompensiert.
A28: Ökonomischer Score | B28: =IFERROR(IF(B14=0,IF(B20>=0,1,3),IF(B20/B14>=Schwellenwerte!B5,1,IF(B20/B14>=Schwellenwerte!B6,2,3))),"Nicht bewertbar") -> 3 | C28: 1/2/3 | D28: Kapitalwert relativ zur Nettoinvestition.
A29: Ressourcen-Score | B29: =IFERROR(IF(B10<=0,3,IF(B22>=Schwellenwerte!B9,1,IF(B22>=Schwellenwerte!B10,2,3))),"Nicht bewertbar") -> 1 | C29: 1/2/3 | D29: Nur Einsparquote wird bewertet.
A30: Gesamt-Score | B30: =IFERROR(MAX(B27:B29),"Nicht bewertbar") -> 3 | C30: 1/2/3 | D30: Schlechteste Kategorie einschließlich Nachweisen.
A31: Ökonomische Ampel | B31: =IF(B5>0,"Nicht bewertbar",IF(B28=1,"Grün",IF(B28=2,"Gelb","Rot"))) -> Rot | C31: Status | D31: Günstig / bedingt / ungünstig.
A32: Ressourcenampel | B32: =IF(B5>0,"Nicht bewertbar",IF(B29=1,"Grün",IF(B29=2,"Gelb","Rot"))) -> Grün | C32: Status | D32: Keine Aussage über gesamtheitliche Umweltbilanz.
A33: Gesamtbewertung | B33: =IF(B5>0,"Nicht bewertbar",IF(B30=1,"Grün",IF(B30=2,"Gelb","Rot"))) -> Rot | C33: Status | D33: Keine behördliche oder normative Freigabe.
A34: Nachweisstatus | B34: =IF(B27=3,"Mindestens ein Nachweis nicht erfüllt",IF(B27=2,"PRÜFBEDARF: Nachweise ungeklärt","Alle Nachweise als erbracht eingetragen")) -> PRÜFBEDARF: Nachweise ungeklärt | C34: Status | D34: Selbstauskunft, Belege separat prüfen.
A35: Jahresbilanzrest | B35: =B8-B10-B26-B38-B39 -> 0 | C35: m³/a | D35: Aufbereitet = Nutzung + Überschuss + Verlust + Endbestand.
A36: Rohwasser-Kontrollrest | B36: =SUM(Nutzungsprofile!G6:G11)-B6 -> 0 | C36: m³/a | D36: Profil-Jahresmenge minus Tagesintegration.
A37: Dynamische Rückgewinnung stabil? | B37: =IF(ISNUMBER(B21),IF(SUMPRODUCT((Zahlungen!A8:A57>=ROUNDUP(B21,0))*(Zahlungen!A8:A57<=Eingaben!$B$11 )*(Zahlungen!J8:J57<0))=0,"Stabil bis Horizont","Spätere Unterdeckung"),"Keine positive Rückgewinnung") -> Keine positive Rückgewinnung | C37: Status | D37: Ersatzinvestition kann erste Amortisation rückgängig machen.
A38: Speicherverluste / verworfene Altmenge | B38: =SUM(Wasserbilanz!O5:O370) -> 79.191243 | C38: m³/a | D38: Übertragsverluste + ungenutzte Vortragsmenge.
A39: Endbestand Bilanzjahr | B39: =IFERROR(INDEX(Wasserbilanz!K5:K370,DATE(Eingaben!$B$10+1,1,1)-DATE(Eingaben!$B$10,1,1)),0) -> 0 | C39: m³ | D39: Jahresende enthält keine im Jahr verbuchte Einsparung.
A40: Kritische Hinweise | B40: =IF(Eingaben!$B$48="Beispieldaten","BEISPIELDATEN · ","")&IF(B5>0,"Eingaben korrigieren (Prüfungen). · ","")&IF(B27>1,B34&" · ","")&IF(B10=0,"Keine Wassereinsparung. · ","")&IF(B18<=0,"Keine positive Nettoeinsparung in Jahr 1. · ","")&IF(AND(ISNUMBER(B19),B19>Eingaben!$B$11),"Statische Amortisation außerhalb Horizont. · ","")&"Schwellen vorläufig; Tagesprofil und Quellen projektbezogen validieren." -> BEISPIELDATEN · PRÜFBEDARF: Nachweise ungeklärt · Statische Amortisation außerhalb Horizont. · Schwellen vorläufig; Tagesprofil und Quellen projektbezogen validieren. | C40: Text | D40: Kein Freigabenachweis.
A41: Bewertungsstatus | B41: =IF(B5>0,"Nicht bewertbar",IF(Eingaben!$B$48="Beispieldaten","Modellergebnis mit Beispieldaten",IF(B27>1,"Modellergebnis mit Prüfbedarf","Modellergebnis – Nachweise eingetragen"))) -> Modellergebnis mit Beispieldaten | C41: Status | D41: Datenqualität und fachliche Freigabe sind getrennt.
A42: Aufbereitungsverlust | B42: =B7-B8 -> 70.509 | C42: m³/a | D42: Verarbeitet minus aufbereitet.
A43: Nicht verarbeitetes Rohwasser | B43: =B6-B7 -> 37.11 | C43: m³/a | D43: Kapazitäts-/Verfügbarkeitsbegrenzung.

Sheet Szenarien
A1: Szenarien & Sensitivität
A2: Dashboard | B2: Eingaben | C2: Profile | D2: Kalender | E2: Methodik
A3: Jede Zeile rechnet die gesamte Tagesbilanz erneut. Faktoren sind frei veränderbare Annahmen; Zinsänderung in Prozentpunkten.
A5: Faktor 1,00 = tatsächlicher Projektansatz. Basisszenario startet mit 1,00; Projekt-Dashboard bleibt unverändert.
A7: Variante | B7: Investitionsfaktor | C7: Wasserpreisfaktor | D7: Bedarfsfaktor | E7: Grauwasserfaktor | F7: Betriebskostenfaktor | G7: Zins Δ | H7: Prüfung | I7: Nutzung m³/a | J7: Einsparquote | K7: CF Jahr 1 € | L7: Kapitalwert € | M7: Statisch Jahre | N7: Ökonomie | O7: Ressourcen | P7: Gesamt
A8: Konservativ | B8: 1.2 | C8: 0.9 | D8: 0.9 | E8: 0.8 | F8: 1.2 | G8: 0.01 | H8: =IFERROR(IF(AND(Prüfungen!$B$4=0,COUNT(B8:G8)=6,MIN(B8:F8)>=0,MAX(B8:F8)<=10,Eingaben!$B$39+G8>=0,Eingaben!$B$39+G8<=1),"OK","FEHLER"),"FEHLER") -> OK | I8: =IF(H8="OK",SUM(Variantenbilanz!K5:K370),"Nicht bewertbar") -> 455.34781 | J8: =IF(H8="OK",IFERROR(I8/(SUM(Variantenbilanz!D5:D370)+Eingaben!$B$12),0),"Nicht bewertbar") -> 0.18840705 | K8: =IF(H8="OK",IFERROR(I8*(Eingaben!$B$36*C8+Eingaben!$B$37*Eingaben!$B$38)-(Eingaben!$B$32+Eingaben!$B$35+SUM(Variantenbilanz!E5:E370)*Eingaben!$B$33*Eingaben!$B$34 )*F8,0),"Nicht bewertbar") -> 137.46664 | L8: =IF(H8="OK",SUM(VariantenCF!I5:I55),"Nicht bewertbar") -> -31663.271 | M8: =IF(H8="OK",IF(MAX(0,Berechnung!$B$13*Szenarien!$B$8-MIN(Eingaben!$B$31,Berechnung!$B$13*Szenarien!$B$8))=0,"Keine Nettoinvestition",IF(K8<=0,"Nicht erreichbar",MAX(0,Berechnung!$B$13*Szenarien!$B$8-MIN(Eingaben!$B$31,Berechnung!$B$13*Szenarien!$B$8))/K8)),"Nicht bewertbar") -> 218.23476 | N8: =IF(H8="OK",IF(IF(MAX(0,Berechnung!$B$13*Szenarien!$B$8-MIN(Eingaben!$B$31,Berechnung!$B$13*Szenarien!$B$8))=0,IF(L8>=0,1,3),IF(L8/MAX(0,Berechnung!$B$13*Szenarien!$B$8-MIN(Eingaben!$B$31,Berechnung!$B$13*Szenarien!$B$8))>=Schwellenwerte!B5,1,IF(L8/MAX(0,Berechnung!$B$13*Szenarien!$B$8-MIN(Eingaben!$B$31,Berechnung!$B$13*Szenarien!$B$8))>=Schwellenwerte!B6,2,3)))=1,"Grün",IF(IF(MAX(0,Berechnung!$B$13*Szenarien!$B$8-MIN(Eingaben!$B$31,Berechnung!$B$13*Szenarien!$B$8))=0,IF(L8>=0,1,3),IF(L8/MAX(0,Berechnung!$B$13*Szenarien!$B$8-MIN(Eingaben!$B$31,Berechnung!$B$13*Szenarien!$B$8))>=Schwellenwerte!B5,1,IF(L8/MAX(0,Berechnung!$B$13*Szenarien!$B$8-MIN(Eingaben!$B$31,Berechnung!$B$13*Szenarien!$B$8))>=Schwellenwerte!B6,2,3)))=2,"Gelb","Rot")),"Nicht bewertbar") -> Rot | O8: =IF(H8="OK",IF(IF(I8<=0,3,IF(J8>=Schwellenwerte!B9,1,IF(J8>=Schwellenwerte!B10,2,3)))=1,"Grün",IF(IF(I8<=0,3,IF(J8>=Schwellenwerte!B9,1,IF(J8>=Schwellenwerte!B10,2,3)))=2,"Gelb","Rot")),"Nicht bewertbar") -> Grün | P8: =IF(H8="OK",IF(OR(N8="Rot",O8="Rot",Berechnung!$B$27=3),"Rot",IF(OR(N8="Gelb",O8="Gelb",Berechnung!$B$27=2),"Gelb","Grün")),"Nicht bewertbar") -> Rot
A9: Basis | B9: 1 | C9: 1 | D9: 1 | E9: 1 | F9: 1 | G9: 0 | H9: =IFERROR(IF(AND(Prüfungen!$B$4=0,COUNT(B9:G9)=6,MIN(B9:F9)>=0,MAX(B9:F9)<=10,Eingaben!$B$39+G9>=0,Eingaben!$B$39+G9<=1),"OK","FEHLER"),"FEHLER") -> OK | I9: =IF(H9="OK",SUM(Variantenbilanz!K371:K736),"Nicht bewertbar") -> 555.38976 | J9: =IF(H9="OK",IFERROR(I9/(SUM(Variantenbilanz!D371:D736)+Eingaben!$B$12),0),"Nicht bewertbar") -> 0.22050651 | K9: =IF(H9="OK",IFERROR(I9*(Eingaben!$B$36*C9+Eingaben!$B$37*Eingaben!$B$38)-(Eingaben!$B$32+Eingaben!$B$35+SUM(Variantenbilanz!E371:E736)*Eingaben!$B$33*Eingaben!$B$34 )*F9,0),"Nicht bewertbar") -> 606.94739 | L9: =IF(H9="OK",SUM(VariantenCF!I56:I106),"Nicht bewertbar") -> -17797.873 | M9: =IF(H9="OK",IF(MAX(0,Berechnung!$B$13*Szenarien!$B$9-MIN(Eingaben!$B$31,Berechnung!$B$13*Szenarien!$B$9))=0,"Keine Nettoinvestition",IF(K9<=0,"Nicht erreichbar",MAX(0,Berechnung!$B$13*Szenarien!$B$9-MIN(Eingaben!$B$31,Berechnung!$B$13*Szenarien!$B$9))/K9)),"Nicht bewertbar") -> 41.189731 | N9: =IF(H9="OK",IF(IF(MAX(0,Berechnung!$B$13*Szenarien!$B$9-MIN(Eingaben!$B$31,Berechnung!$B$13*Szenarien!$B$9))=0,IF(L9>=0,1,3),IF(L9/MAX(0,Berechnung!$B$13*Szenarien!$B$9-MIN(Eingaben!$B$31,Berechnung!$B$13*Szenarien!$B$9))>=Schwellenwerte!B5,1,IF(L9/MAX(0,Berechnung!$B$13*Szenarien!$B$9-MIN(Eingaben!$B$31,Berechnung!$B$13*Szenarien!$B$9))>=Schwellenwerte!B6,2,3)))=1,"Grün",IF(IF(MAX(0,Berechnung!$B$13*Szenarien!$B$9-MIN(Eingaben!$B$31,Berechnung!$B$13*Szenarien!$B$9))=0,IF(L9>=0,1,3),IF(L9/MAX(0,Berechnung!$B$13*Szenarien!$B$9-MIN(Eingaben!$B$31,Berechnung!$B$13*Szenarien!$B$9))>=Schwellenwerte!B5,1,IF(L9/MAX(0,Berechnung!$B$13*Szenarien!$B$9-MIN(Eingaben!$B$31,Berechnung!$B$13*Szenarien!$B$9))>=Schwellenwerte!B6,2,3)))=2,"Gelb","Rot")),"Nicht bewertbar") -> Rot | O9: =IF(H9="OK",IF(IF(I9<=0,3,IF(J9>=Schwellenwerte!B9,1,IF(J9>=Schwellenwerte!B10,2,3)))=1,"Grün",IF(IF(I9<=0,3,IF(J9>=Schwellenwerte!B9,1,IF(J9>=Schwellenwerte!B10,2,3)))=2,"Gelb","Rot")),"Nicht bewertbar") -> Grün | P9: =IF(H9="OK",IF(OR(N9="Rot",O9="Rot",Berechnung!$B$27=3),"Rot",IF(OR(N9="Gelb",O9="Gelb",Berechnung!$B$27=2),"Gelb","Grün")),"Nicht bewertbar") -> Rot
A10: Optimistisch | B10: 0.8 | C10: 1.1 | D10: 1.1 | E10: 1.2 | F10: 0.8 | G10: -0.01 | H10: =IFERROR(IF(AND(Prüfungen!$B$4=0,COUNT(B10:G10)=6,MIN(B10:F10)>=0,MAX(B10:F10)<=10,Eingaben!$B$39+G10>=0,Eingaben!$B$39+G10<=1),"OK","FEHLER"),"FEHLER") -> OK | I10: =IF(H10="OK",SUM(Variantenbilanz!K737:K1102),"Nicht bewertbar") -> 652.51397 | J10: =IF(H10="OK",IFERROR(I10/(SUM(Variantenbilanz!D737:D1102)+Eingaben!$B$12),0),"Nicht bewertbar") -> 0.24899696 | K10: =IF(H10="OK",IFERROR(I10*(Eingaben!$B$36*C10+Eingaben!$B$37*Eingaben!$B$38)-(Eingaben!$B$32+Eingaben!$B$35+SUM(Variantenbilanz!E737:E1102)*Eingaben!$B$33*Eingaben!$B$34 )*F10,0),"Nicht bewertbar") -> 1135.3475 | L10: =IF(H10="OK",SUM(VariantenCF!I107:I157),"Nicht bewertbar") -> -875.53904 | M10: =IF(H10="OK",IF(MAX(0,Berechnung!$B$13*Szenarien!$B$10-MIN(Eingaben!$B$31,Berechnung!$B$13*Szenarien!$B$10))=0,"Keine Nettoinvestition",IF(K10<=0,"Nicht erreichbar",MAX(0,Berechnung!$B$13*Szenarien!$B$10-MIN(Eingaben!$B$31,Berechnung!$B$13*Szenarien!$B$10))/K10)),"Nicht bewertbar") -> 17.615752 | N10: =IF(H10="OK",IF(IF(MAX(0,Berechnung!$B$13*Szenarien!$B$10-MIN(Eingaben!$B$31,Berechnung!$B$13*Szenarien!$B$10))=0,IF(L10>=0,1,3),IF(L10/MAX(0,Berechnung!$B$13*Szenarien!$B$10-MIN(Eingaben!$B$31,Berechnung!$B$13*Szenarien!$B$10))>=Schwellenwerte!B5,1,IF(L10/MAX(0,Berechnung!$B$13*Szenarien!$B$10-MIN(Eingaben!$B$31,Berechnung!$B$13*Szenarien!$B$10))>=Schwellenwerte!B6,2,3)))=1,"Grün",IF(IF(MAX(0,Berechnung!$B$13*Szenarien!$B$10-MIN(Eingaben!$B$31,Berechnung!$B$13*Szenarien!$B$10))=0,IF(L10>=0,1,3),IF(L10/MAX(0,Berechnung!$B$13*Szenarien!$B$10-MIN(Eingaben!$B$31,Berechnung!$B$13*Szenarien!$B$10))>=Schwellenwerte!B5,1,IF(L10/MAX(0,Berechnung!$B$13*Szenarien!$B$10-MIN(Eingaben!$B$31,Berechnung!$B$13*Szenarien!$B$10))>=Schwellenwerte!B6,2,3)))=2,"Gelb","Rot")),"Nicht bewertbar") -> Gelb | O10: =IF(H10="OK",IF(IF(I10<=0,3,IF(J10>=Schwellenwerte!B9,1,IF(J10>=Schwellenwerte!B10,2,3)))=1,"Grün",IF(IF(I10<=0,3,IF(J10>=Schwellenwerte!B9,1,IF(J10>=Schwellenwerte!B10,2,3)))=2,"Gelb","Rot")),"Nicht bewertbar") -> Grün | P10: =IF(H10="OK",IF(OR(N10="Rot",O10="Rot",Berechnung!$B$27=3),"Rot",IF(OR(N10="Gelb",O10="Gelb",Berechnung!$B$27=2),"Gelb","Grün")),"Nicht bewertbar") -> Gelb
A12: Einzelfaktor-Sensitivitäten: alle anderen Faktoren = 1. Die Beschriftungen beschreiben die Startwerte; Werte frei editierbar.
L13: Kapitalwert €
A14: Investition −20 % | B14: 0.8 | C14: 1 | D14: 1 | E14: 1 | F14: 1 | G14: 0 | H14: =IFERROR(IF(AND(Prüfungen!$B$4=0,COUNT(B14:G14)=6,MIN(B14:F14)>=0,MAX(B14:F14)<=10,Eingaben!$B$39+G14>=0,Eingaben!$B$39+G14<=1),"OK","FEHLER"),"FEHLER") -> OK | I14: =IF(H14="OK",SUM(Variantenbilanz!K1103:K1468),"Nicht bewertbar") -> 555.38976 | J14: =IF(H14="OK",IFERROR(I14/(SUM(Variantenbilanz!D1103:D1468)+Eingaben!$B$12),0),"Nicht bewertbar") -> 0.22050651 | K14: =IF(H14="OK",IFERROR(I14*(Eingaben!$B$36*C14+Eingaben!$B$37*Eingaben!$B$38)-(Eingaben!$B$32+Eingaben!$B$35+SUM(Variantenbilanz!E1103:E1468)*Eingaben!$B$33*Eingaben!$B$34 )*F14,0),"Nicht bewertbar") -> 606.94739 | L14: =IF(H14="OK",SUM(VariantenCF!I158:I208),"Nicht bewertbar") -> -12086.464 | M14: =IF(H14="OK",IF(MAX(0,Berechnung!$B$13*Szenarien!$B$14-MIN(Eingaben!$B$31,Berechnung!$B$13*Szenarien!$B$14))=0,"Keine Nettoinvestition",IF(K14<=0,"Nicht erreichbar",MAX(0,Berechnung!$B$13*Szenarien!$B$14-MIN(Eingaben!$B$31,Berechnung!$B$13*Szenarien!$B$14))/K14)),"Nicht bewertbar") -> 32.951785 | N14: =IF(H14="OK",IF(IF(MAX(0,Berechnung!$B$13*Szenarien!$B$14-MIN(Eingaben!$B$31,Berechnung!$B$13*Szenarien!$B$14))=0,IF(L14>=0,1,3),IF(L14/MAX(0,Berechnung!$B$13*Szenarien!$B$14-MIN(Eingaben!$B$31,Berechnung!$B$13*Szenarien!$B$14))>=Schwellenwerte!B5,1,IF(L14/MAX(0,Berechnung!$B$13*Szenarien!$B$14-MIN(Eingaben!$B$31,Berechnung!$B$13*Szenarien!$B$14))>=Schwellenwerte!B6,2,3)))=1,"Grün",IF(IF(MAX(0,Berechnung!$B$13*Szenarien!$B$14-MIN(Eingaben!$B$31,Berechnung!$B$13*Szenarien!$B$14))=0,IF(L14>=0,1,3),IF(L14/MAX(0,Berechnung!$B$13*Szenarien!$B$14-MIN(Eingaben!$B$31,Berechnung!$B$13*Szenarien!$B$14))>=Schwellenwerte!B5,1,IF(L14/MAX(0,Berechnung!$B$13*Szenarien!$B$14-MIN(Eingaben!$B$31,Berechnung!$B$13*Szenarien!$B$14))>=Schwellenwerte!B6,2,3)))=2,"Gelb","Rot")),"Nicht bewertbar") -> Rot | O14: =IF(H14="OK",IF(IF(I14<=0,3,IF(J14>=Schwellenwerte!B9,1,IF(J14>=Schwellenwerte!B10,2,3)))=1,"Grün",IF(IF(I14<=0,3,IF(J14>=Schwellenwerte!B9,1,IF(J14>=Schwellenwerte!B10,2,3)))=2,"Gelb","Rot")),"Nicht bewertbar") -> Grün | P14: =IF(H14="OK",IF(OR(N14="Rot",O14="Rot",Berechnung!$B$27=3),"Rot",IF(OR(N14="Gelb",O14="Gelb",Berechnung!$B$27=2),"Gelb","Grün")),"Nicht bewertbar") -> Rot
A15: Investition +20 % | B15: 1.2 | C15: 1 | D15: 1 | E15: 1 | F15: 1 | G15: 0 | H15: =IFERROR(IF(AND(Prüfungen!$B$4=0,COUNT(B15:G15)=6,MIN(B15:F15)>=0,MAX(B15:F15)<=10,Eingaben!$B$39+G15>=0,Eingaben!$B$39+G15<=1),"OK","FEHLER"),"FEHLER") -> OK | I15: =IF(H15="OK",SUM(Variantenbilanz!K1469:K1834),"Nicht bewertbar") -> 555.38976 | J15: =IF(H15="OK",IFERROR(I15/(SUM(Variantenbilanz!D1469:D1834)+Eingaben!$B$12),0),"Nicht bewertbar") -> 0.22050651 | K15: =IF(H15="OK",IFERROR(I15*(Eingaben!$B$36*C15+Eingaben!$B$37*Eingaben!$B$38)-(Eingaben!$B$32+Eingaben!$B$35+SUM(Variantenbilanz!E1469:E1834)*Eingaben!$B$33*Eingaben!$B$34 )*F15,0),"Nicht bewertbar") -> 606.94739 | L15: =IF(H15="OK",SUM(VariantenCF!I209:I259),"Nicht bewertbar") -> -23509.282 | M15: =IF(H15="OK",IF(MAX(0,Berechnung!$B$13*Szenarien!$B$15-MIN(Eingaben!$B$31,Berechnung!$B$13*Szenarien!$B$15))=0,"Keine Nettoinvestition",IF(K15<=0,"Nicht erreichbar",MAX(0,Berechnung!$B$13*Szenarien!$B$15-MIN(Eingaben!$B$31,Berechnung!$B$13*Szenarien!$B$15))/K15)),"Nicht bewertbar") -> 49.427677 | N15: =IF(H15="OK",IF(IF(MAX(0,Berechnung!$B$13*Szenarien!$B$15-MIN(Eingaben!$B$31,Berechnung!$B$13*Szenarien!$B$15))=0,IF(L15>=0,1,3),IF(L15/MAX(0,Berechnung!$B$13*Szenarien!$B$15-MIN(Eingaben!$B$31,Berechnung!$B$13*Szenarien!$B$15))>=Schwellenwerte!B5,1,IF(L15/MAX(0,Berechnung!$B$13*Szenarien!$B$15-MIN(Eingaben!$B$31,Berechnung!$B$13*Szenarien!$B$15))>=Schwellenwerte!B6,2,3)))=1,"Grün",IF(IF(MAX(0,Berechnung!$B$13*Szenarien!$B$15-MIN(Eingaben!$B$31,Berechnung!$B$13*Szenarien!$B$15))=0,IF(L15>=0,1,3),IF(L15/MAX(0,Berechnung!$B$13*Szenarien!$B$15-MIN(Eingaben!$B$31,Berechnung!$B$13*Szenarien!$B$15))>=Schwellenwerte!B5,1,IF(L15/MAX(0,Berechnung!$B$13*Szenarien!$B$15-MIN(Eingaben!$B$31,Berechnung!$B$13*Szenarien!$B$15))>=Schwellenwerte!B6,2,3)))=2,"Gelb","Rot")),"Nicht bewertbar") -> Rot | O15: =IF(H15="OK",IF(IF(I15<=0,3,IF(J15>=Schwellenwerte!B9,1,IF(J15>=Schwellenwerte!B10,2,3)))=1,"Grün",IF(IF(I15<=0,3,IF(J15>=Schwellenwerte!B9,1,IF(J15>=Schwellenwerte!B10,2,3)))=2,"Gelb","Rot")),"Nicht bewertbar") -> Grün | P15: =IF(H15="OK",IF(OR(N15="Rot",O15="Rot",Berechnung!$B$27=3),"Rot",IF(OR(N15="Gelb",O15="Gelb",Berechnung!$B$27=2),"Gelb","Grün")),"Nicht bewertbar") -> Rot
A16: Trinkwasserpreis −20 % | B16: 1 | C16: 0.8 | D16: 1 | E16: 1 | F16: 1 | G16: 0 | H16: =IFERROR(IF(AND(Prüfungen!$B$4=0,COUNT(B16:G16)=6,MIN(B16:F16)>=0,MAX(B16:F16)<=10,Eingaben!$B$39+G16>=0,Eingaben!$B$39+G16<=1),"OK","FEHLER"),"FEHLER") -> OK | I16: =IF(H16="OK",SUM(Variantenbilanz!K1835:K2200),"Nicht bewertbar") -> 555.38976 | J16: =IF(H16="OK",IFERROR(I16/(SUM(Variantenbilanz!D1835:D2200)+Eingaben!$B$12),0),"Nicht bewertbar") -> 0.22050651 | K16: =IF(H16="OK",IFERROR(I16*(Eingaben!$B$36*C16+Eingaben!$B$37*Eingaben!$B$38)-(Eingaben!$B$32+Eingaben!$B$35+SUM(Variantenbilanz!E1835:E2200)*Eingaben!$B$33*Eingaben!$B$34 )*F16,0),"Nicht bewertbar") -> 329.25251 | L16: =IF(H16="OK",SUM(VariantenCF!I260:I310),"Nicht bewertbar") -> -22720.485 | M16: =IF(H16="OK",IF(MAX(0,Berechnung!$B$13*Szenarien!$B$16-MIN(Eingaben!$B$31,Berechnung!$B$13*Szenarien!$B$16))=0,"Keine Nettoinvestition",IF(K16<=0,"Nicht erreichbar",MAX(0,Berechnung!$B$13*Szenarien!$B$16-MIN(Eingaben!$B$31,Berechnung!$B$13*Szenarien!$B$16))/K16)),"Nicht bewertbar") -> 75.929564 | N16: =IF(H16="OK",IF(IF(MAX(0,Berechnung!$B$13*Szenarien!$B$16-MIN(Eingaben!$B$31,Berechnung!$B$13*Szenarien!$B$16))=0,IF(L16>=0,1,3),IF(L16/MAX(0,Berechnung!$B$13*Szenarien!$B$16-MIN(Eingaben!$B$31,Berechnung!$B$13*Szenarien!$B$16))>=Schwellenwerte!B5,1,IF(L16/MAX(0,Berechnung!$B$13*Szenarien!$B$16-MIN(Eingaben!$B$31,Berechnung!$B$13*Szenarien!$B$16))>=Schwellenwerte!B6,2,3)))=1,"Grün",IF(IF(MAX(0,Berechnung!$B$13*Szenarien!$B$16-MIN(Eingaben!$B$31,Berechnung!$B$13*Szenarien!$B$16))=0,IF(L16>=0,1,3),IF(L16/MAX(0,Berechnung!$B$13*Szenarien!$B$16-MIN(Eingaben!$B$31,Berechnung!$B$13*Szenarien!$B$16))>=Schwellenwerte!B5,1,IF(L16/MAX(0,Berechnung!$B$13*Szenarien!$B$16-MIN(Eingaben!$B$31,Berechnung!$B$13*Szenarien!$B$16))>=Schwellenwerte!B6,2,3)))=2,"Gelb","Rot")),"Nicht bewertbar") -> Rot | O16: =IF(H16="OK",IF(IF(I16<=0,3,IF(J16>=Schwellenwerte!B9,1,IF(J16>=Schwellenwerte!B10,2,3)))=1,"Grün",IF(IF(I16<=0,3,IF(J16>=Schwellenwerte!B9,1,IF(J16>=Schwellenwerte!B10,2,3)))=2,"Gelb","Rot")),"Nicht bewertbar") -> Grün | P16: =IF(H16="OK",IF(OR(N16="Rot",O16="Rot",Berechnung!$B$27=3),"Rot",IF(OR(N16="Gelb",O16="Gelb",Berechnung!$B$27=2),"Gelb","Grün")),"Nicht bewertbar") -> Rot
A17: Trinkwasserpreis +20 % | B17: 1 | C17: 1.2 | D17: 1 | E17: 1 | F17: 1 | G17: 0 | H17: =IFERROR(IF(AND(Prüfungen!$B$4=0,COUNT(B17:G17)=6,MIN(B17:F17)>=0,MAX(B17:F17)<=10,Eingaben!$B$39+G17>=0,Eingaben!$B$39+G17<=1),"OK","FEHLER"),"FEHLER") -> OK | I17: =IF(H17="OK",SUM(Variantenbilanz!K2201:K2566),"Nicht bewertbar") -> 555.38976 | J17: =IF(H17="OK",IFERROR(I17/(SUM(Variantenbilanz!D2201:D2566)+Eingaben!$B$12),0),"Nicht bewertbar") -> 0.22050651 | K17: =IF(H17="OK",IFERROR(I17*(Eingaben!$B$36*C17+Eingaben!$B$37*Eingaben!$B$38)-(Eingaben!$B$32+Eingaben!$B$35+SUM(Variantenbilanz!E2201:E2566)*Eingaben!$B$33*Eingaben!$B$34 )*F17,0),"Nicht bewertbar") -> 884.64227 | L17: =IF(H17="OK",SUM(VariantenCF!I311:I361),"Nicht bewertbar") -> -12875.26 | M17: =IF(H17="OK",IF(MAX(0,Berechnung!$B$13*Szenarien!$B$17-MIN(Eingaben!$B$31,Berechnung!$B$13*Szenarien!$B$17))=0,"Keine Nettoinvestition",IF(K17<=0,"Nicht erreichbar",MAX(0,Berechnung!$B$13*Szenarien!$B$17-MIN(Eingaben!$B$31,Berechnung!$B$13*Szenarien!$B$17))/K17)),"Nicht bewertbar") -> 28.260011 | N17: =IF(H17="OK",IF(IF(MAX(0,Berechnung!$B$13*Szenarien!$B$17-MIN(Eingaben!$B$31,Berechnung!$B$13*Szenarien!$B$17))=0,IF(L17>=0,1,3),IF(L17/MAX(0,Berechnung!$B$13*Szenarien!$B$17-MIN(Eingaben!$B$31,Berechnung!$B$13*Szenarien!$B$17))>=Schwellenwerte!B5,1,IF(L17/MAX(0,Berechnung!$B$13*Szenarien!$B$17-MIN(Eingaben!$B$31,Berechnung!$B$13*Szenarien!$B$17))>=Schwellenwerte!B6,2,3)))=1,"Grün",IF(IF(MAX(0,Berechnung!$B$13*Szenarien!$B$17-MIN(Eingaben!$B$31,Berechnung!$B$13*Szenarien!$B$17))=0,IF(L17>=0,1,3),IF(L17/MAX(0,Berechnung!$B$13*Szenarien!$B$17-MIN(Eingaben!$B$31,Berechnung!$B$13*Szenarien!$B$17))>=Schwellenwerte!B5,1,IF(L17/MAX(0,Berechnung!$B$13*Szenarien!$B$17-MIN(Eingaben!$B$31,Berechnung!$B$13*Szenarien!$B$17))>=Schwellenwerte!B6,2,3)))=2,"Gelb","Rot")),"Nicht bewertbar") -> Rot | O17: =IF(H17="OK",IF(IF(I17<=0,3,IF(J17>=Schwellenwerte!B9,1,IF(J17>=Schwellenwerte!B10,2,3)))=1,"Grün",IF(IF(I17<=0,3,IF(J17>=Schwellenwerte!B9,1,IF(J17>=Schwellenwerte!B10,2,3)))=2,"Gelb","Rot")),"Nicht bewertbar") -> Grün | P17: =IF(H17="OK",IF(OR(N17="Rot",O17="Rot",Berechnung!$B$27=3),"Rot",IF(OR(N17="Gelb",O17="Gelb",Berechnung!$B$27=2),"Gelb","Grün")),"Nicht bewertbar") -> Rot
A18: Betriebswasserbedarf −20 % | B18: 1 | C18: 1 | D18: 0.8 | E18: 1 | F18: 1 | G18: 0 | H18: =IFERROR(IF(AND(Prüfungen!$B$4=0,COUNT(B18:G18)=6,MIN(B18:F18)>=0,MAX(B18:F18)<=10,Eingaben!$B$39+G18>=0,Eingaben!$B$39+G18<=1),"OK","FEHLER"),"FEHLER") -> OK | I18: =IF(H18="OK",SUM(Variantenbilanz!K2567:K2932),"Nicht bewertbar") -> 533.31776 | J18: =IF(H18="OK",IFERROR(I18/(SUM(Variantenbilanz!D2567:D2932)+Eingaben!$B$12),0),"Nicht bewertbar") -> 0.23037882 | K18: =IF(H18="OK",IFERROR(I18*(Eingaben!$B$36*C18+Eingaben!$B$37*Eingaben!$B$38)-(Eingaben!$B$32+Eingaben!$B$35+SUM(Variantenbilanz!E2567:E2932)*Eingaben!$B$33*Eingaben!$B$34 )*F18,0),"Nicht bewertbar") -> 551.76739 | L18: =IF(H18="OK",SUM(VariantenCF!I362:I412),"Nicht bewertbar") -> -18776.032 | M18: =IF(H18="OK",IF(MAX(0,Berechnung!$B$13*Szenarien!$B$18-MIN(Eingaben!$B$31,Berechnung!$B$13*Szenarien!$B$18))=0,"Keine Nettoinvestition",IF(K18<=0,"Nicht erreichbar",MAX(0,Berechnung!$B$13*Szenarien!$B$18-MIN(Eingaben!$B$31,Berechnung!$B$13*Szenarien!$B$18))/K18)),"Nicht bewertbar") -> 45.308948 | N18: =IF(H18="OK",IF(IF(MAX(0,Berechnung!$B$13*Szenarien!$B$18-MIN(Eingaben!$B$31,Berechnung!$B$13*Szenarien!$B$18))=0,IF(L18>=0,1,3),IF(L18/MAX(0,Berechnung!$B$13*Szenarien!$B$18-MIN(Eingaben!$B$31,Berechnung!$B$13*Szenarien!$B$18))>=Schwellenwerte!B5,1,IF(L18/MAX(0,Berechnung!$B$13*Szenarien!$B$18-MIN(Eingaben!$B$31,Berechnung!$B$13*Szenarien!$B$18))>=Schwellenwerte!B6,2,3)))=1,"Grün",IF(IF(MAX(0,Berechnung!$B$13*Szenarien!$B$18-MIN(Eingaben!$B$31,Berechnung!$B$13*Szenarien!$B$18))=0,IF(L18>=0,1,3),IF(L18/MAX(0,Berechnung!$B$13*Szenarien!$B$18-MIN(Eingaben!$B$31,Berechnung!$B$13*Szenarien!$B$18))>=Schwellenwerte!B5,1,IF(L18/MAX(0,Berechnung!$B$13*Szenarien!$B$18-MIN(Eingaben!$B$31,Berechnung!$B$13*Szenarien!$B$18))>=Schwellenwerte!B6,2,3)))=2,"Gelb","Rot")),"Nicht bewertbar") -> Rot | O18: =IF(H18="OK",IF(IF(I18<=0,3,IF(J18>=Schwellenwerte!B9,1,IF(J18>=Schwellenwerte!B10,2,3)))=1,"Grün",IF(IF(I18<=0,3,IF(J18>=Schwellenwerte!B9,1,IF(J18>=Schwellenwerte!B10,2,3)))=2,"Gelb","Rot")),"Nicht bewertbar") -> Grün | P18: =IF(H18="OK",IF(OR(N18="Rot",O18="Rot",Berechnung!$B$27=3),"Rot",IF(OR(N18="Gelb",O18="Gelb",Berechnung!$B$27=2),"Gelb","Grün")),"Nicht bewertbar") -> Rot
A19: Betriebswasserbedarf +20 % | B19: 1 | C19: 1 | D19: 1.2 | E19: 1 | F19: 1 | G19: 0 | H19: =IFERROR(IF(AND(Prüfungen!$B$4=0,COUNT(B19:G19)=6,MIN(B19:F19)>=0,MAX(B19:F19)<=10,Eingaben!$B$39+G19>=0,Eingaben!$B$39+G19<=1),"OK","FEHLER"),"FEHLER") -> OK | I19: =IF(H19="OK",SUM(Variantenbilanz!K2933:K3298),"Nicht bewertbar") -> 577.46176 | J19: =IF(H19="OK",IFERROR(I19/(SUM(Variantenbilanz!D2933:D3298)+Eingaben!$B$12),0),"Nicht bewertbar") -> 0.21211184 | K19: =IF(H19="OK",IFERROR(I19*(Eingaben!$B$36*C19+Eingaben!$B$37*Eingaben!$B$38)-(Eingaben!$B$32+Eingaben!$B$35+SUM(Variantenbilanz!E2933:E3298)*Eingaben!$B$33*Eingaben!$B$34 )*F19,0),"Nicht bewertbar") -> 662.12739 | L19: =IF(H19="OK",SUM(VariantenCF!I413:I463),"Nicht bewertbar") -> -16819.714 | M19: =IF(H19="OK",IF(MAX(0,Berechnung!$B$13*Szenarien!$B$19-MIN(Eingaben!$B$31,Berechnung!$B$13*Szenarien!$B$19))=0,"Keine Nettoinvestition",IF(K19<=0,"Nicht erreichbar",MAX(0,Berechnung!$B$13*Szenarien!$B$19-MIN(Eingaben!$B$31,Berechnung!$B$13*Szenarien!$B$19))/K19)),"Nicht bewertbar") -> 37.757085 | N19: =IF(H19="OK",IF(IF(MAX(0,Berechnung!$B$13*Szenarien!$B$19-MIN(Eingaben!$B$31,Berechnung!$B$13*Szenarien!$B$19))=0,IF(L19>=0,1,3),IF(L19/MAX(0,Berechnung!$B$13*Szenarien!$B$19-MIN(Eingaben!$B$31,Berechnung!$B$13*Szenarien!$B$19))>=Schwellenwerte!B5,1,IF(L19/MAX(0,Berechnung!$B$13*Szenarien!$B$19-MIN(Eingaben!$B$31,Berechnung!$B$13*Szenarien!$B$19))>=Schwellenwerte!B6,2,3)))=1,"Grün",IF(IF(MAX(0,Berechnung!$B$13*Szenarien!$B$19-MIN(Eingaben!$B$31,Berechnung!$B$13*Szenarien!$B$19))=0,IF(L19>=0,1,3),IF(L19/MAX(0,Berechnung!$B$13*Szenarien!$B$19-MIN(Eingaben!$B$31,Berechnung!$B$13*Szenarien!$B$19))>=Schwellenwerte!B5,1,IF(L19/MAX(0,Berechnung!$B$13*Szenarien!$B$19-MIN(Eingaben!$B$31,Berechnung!$B$13*Szenarien!$B$19))>=Schwellenwerte!B6,2,3)))=2,"Gelb","Rot")),"Nicht bewertbar") -> Rot | O19: =IF(H19="OK",IF(IF(I19<=0,3,IF(J19>=Schwellenwerte!B9,1,IF(J19>=Schwellenwerte!B10,2,3)))=1,"Grün",IF(IF(I19<=0,3,IF(J19>=Schwellenwerte!B9,1,IF(J19>=Schwellenwerte!B10,2,3)))=2,"Gelb","Rot")),"Nicht bewertbar") -> Grün | P19: =IF(H19="OK",IF(OR(N19="Rot",O19="Rot",Berechnung!$B$27=3),"Rot",IF(OR(N19="Gelb",O19="Gelb",Berechnung!$B$27=2),"Gelb","Grün")),"Nicht bewertbar") -> Rot
A20: Grauwasseranfall −20 % | B20: 1 | C20: 1 | D20: 1 | E20: 0.8 | F20: 1 | G20: 0 | H20: =IFERROR(IF(AND(Prüfungen!$B$4=0,COUNT(B20:G20)=6,MIN(B20:F20)>=0,MAX(B20:F20)<=10,Eingaben!$B$39+G20>=0,Eingaben!$B$39+G20<=1),"OK","FEHLER"),"FEHLER") -> OK | I20: =IF(H20="OK",SUM(Variantenbilanz!K3299:K3664),"Nicht bewertbar") -> 466.38381 | J20: =IF(H20="OK",IFERROR(I20/(SUM(Variantenbilanz!D3299:D3664)+Eingaben!$B$12),0),"Nicht bewertbar") -> 0.18516846 | K20: =IF(H20="OK",IFERROR(I20*(Eingaben!$B$36*C20+Eingaben!$B$37*Eingaben!$B$38)-(Eingaben!$B$32+Eingaben!$B$35+SUM(Variantenbilanz!E3299:E3664)*Eingaben!$B$33*Eingaben!$B$34 )*F20,0),"Nicht bewertbar") -> 426.73791 | L20: =IF(H20="OK",SUM(VariantenCF!I464:I514),"Nicht bewertbar") -> -20992.391 | M20: =IF(H20="OK",IF(MAX(0,Berechnung!$B$13*Szenarien!$B$20-MIN(Eingaben!$B$31,Berechnung!$B$13*Szenarien!$B$20))=0,"Keine Nettoinvestition",IF(K20<=0,"Nicht erreichbar",MAX(0,Berechnung!$B$13*Szenarien!$B$20-MIN(Eingaben!$B$31,Berechnung!$B$13*Szenarien!$B$20))/K20)),"Nicht bewertbar") -> 58.583967 | N20: =IF(H20="OK",IF(IF(MAX(0,Berechnung!$B$13*Szenarien!$B$20-MIN(Eingaben!$B$31,Berechnung!$B$13*Szenarien!$B$20))=0,IF(L20>=0,1,3),IF(L20/MAX(0,Berechnung!$B$13*Szenarien!$B$20-MIN(Eingaben!$B$31,Berechnung!$B$13*Szenarien!$B$20))>=Schwellenwerte!B5,1,IF(L20/MAX(0,Berechnung!$B$13*Szenarien!$B$20-MIN(Eingaben!$B$31,Berechnung!$B$13*Szenarien!$B$20))>=Schwellenwerte!B6,2,3)))=1,"Grün",IF(IF(MAX(0,Berechnung!$B$13*Szenarien!$B$20-MIN(Eingaben!$B$31,Berechnung!$B$13*Szenarien!$B$20))=0,IF(L20>=0,1,3),IF(L20/MAX(0,Berechnung!$B$13*Szenarien!$B$20-MIN(Eingaben!$B$31,Berechnung!$B$13*Szenarien!$B$20))>=Schwellenwerte!B5,1,IF(L20/MAX(0,Berechnung!$B$13*Szenarien!$B$20-MIN(Eingaben!$B$31,Berechnung!$B$13*Szenarien!$B$20))>=Schwellenwerte!B6,2,3)))=2,"Gelb","Rot")),"Nicht bewertbar") -> Rot | O20: =IF(H20="OK",IF(IF(I20<=0,3,IF(J20>=Schwellenwerte!B9,1,IF(J20>=Schwellenwerte!B10,2,3)))=1,"Grün",IF(IF(I20<=0,3,IF(J20>=Schwellenwerte!B9,1,IF(J20>=Schwellenwerte!B10,2,3)))=2,"Gelb","Rot")),"Nicht bewertbar") -> Grün | P20: =IF(H20="OK",IF(OR(N20="Rot",O20="Rot",Berechnung!$B$27=3),"Rot",IF(OR(N20="Gelb",O20="Gelb",Berechnung!$B$27=2),"Gelb","Grün")),"Nicht bewertbar") -> Rot
A21: Grauwasseranfall +20 % | B21: 1 | C21: 1 | D21: 1 | E21: 1.2 | F21: 1 | G21: 0 | H21: =IFERROR(IF(AND(Prüfungen!$B$4=0,COUNT(B21:G21)=6,MIN(B21:F21)>=0,MAX(B21:F21)<=10,Eingaben!$B$39+G21>=0,Eingaben!$B$39+G21<=1),"OK","FEHLER"),"FEHLER") -> OK | I21: =IF(H21="OK",SUM(Variantenbilanz!K3665:K4030),"Nicht bewertbar") -> 641.47797 | J21: =IF(H21="OK",IFERROR(I21/(SUM(Variantenbilanz!D3665:D4030)+Eingaben!$B$12),0),"Nicht bewertbar") -> 0.25468614 | K21: =IF(H21="OK",IFERROR(I21*(Eingaben!$B$36*C21+Eingaben!$B$37*Eingaben!$B$38)-(Eingaben!$B$32+Eingaben!$B$35+SUM(Variantenbilanz!E3665:E4030)*Eingaben!$B$33*Eingaben!$B$34 )*F21,0),"Nicht bewertbar") -> 779.86254 | L21: =IF(H21="OK",SUM(VariantenCF!I515:I565),"Nicht bewertbar") -> -14732.659 | M21: =IF(H21="OK",IF(MAX(0,Berechnung!$B$13*Szenarien!$B$21-MIN(Eingaben!$B$31,Berechnung!$B$13*Szenarien!$B$21))=0,"Keine Nettoinvestition",IF(K21<=0,"Nicht erreichbar",MAX(0,Berechnung!$B$13*Szenarien!$B$21-MIN(Eingaben!$B$31,Berechnung!$B$13*Szenarien!$B$21))/K21)),"Nicht bewertbar") -> 32.056932 | N21: =IF(H21="OK",IF(IF(MAX(0,Berechnung!$B$13*Szenarien!$B$21-MIN(Eingaben!$B$31,Berechnung!$B$13*Szenarien!$B$21))=0,IF(L21>=0,1,3),IF(L21/MAX(0,Berechnung!$B$13*Szenarien!$B$21-MIN(Eingaben!$B$31,Berechnung!$B$13*Szenarien!$B$21))>=Schwellenwerte!B5,1,IF(L21/MAX(0,Berechnung!$B$13*Szenarien!$B$21-MIN(Eingaben!$B$31,Berechnung!$B$13*Szenarien!$B$21))>=Schwellenwerte!B6,2,3)))=1,"Grün",IF(IF(MAX(0,Berechnung!$B$13*Szenarien!$B$21-MIN(Eingaben!$B$31,Berechnung!$B$13*Szenarien!$B$21))=0,IF(L21>=0,1,3),IF(L21/MAX(0,Berechnung!$B$13*Szenarien!$B$21-MIN(Eingaben!$B$31,Berechnung!$B$13*Szenarien!$B$21))>=Schwellenwerte!B5,1,IF(L21/MAX(0,Berechnung!$B$13*Szenarien!$B$21-MIN(Eingaben!$B$31,Berechnung!$B$13*Szenarien!$B$21))>=Schwellenwerte!B6,2,3)))=2,"Gelb","Rot")),"Nicht bewertbar") -> Rot | O21: =IF(H21="OK",IF(IF(I21<=0,3,IF(J21>=Schwellenwerte!B9,1,IF(J21>=Schwellenwerte!B10,2,3)))=1,"Grün",IF(IF(I21<=0,3,IF(J21>=Schwellenwerte!B9,1,IF(J21>=Schwellenwerte!B10,2,3)))=2,"Gelb","Rot")),"Nicht bewertbar") -> Grün | P21: =IF(H21="OK",IF(OR(N21="Rot",O21="Rot",Berechnung!$B$27=3),"Rot",IF(OR(N21="Gelb",O21="Gelb",Berechnung!$B$27=2),"Gelb","Grün")),"Nicht bewertbar") -> Rot
A22: Betriebskosten −20 % | B22: 1 | C22: 1 | D22: 1 | E22: 1 | F22: 0.8 | G22: 0 | H22: =IFERROR(IF(AND(Prüfungen!$B$4=0,COUNT(B22:G22)=6,MIN(B22:F22)>=0,MAX(B22:F22)<=10,Eingaben!$B$39+G22>=0,Eingaben!$B$39+G22<=1),"OK","FEHLER"),"FEHLER") -> OK | I22: =IF(H22="OK",SUM(Variantenbilanz!K4031:K4396),"Nicht bewertbar") -> 555.38976 | J22: =IF(H22="OK",IFERROR(I22/(SUM(Variantenbilanz!D4031:D4396)+Eingaben!$B$12),0),"Nicht bewertbar") -> 0.22050651 | K22: =IF(H22="OK",IFERROR(I22*(Eingaben!$B$36*C22+Eingaben!$B$37*Eingaben!$B$38)-(Eingaben!$B$32+Eingaben!$B$35+SUM(Variantenbilanz!E4031:E4396)*Eingaben!$B$33*Eingaben!$B$34 )*F22,0),"Nicht bewertbar") -> 763.25279 | L22: =IF(H22="OK",SUM(VariantenCF!I566:I616),"Nicht bewertbar") -> -15027.095 | M22: =IF(H22="OK",IF(MAX(0,Berechnung!$B$13*Szenarien!$B$22-MIN(Eingaben!$B$31,Berechnung!$B$13*Szenarien!$B$22))=0,"Keine Nettoinvestition",IF(K22<=0,"Nicht erreichbar",MAX(0,Berechnung!$B$13*Szenarien!$B$22-MIN(Eingaben!$B$31,Berechnung!$B$13*Szenarien!$B$22))/K22)),"Nicht bewertbar") -> 32.754548 | N22: =IF(H22="OK",IF(IF(MAX(0,Berechnung!$B$13*Szenarien!$B$22-MIN(Eingaben!$B$31,Berechnung!$B$13*Szenarien!$B$22))=0,IF(L22>=0,1,3),IF(L22/MAX(0,Berechnung!$B$13*Szenarien!$B$22-MIN(Eingaben!$B$31,Berechnung!$B$13*Szenarien!$B$22))>=Schwellenwerte!B5,1,IF(L22/MAX(0,Berechnung!$B$13*Szenarien!$B$22-MIN(Eingaben!$B$31,Berechnung!$B$13*Szenarien!$B$22))>=Schwellenwerte!B6,2,3)))=1,"Grün",IF(IF(MAX(0,Berechnung!$B$13*Szenarien!$B$22-MIN(Eingaben!$B$31,Berechnung!$B$13*Szenarien!$B$22))=0,IF(L22>=0,1,3),IF(L22/MAX(0,Berechnung!$B$13*Szenarien!$B$22-MIN(Eingaben!$B$31,Berechnung!$B$13*Szenarien!$B$22))>=Schwellenwerte!B5,1,IF(L22/MAX(0,Berechnung!$B$13*Szenarien!$B$22-MIN(Eingaben!$B$31,Berechnung!$B$13*Szenarien!$B$22))>=Schwellenwerte!B6,2,3)))=2,"Gelb","Rot")),"Nicht bewertbar") -> Rot | O22: =IF(H22="OK",IF(IF(I22<=0,3,IF(J22>=Schwellenwerte!B9,1,IF(J22>=Schwellenwerte!B10,2,3)))=1,"Grün",IF(IF(I22<=0,3,IF(J22>=Schwellenwerte!B9,1,IF(J22>=Schwellenwerte!B10,2,3)))=2,"Gelb","Rot")),"Nicht bewertbar") -> Grün | P22: =IF(H22="OK",IF(OR(N22="Rot",O22="Rot",Berechnung!$B$27=3),"Rot",IF(OR(N22="Gelb",O22="Gelb",Berechnung!$B$27=2),"Gelb","Grün")),"Nicht bewertbar") -> Rot
A23: Betriebskosten +20 % | B23: 1 | C23: 1 | D23: 1 | E23: 1 | F23: 1.2 | G23: 0 | H23: =IFERROR(IF(AND(Prüfungen!$B$4=0,COUNT(B23:G23)=6,MIN(B23:F23)>=0,MAX(B23:F23)<=10,Eingaben!$B$39+G23>=0,Eingaben!$B$39+G23<=1),"OK","FEHLER"),"FEHLER") -> OK | I23: =IF(H23="OK",SUM(Variantenbilanz!K4397:K4762),"Nicht bewertbar") -> 555.38976 | J23: =IF(H23="OK",IFERROR(I23/(SUM(Variantenbilanz!D4397:D4762)+Eingaben!$B$12),0),"Nicht bewertbar") -> 0.22050651 | K23: =IF(H23="OK",IFERROR(I23*(Eingaben!$B$36*C23+Eingaben!$B$37*Eingaben!$B$38)-(Eingaben!$B$32+Eingaben!$B$35+SUM(Variantenbilanz!E4397:E4762)*Eingaben!$B$33*Eingaben!$B$34 )*F23,0),"Nicht bewertbar") -> 450.64199 | L23: =IF(H23="OK",SUM(VariantenCF!I617:I667),"Nicht bewertbar") -> -20568.651 | M23: =IF(H23="OK",IF(MAX(0,Berechnung!$B$13*Szenarien!$B$23-MIN(Eingaben!$B$31,Berechnung!$B$13*Szenarien!$B$23))=0,"Keine Nettoinvestition",IF(K23<=0,"Nicht erreichbar",MAX(0,Berechnung!$B$13*Szenarien!$B$23-MIN(Eingaben!$B$31,Berechnung!$B$13*Szenarien!$B$23))/K23)),"Nicht bewertbar") -> 55.47641 | N23: =IF(H23="OK",IF(IF(MAX(0,Berechnung!$B$13*Szenarien!$B$23-MIN(Eingaben!$B$31,Berechnung!$B$13*Szenarien!$B$23))=0,IF(L23>=0,1,3),IF(L23/MAX(0,Berechnung!$B$13*Szenarien!$B$23-MIN(Eingaben!$B$31,Berechnung!$B$13*Szenarien!$B$23))>=Schwellenwerte!B5,1,IF(L23/MAX(0,Berechnung!$B$13*Szenarien!$B$23-MIN(Eingaben!$B$31,Berechnung!$B$13*Szenarien!$B$23))>=Schwellenwerte!B6,2,3)))=1,"Grün",IF(IF(MAX(0,Berechnung!$B$13*Szenarien!$B$23-MIN(Eingaben!$B$31,Berechnung!$B$13*Szenarien!$B$23))=0,IF(L23>=0,1,3),IF(L23/MAX(0,Berechnung!$B$13*Szenarien!$B$23-MIN(Eingaben!$B$31,Berechnung!$B$13*Szenarien!$B$23))>=Schwellenwerte!B5,1,IF(L23/MAX(0,Berechnung!$B$13*Szenarien!$B$23-MIN(Eingaben!$B$31,Berechnung!$B$13*Szenarien!$B$23))>=Schwellenwerte!B6,2,3)))=2,"Gelb","Rot")),"Nicht bewertbar") -> Rot | O23: =IF(H23="OK",IF(IF(I23<=0,3,IF(J23>=Schwellenwerte!B9,1,IF(J23>=Schwellenwerte!B10,2,3)))=1,"Grün",IF(IF(I23<=0,3,IF(J23>=Schwellenwerte!B9,1,IF(J23>=Schwellenwerte!B10,2,3)))=2,"Gelb","Rot")),"Nicht bewertbar") -> Grün | P23: =IF(H23="OK",IF(OR(N23="Rot",O23="Rot",Berechnung!$B$27=3),"Rot",IF(OR(N23="Gelb",O23="Gelb",Berechnung!$B$27=2),"Gelb","Grün")),"Nicht bewertbar") -> Rot
A24: Kalkulationszins −1 %-Punkt | B24: 1 | C24: 1 | D24: 1 | E24: 1 | F24: 1 | G24: -0.01 | H24: =IFERROR(IF(AND(Prüfungen!$B$4=0,COUNT(B24:G24)=6,MIN(B24:F24)>=0,MAX(B24:F24)<=10,Eingaben!$B$39+G24>=0,Eingaben!$B$39+G24<=1),"OK","FEHLER"),"FEHLER") -> OK | I24: =IF(H24="OK",SUM(Variantenbilanz!K4763:K5128),"Nicht bewertbar") -> 555.38976 | J24: =IF(H24="OK",IFERROR(I24/(SUM(Variantenbilanz!D4763:D5128)+Eingaben!$B$12),0),"Nicht bewertbar") -> 0.22050651 | K24: =IF(H24="OK",IFERROR(I24*(Eingaben!$B$36*C24+Eingaben!$B$37*Eingaben!$B$38)-(Eingaben!$B$32+Eingaben!$B$35+SUM(Variantenbilanz!E4763:E5128)*Eingaben!$B$33*Eingaben!$B$34 )*F24,0),"Nicht bewertbar") -> 606.94739 | L24: =IF(H24="OK",SUM(VariantenCF!I668:I718),"Nicht bewertbar") -> -17020.639 | M24: =IF(H24="OK",IF(MAX(0,Berechnung!$B$13*Szenarien!$B$24-MIN(Eingaben!$B$31,Berechnung!$B$13*Szenarien!$B$24))=0,"Keine Nettoinvestition",IF(K24<=0,"Nicht erreichbar",MAX(0,Berechnung!$B$13*Szenarien!$B$24-MIN(Eingaben!$B$31,Berechnung!$B$13*Szenarien!$B$24))/K24)),"Nicht bewertbar") -> 41.189731 | N24: =IF(H24="OK",IF(IF(MAX(0,Berechnung!$B$13*Szenarien!$B$24-MIN(Eingaben!$B$31,Berechnung!$B$13*Szenarien!$B$24))=0,IF(L24>=0,1,3),IF(L24/MAX(0,Berechnung!$B$13*Szenarien!$B$24-MIN(Eingaben!$B$31,Berechnung!$B$13*Szenarien!$B$24))>=Schwellenwerte!B5,1,IF(L24/MAX(0,Berechnung!$B$13*Szenarien!$B$24-MIN(Eingaben!$B$31,Berechnung!$B$13*Szenarien!$B$24))>=Schwellenwerte!B6,2,3)))=1,"Grün",IF(IF(MAX(0,Berechnung!$B$13*Szenarien!$B$24-MIN(Eingaben!$B$31,Berechnung!$B$13*Szenarien!$B$24))=0,IF(L24>=0,1,3),IF(L24/MAX(0,Berechnung!$B$13*Szenarien!$B$24-MIN(Eingaben!$B$31,Berechnung!$B$13*Szenarien!$B$24))>=Schwellenwerte!B5,1,IF(L24/MAX(0,Berechnung!$B$13*Szenarien!$B$24-MIN(Eingaben!$B$31,Berechnung!$B$13*Szenarien!$B$24))>=Schwellenwerte!B6,2,3)))=2,"Gelb","Rot")),"Nicht bewertbar") -> Rot | O24: =IF(H24="OK",IF(IF(I24<=0,3,IF(J24>=Schwellenwerte!B9,1,IF(J24>=Schwellenwerte!B10,2,3)))=1,"Grün",IF(IF(I24<=0,3,IF(J24>=Schwellenwerte!B9,1,IF(J24>=Schwellenwerte!B10,2,3)))=2,"Gelb","Rot")),"Nicht bewertbar") -> Grün | P24: =IF(H24="OK",IF(OR(N24="Rot",O24="Rot",Berechnung!$B$27=3),"Rot",IF(OR(N24="Gelb",O24="Gelb",Berechnung!$B$27=2),"Gelb","Grün")),"Nicht bewertbar") -> Rot
A25: Kalkulationszins +1 %-Punkt | B25: 1 | C25: 1 | D25: 1 | E25: 1 | F25: 1 | G25: 0.01 | H25: =IFERROR(IF(AND(Prüfungen!$B$4=0,COUNT(B25:G25)=6,MIN(B25:F25)>=0,MAX(B25:F25)<=10,Eingaben!$B$39+G25>=0,Eingaben!$B$39+G25<=1),"OK","FEHLER"),"FEHLER") -> OK | I25: =IF(H25="OK",SUM(Variantenbilanz!K5129:K5494),"Nicht bewertbar") -> 555.38976 | J25: =IF(H25="OK",IFERROR(I25/(SUM(Variantenbilanz!D5129:D5494)+Eingaben!$B$12),0),"Nicht bewertbar") -> 0.22050651 | K25: =IF(H25="OK",IFERROR(I25*(Eingaben!$B$36*C25+Eingaben!$B$37*Eingaben!$B$38)-(Eingaben!$B$32+Eingaben!$B$35+SUM(Variantenbilanz!E5129:E5494)*Eingaben!$B$33*Eingaben!$B$34 )*F25,0),"Nicht bewertbar") -> 606.94739 | L25: =IF(H25="OK",SUM(VariantenCF!I719:I769),"Nicht bewertbar") -> -18462.662 | M25: =IF(H25="OK",IF(MAX(0,Berechnung!$B$13*Szenarien!$B$25-MIN(Eingaben!$B$31,Berechnung!$B$13*Szenarien!$B$25))=0,"Keine Nettoinvestition",IF(K25<=0,"Nicht erreichbar",MAX(0,Berechnung!$B$13*Szenarien!$B$25-MIN(Eingaben!$B$31,Berechnung!$B$13*Szenarien!$B$25))/K25)),"Nicht bewertbar") -> 41.189731 | N25: =IF(H25="OK",IF(IF(MAX(0,Berechnung!$B$13*Szenarien!$B$25-MIN(Eingaben!$B$31,Berechnung!$B$13*Szenarien!$B$25))=0,IF(L25>=0,1,3),IF(L25/MAX(0,Berechnung!$B$13*Szenarien!$B$25-MIN(Eingaben!$B$31,Berechnung!$B$13*Szenarien!$B$25))>=Schwellenwerte!B5,1,IF(L25/MAX(0,Berechnung!$B$13*Szenarien!$B$25-MIN(Eingaben!$B$31,Berechnung!$B$13*Szenarien!$B$25))>=Schwellenwerte!B6,2,3)))=1,"Grün",IF(IF(MAX(0,Berechnung!$B$13*Szenarien!$B$25-MIN(Eingaben!$B$31,Berechnung!$B$13*Szenarien!$B$25))=0,IF(L25>=0,1,3),IF(L25/MAX(0,Berechnung!$B$13*Szenarien!$B$25-MIN(Eingaben!$B$31,Berechnung!$B$13*Szenarien!$B$25))>=Schwellenwerte!B5,1,IF(L25/MAX(0,Berechnung!$B$13*Szenarien!$B$25-MIN(Eingaben!$B$31,Berechnung!$B$13*Szenarien!$B$25))>=Schwellenwerte!B6,2,3)))=2,"Gelb","Rot")),"Nicht bewertbar") -> Rot | O25: =IF(H25="OK",IF(IF(I25<=0,3,IF(J25>=Schwellenwerte!B9,1,IF(J25>=Schwellenwerte!B10,2,3)))=1,"Grün",IF(IF(I25<=0,3,IF(J25>=Schwellenwerte!B9,1,IF(J25>=Schwellenwerte!B10,2,3)))=2,"Gelb","Rot")),"Nicht bewertbar") -> Grün | P25: =IF(H25="OK",IF(OR(N25="Rot",O25="Rot",Berechnung!$B$27=3),"Rot",IF(OR(N25="Gelb",O25="Gelb",Berechnung!$B$27=2),"Gelb","Grün")),"Nicht bewertbar") -> Rot
A27: Keine Wahrscheinlichkeiten: Konservativ / Optimistisch sind Modellvarianten, keine Prognose oder statistische Unsicherheit.
A28: Andere Trinkwasser-Baseline außerhalb Betriebsbedarf bleibt konstant; Förderung absolut, Ersatzkosten/Restwert skaliert mit Investition.

Sheet Variantenbilanz
A1: Tagesbilanzen aller Varianten
A2: Dashboard | B2: Eingaben | C2: Profile | D2: Kalender | E2: Methodik
A3: Berechnung, keine Eingaben. Je Variante 366 Tageszeilen; gleiche Kalender- und Speicherregeln wie im Basismodell.
A4: Variante | B4: Tag | C4: Rohmenge | D4: Bedarf | E4: Verarbeitet | F4: Aufbereitet | G4: Alt nach Verlust | H4: Altverbrauch | I4: Direktverbrauch | J4: Endbestand | K4: Nutzung | L4: Nachspeisung | M4: Überschuss | N4: Speicherverluste
A5: ="Konservativ" -> Konservativ | B5: =1 -> 1 | C5: =IF(Szenarien!$H$8="OK",(IFERROR(SUMIF(Nutzungsprofile!$B$6:$B$11,"Schulbetrieb",Nutzungsprofile!$G$6:$G$11)*Kalender!C5/SUM(Kalender!$C$5:$C$370),0)+IFERROR(SUMIF(Nutzungsprofile!$B$6:$B$11,"Halle",Nutzungsprofile!$G$6:$G$11)*Kalender!D5/SUM(Kalender!$D$5:$D$370),0)+IFERROR(SUMIF(Nutzungsprofile!$B$6:$B$11,"Individuell",Nutzungsprofile!$G$6:$G$11)*Kalender!E5/SUM(Kalender!$E$5:$E$370),0))*Szenarien!$E$8,0) -> 2.352 | D5: =IF(Szenarien!$H$8="OK",(IFERROR(SUMIF(Nutzungsprofile!$B$17:$B$22,"Schulbetrieb",Nutzungsprofile!$G$17:$G$22)*Kalender!C5/SUM(Kalender!$C$5:$C$370),0)+IFERROR(SUMIF(Nutzungsprofile!$B$17:$B$22,"Halle",Nutzungsprofile!$G$17:$G$22)*Kalender!D5/SUM(Kalender!$D$5:$D$370),0)+IFERROR(SUMIF(Nutzungsprofile!$B$17:$B$22,"Individuell",Nutzungsprofile!$G$17:$G$22)*Kalender!E5/SUM(Kalender!$E$5:$E$370),0))*Szenarien!$D$8,0) -> 4.446 | E5: =IFERROR(MIN(C5,Eingaben!$B$17)*Eingaben!$B$16,0) -> 2.2344 | F5: =IFERROR(E5*Eingaben!$B$15,0) -> 2.01096 | G5: =0 -> 0 | H5: =MIN(G5,D5) -> 0 | I5: =IFERROR(MIN(F5*Eingaben!$B$19,MAX(0,D5-H5)),0) -> 1.407672 | J5: =IFERROR(MIN(Eingaben!$B$18,MAX(0,F5-I5)),0) -> 0.603288 | K5: =H5+I5 -> 1.407672 | L5: =MAX(0,D5-K5) -> 3.038328 | M5: =MAX(0,F5-I5-J5) -> 0 | N5: =0 -> 0
A6: ="" | B6: =2 -> 2 | C6: =IF(Szenarien!$H$8="OK",(IFERROR(SUMIF(Nutzungsprofile!$B$6:$B$11,"Schulbetrieb",Nutzungsprofile!$G$6:$G$11)*Kalender!C6/SUM(Kalender!$C$5:$C$370),0)+IFERROR(SUMIF(Nutzungsprofile!$B$6:$B$11,"Halle",Nutzungsprofile!$G$6:$G$11)*Kalender!D6/SUM(Kalender!$D$5:$D$370),0)+IFERROR(SUMIF(Nutzungsprofile!$B$6:$B$11,"Individuell",Nutzungsprofile!$G$6:$G$11)*Kalender!E6/SUM(Kalender!$E$5:$E$370),0))*Szenarien!$E$8,0) -> 2.352 | D6: =IF(Szenarien!$H$8="OK",(IFERROR(SUMIF(Nutzungsprofile!$B$17:$B$22,"Schulbetrieb",Nutzungsprofile!$G$17:$G$22)*Kalender!C6/SUM(Kalender!$C$5:$C$370),0)+IFERROR(SUMIF(Nutzungsprofile!$B$17:$B$22,"Halle",Nutzungsprofile!$G$17:$G$22)*Kalender!D6/SUM(Kalender!$D$5:$D$370),0)+IFERROR(SUMIF(Nutzungsprofile!$B$17:$B$22,"Individuell",Nutzungsprofile!$G$17:$G$22)*Kalender!E6/SUM(Kalender!$E$5:$E$370),0))*Szenarien!$D$8,0) -> 4.446 | E6: =IFERROR(MIN(C6,Eingaben!$B$17)*Eingaben!$B$16,0) -> 2.2344 | F6: =IFERROR(E6*Eingaben!$B$15,0) -> 2.01096 | G6: =IFERROR(IF(Kalender!A6="",0,J5*(1-Eingaben!$B$20)),0) -> 0.59122224 | H6: =MIN(G6,D6) -> 0.59122224 | I6: =IFERROR(MIN(F6*Eingaben!$B$19,MAX(0,D6-H6)),0) -> 1.407672 | J6: =IFERROR(MIN(Eingaben!$B$18,MAX(0,F6-I6)),0) -> 0.603288 | K6: =H6+I6 -> 1.9988942 | L6: =MAX(0,D6-K6) -> 2.4471058 | M6: =MAX(0,F6-I6-J6) -> 0 | N6: =IF(Kalender!A6="",0,J5-H6) -> 0.01206576
A7: ="" | B7: =3 -> 3 | C7: =IF(Szenarien!$H$8="OK",(IFERROR(SUMIF(Nutzungsprofile!$B$6:$B$11,"Schulbetrieb",Nutzungsprofile!$G$6:$G$11)*Kalender!C7/SUM(Kalender!$C$5:$C$370),0)+IFERROR(SUMIF(Nutzungsprofile!$B$6:$B$11,"Halle",Nutzungsprofile!$G$6:$G$11)*Kalender!D7/SUM(Kalender!$D$5:$D$370),0)+IFERROR(SUMIF(Nutzungsprofile!$B$6:$B$11,"Individuell",Nutzungsprofile!$G$6:$G$11)*Kalender!E7/SUM(Kalender!$E$5:$E$370),0))*Szenarien!$E$8,0) -> 1.632 | D7: =IF(Szenarien!$H$8="OK",(IFERROR(SUMIF(Nutzungsprofile!$B$17:$B$22,"Schulbetrieb",Nutzungsprofile!$G$17:$G$22)*Kalender!C7/SUM(Kalender!$C$5:$C$370),0)+IFERROR(SUMIF(Nutzungsprofile!$B$17:$B$22,"Halle",Nutzungsprofile!$G$17:$G$22)*Kalender!D7/SUM(Kalender!$D$5:$D$370),0)+IFERROR(SUMIF(Nutzungsprofile!$B$17:$B$22,"Individuell",Nutzungsprofile!$G$17:$G$22)*Kalender!E7/SUM(Kalender!$E$5:$E$370),0))*Szenarien!$D$8,0) -> 0.801 | E7: =IFERROR(MIN(C7,Eingaben!$B$17)*Eingaben!$B$16,0) -> 1.5504 | F7: =IFERROR(E7*Eingaben!$B$15,0) -> 1.39536 | G7: =IFERROR(IF(Kalender!A7="",0,J6*(1-Eingaben!$B$20)),0) -> 0.59122224 | H7: =MIN(G7,D7) -> 0.59122224 | I7: =IFERROR(MIN(F7*Eingaben!$B$19,MAX(0,D7-H7)),0) -> 0.20977776 | J7: =IFERROR(MIN(Eingaben!$B$18,MAX(0,F7-I7)),0) -> 1.1855822 | K7: =H7+I7 -> 0.801 | L7: =MAX(0,D7-K7) -> 0 | M7: =MAX(0,F7-I7-J7) -> 0 | N7: =IF(Kalender!A7="",0,J6-H7) -> 0.01206576
A8: ="" | B8: =4 -> 4 | C8: =IF(Szenarien!$H$8="OK",(IFERROR(SUMIF(Nutzungsprofile!$B$6:$B$11,"Schulbetrieb",Nutzungsprofile!$G$6:$G$11)*Kalender!C8/SUM(Kalender!$C$5:$C$370),0)+IFERROR(SUMIF(Nutzungsprofile!$B$6:$B$11,"Halle",Nutzungsprofile!$G$6:$G$11)*Kalender!D8/SUM(Kalender!$D$5:$D$370),0)+IFERROR(SUMIF(Nutzungsprofile!$B$6:$B$11,"Individuell",Nutzungsprofile!$G$6:$G$11)*Kalender!E8/SUM(Kalender!$E$5:$E$370),0))*Szenarien!$E$8,0) -> 1.632 | D8: =IF(Szenarien!$H$8="OK",(IFERROR(SUMIF(Nutzungsprofile!$B$17:$B$22,"Schulbetrieb",Nutzungsprofile!$G$17:$G$22)*Kalender!C8/SUM(Kalender!$C$5:$C$370),0)+IFERROR(SUMIF(Nutzungsprofile!$B$17:$B$22,"Halle",Nutzungsprofile!$G$17:$G$22)*Kalender!D8/SUM(Kalender!$D$5:$D$370),0)+IFERROR(SUMIF(Nutzungsprofile!$B$17:$B$22,"Individuell",Nutzungsprofile!$G$17:$G$22)*Kalender!E8/SUM(Kalender!$E$5:$E$370),0))*Szenarien!$D$8,0) -> 0.801 | E8: =IFERROR(MIN(C8,Eingaben!$B$17)*Eingaben!$B$16,0) -> 1.5504 | F8: =IFERROR(E8*Eingaben!$B$15,0) -> 1.39536 | G8: =IFERROR(IF(Kalender!A8="",0,J7*(1-Eingaben!$B$20)),0) -> 1.1618706 | H8: =MIN(G8,D8) -> 0.801 | I8: =IFERROR(MIN(F8*Eingaben!$B$19,MAX(0,D8-H8)),0) -> 0 | J8: =IFERROR(MIN(Eingaben!$B$18,MAX(0,F8-I8)),0) -> 1.39536 | K8: =H8+I8 -> 0.801 | L8: =MAX(0,D8-K8) -> 0 | M8: =MAX(0,F8-I8-J8) -> 0 | N8: =IF(Kalender!A8="",0,J7-H8) -> 0.38458224
A9: ="" | B9: =5 -> 5 | C9: =IF(Szenarien!$H$8="OK",(IFERROR(SUMIF(Nutzungsprofile!$B$6:$B$11,"Schulbetrieb",Nutzungsprofile!$G$6:$G$11)*Kalender!C9/SUM(Kalender!$C$5:$C$370),0)+IFERROR(SUMIF(Nutzungsprofile!$B$6:$B$11,"Halle",Nutzungsprofile!$G$6:$G$11)*Kalender!D9/SUM(Kalender!$D$5:$D$370),0)+IFERROR(SUMIF(Nutzungsprofile!$B$6:$B$11,"Individuell",Nutzungsprofile!$G$6:$G$11)*Kalender!E9/SUM(Kalender!$E$5:$E$370),0))*Szenarien!$E$8,0) -> 2.352 | D9: =IF(Szenarien!$H$8="OK",(IFERROR(SUMIF(Nutzungsprofile!$B$17:$B$22,"Schulbetrieb",Nutzungsprofile!$G$17:$G$22)*Kalender!C9/SUM(Kalender!$C$5:$C$370),0)+IFERROR(SUMIF(Nutzungsprofile!$B$17:$B$22,"Halle",Nutzungsprofile!$G$17:$G$22)*Kalender!D9/SUM(Kalender!$D$5:$D$370),0)+IFERROR(SUMIF(Nutzungsprofile!$B$17:$B$22,"Individuell",Nutzungsprofile!$G$17:$G$22)*Kalender!E9/SUM(Kalender!$E$5:$E$370),0))*Szenarien!$D$8,0) -> 4.446 | E9: =IFERROR(MIN(C9,Eingaben!$B$17)*Eingaben!$B$16,0) -> 2.2344 | F9: =IFERROR(E9*Eingaben!$B$15,0) -> 2.01096 | G9: =IFERROR(IF(Kalender!A9="",0,J8*(1-Eingaben!$B$20)),0) -> 1.3674528 | H9: =MIN(G9,D9) -> 1.3674528 | I9: =IFERROR(MIN(F9*Eingaben!$B$19,MAX(0,D9-H9)),0) -> 1.407672 | J9: =IFERROR(MIN(Eingaben!$B$18,MAX(0,F9-I9)),0) -> 0.603288 | K9: =H9+I9 -> 2.7751248 | L9: =MAX(0,D9-K9) -> 1.6708752 | M9: =MAX(0,F9-I9-J9) -> 0 | N9: =IF(Kalender!A9="",0,J8-H9) -> 0.0279072
A10: ="" | B10: =6 -> 6 | C10: =IF(Szenarien!$H$8="OK",(IFERROR(SUMIF(Nutzungsprofile!$B$6:$B$11,"Schulbetrieb",Nutzungsprofile!$G$6:$G$11)*Kalender!C10/SUM(Kalender!$C$5:$C$370),0)+IFERROR(SUMIF(Nutzungsprofile!$B$6:$B$11,"Halle",Nutzungsprofile!$G$6:$G$11)*Kalender!D10/SUM(Kalender!$D$5:$D$370),0)+IFERROR(SUMIF(Nutzungsprofile!$B$6:$B$11,"Individuell",Nutzungsprofile!$G$6:$G$11)*Kalender!E10/SUM(Kalender!$E$5:$E$370),0))*Szenarien!$E$8,0) -> 2.352 | D10: =IF(Szenarien!$H$8="OK",(IFERROR(SUMIF(Nutzungsprofile!$B$17:$B$22,"Schulbetrieb",Nutzungsprofile!$G$17:$G$22)*Kalender!C10/SUM(Kalender!$C$5:$C$370),0)+IFERROR(SUMIF(Nutzungsprofile!$B$17:$B$22,"Halle",Nutzungsprofile!$G$17:$G$22)*Kalender!D10/SUM(Kalender!$D$5:$D$370),0)+IFERROR(SUMIF(Nutzungsprofile!$B$17:$B$22,"Individuell",Nutzungsprofile!$G$17:$G$22)*Kalender!E10/SUM(Kalender!$E$5:$E$370),0))*Szenarien!$D$8,0) -> 4.446 | E10: =IFERROR(MIN(C10,Eingaben!$B$17)*Eingaben!$B$16,0) -> 2.2344 | F10: =IFERROR(E10*Eingaben!$B$15,0) -> 2.01096 | G10: =IFERROR(IF(Kalender!A10="",0,J9*(1-Eingaben!$B$20)),0) -> 0.59122224 | H10: =MIN(G10,D10) -> 0.59122224 | I10: =IFERROR(MIN(F10*Eingaben!$B$19,MAX(0,D10-H10)),0) -> 1.407672 | J10: =IFERROR(MIN(Eingaben!$B$18,MAX(0,F10-I10)),0) -> 0.603288 | K10: =H10+I10 -> 1.9988942 | L10: =MAX(0,D10-K10) -> 2.4471058 | M10: =MAX(0,F10-I10-J10) -> 0 | N10: =IF(Kalender!A10="",0,J9-H10) -> 0.01206576
A11: ="" | B11: =7 -> 7 | C11: =IF(Szenarien!$H$8="OK",(IFERROR(SUMIF(Nutzungsprofile!$B$6:$B$11,"Schulbetrieb",Nutzungsprofile!$G$6:$G$11)*Kalender!C11/SUM(Kalender!$C$5:$C$370),0)+IFERROR(SUMIF(Nutzungsprofile!$B$6:$B$11,"Halle",Nutzungsprofile!$G$6:$G$11)*Kalender!D11/SUM(Kalender!$D$5:$D$370),0)+IFERROR(SUMIF(Nutzungsprofile!$B$6:$B$11,"Individuell",Nutzungsprofile!$G$6:$G$11)*Kalender!E11/SUM(Kalender!$E$5:$E$370),0))*Szenarien!$E$8,0) -> 2.352 | D11: =IF(Szenarien!$H$8="OK",(IFERROR(SUMIF(Nutzungsprofile!$B$17:$B$22,"Schulbetrieb",Nutzungsprofile!$G$17:$G$22)*Kalender!C11/SUM(Kalender!$C$5:$C$370),0)+IFERROR(SUMIF(Nutzungsprofile!$B$17:$B$22,"Halle",Nutzungsprofile!$G$17:$G$22)*Kalender!D11/SUM(Kalender!$D$5:$D$370),0)+IFERROR(SUMIF(Nutzungsprofile!$B$17:$B$22,"Individuell",Nutzungsprofile!$G$17:$G$22)*Kalender!E11/SUM(Kalender!$E$5:$E$370),0))*Szenarien!$D$8,0) -> 4.446 | E11: =IFERROR(MIN(C11,Eingaben!$B$17)*Eingaben!$B$16,0) -> 2.2344 | F11: =IFERROR(E11*Eingaben!$B$15,0) -> 2.01096 | G11: =IFERROR(IF(Kalender!A11="",0,J10*(1-Eingaben!$B$20)),0) -> 0.59122224 | H11: =MIN(G11,D11) -> 0.59122224 | I11: =IFERROR(MIN(F11*Eingaben!$B$19,MAX(0,D11-H11)),0) -> 1.407672 | J11: =IFERROR(MIN(Eingaben!$B$18,MAX(0,F11-I11)),0) -> 0.603288 | K11: =H11+I11 -> 1.9988942 | L11: =MAX(0,D11-K11) -> 2.4471058 | M11: =MAX(0,F11-I11-J11) -> 0 | N11: =IF(Kalender!A11="",0,J10-H11) -> 0.01206576
A12: ="" | B12: =8 -> 8 | C12: =IF(Szenarien!$H$8="OK",(IFERROR(SUMIF(Nutzungsprofile!$B$6:$B$11,"Schulbetrieb",Nutzungsprofile!$G$6:$G$11)*Kalender!C12/SUM(Kalender!$C$5:$C$370),0)+IFERROR(SUMIF(Nutzungsprofile!$B$6:$B$11,"Halle",Nutzungsprofile!$G$6:$G$11)*Kalender!D12/SUM(Kalender!$D$5:$D$370),0)+IFERROR(SUMIF(Nutzungsprofile!$B$6:$B$11,"Individuell",Nutzungsprofile!$G$6:$G$11)*Kalender!E12/SUM(Kalender!$E$5:$E$370),0))*Szenarien!$E$8,0) -> 2.352 | D12: =IF(Szenarien!$H$8="OK",(IFERROR(SUMIF(Nutzungsprofile!$B$17:$B$22,"Schulbetrieb",Nutzungsprofile!$G$17:$G$22)*Kalender!C12/SUM(Kalender!$C$5:$C$370),0)+IFERROR(SUMIF(Nutzungsprofile!$B$17:$B$22,"Halle",Nutzungsprofile!$G$17:$G$22)*Kalender!D12/SUM(Kalender!$D$5:$D$370),0)+IFERROR(SUMIF(Nutzungsprofile!$B$17:$B$22,"Individuell",Nutzungsprofile!$G$17:$G$22)*Kalender!E12/SUM(Kalender!$E$5:$E$370),0))*Szenarien!$D$8,0) -> 4.446 | E12: =IFERROR(MIN(C12,Eingaben!$B$17)*Eingaben!$B$16,0) -> 2.2344 | F12: =IFERROR(E12*Eingaben!$B$15,0) -> 2.01096 | G12: =IFERROR(IF(Kalender!A12="",0,J11*(1-Eingaben!$B$20)),0) -> 0.59122224 | H12: =MIN(G12,D12) -> 0.59122224 | I12: =IFERROR(MIN(F12*Eingaben!$B$19,MAX(0,D12-H12)),0) -> 1.407672 | J12: =IFERROR(MIN(Eingaben!$B$18,MAX(0,F12-I12)),0) -> 0.603288 | K12: =H12+I12 -> 1.9988942 | L12: =MAX(0,D12-K12) -> 2.4471058 | M12: =MAX(0,F12-I12-J12) -> 0 | N12: =IF(Kalender!A12="",0,J11-H12) -> 0.01206576
A13: ="" | B13: =9 -> 9 | C13: =IF(Szenarien!$H$8="OK",(IFERROR(SUMIF(Nutzungsprofile!$B$6:$B$11,"Schulbetrieb",Nutzungsprofile!$G$6:$G$11)*Kalender!C13/SUM(Kalender!$C$5:$C$370),0)+IFERROR(SUMIF(Nutzungsprofile!$B$6:$B$11,"Halle",Nutzungsprofile!$G$6:$G$11)*Kalender!D13/SUM(Kalender!$D$5:$D$370),0)+IFERROR(SUMIF(Nutzungsprofile!$B$6:$B$11,"Individuell",Nutzungsprofile!$G$6:$G$11)*Kalender!E13/SUM(Kalender!$E$5:$E$370),0))*Szenarien!$E$8,0) -> 2.352 | D13: =IF(Szenarien!$H$8="OK",(IFERROR(SUMIF(Nutzungsprofile!$B$17:$B$22,"Schulbetrieb",Nutzungsprofile!$G$17:$G$22)*Kalender!C13/SUM(Kalender!$C$5:$C$370),0)+IFERROR(SUMIF(Nutzungsprofile!$B$17:$B$22,"Halle",Nutzungsprofile!$G$17:$G$22)*Kalender!D13/SUM(Kalender!$D$5:$D$370),0)+IFERROR(SUMIF(Nutzungsprofile!$B$17:$B$22,"Individuell",Nutzungsprofile!$G$17:$G$22)*Kalender!E13/SUM(Kalender!$E$5:$E$370),0))*Szenarien!$D$8,0) -> 4.446 | E13: =IFERROR(MIN(C13,Eingaben!$B$17)*Eingaben!$B$16,0) -> 2.2344 | F13: =IFERROR(E13*Eingaben!$B$15,0) -> 2.01096 | G13: =IFERROR(IF(Kalender!A13="",0,J12*(1-Eingaben!$B$20)),0) -> 0.59122224 | H13: =MIN(G13,D13) -> 0.59122224 | I13: =IFERROR(MIN(F13*Eingaben!$B$19,MAX(0,D13-H13)),0) -> 1.407672 | J13: =IFERROR(MIN(Eingaben!$B$18,MAX(0,F13-I13)),0) -> 0.603288 | K13: =H13+I13 -> 1.9988942 | L13: =MAX(0,D13-K13) -> 2.4471058 | M13: =MAX(0,F13-I13-J13) -> 0 | N13: =IF(Kalender!A13="",0,J12-H13) -> 0.01206576
A14: ="" | B14: =10 -> 10 | C14: =IF(Szenarien!$H$8="OK",(IFERROR(SUMIF(Nutzungsprofile!$B$6:$B$11,"Schulbetrieb",Nutzungsprofile!$G$6:$G$11)*Kalender!C14/SUM(Kalender!$C$5:$C$370),0)+IFERROR(SUMIF(Nutzungsprofile!$B$6:$B$11,"Halle",Nutzungsprofile!$G$6:$G$11)*Kalender!D14/SUM(Kalender!$D$5:$D$370),0)+IFERROR(SUMIF(Nutzungsprofile!$B$6:$B$11,"Individuell",Nutzungsprofile!$G$6:$G$11)*Kalender!E14/SUM(Kalender!$E$5:$E$370),0))*Szenarien!$E$8,0) -> 1.632 | D14: =IF(Szenarien!$H$8="OK",(IFERROR(SUMIF(Nutzungsprofile!$B$17:$B$22,"Schulbetrieb",Nutzungsprofile!$G$17:$G$22)*Kalender!C14/SUM(Kalender!$C$5:$C$370),0)+IFERROR(SUMIF(Nutzungsprofile!$B$17:$B$22,"Halle",Nutzungsprofile!$G$17:$G$22)*Kalender!D14/SUM(Kalender!$D$5:$D$370),0)+IFERROR(SUMIF(Nutzungsprofile!$B$17:$B$22,"Individuell",Nutzungsprofile!$G$17:$G$22)*Kalender!E14/SUM(Kalender!$E$5:$E$370),0))*Szenarien!$D$8,0) -> 0.801 | E14: =IFERROR(MIN(C14,Eingaben!$B$17)*Eingaben!$B$16,0) -> 1.5504 | F14: =IFERROR(E14*Eingaben!$B$15,0) -> 1.39536 | G14: =IFERROR(IF(Kalender!A14="",0,J13*(1-Eingaben!$B$20)),0) -> 0.59122224 | H14: =MIN(G14,D14) -> 0.59122224 | I14: =IFERROR(MIN(F14*Eingaben!$B$19,MAX(0,D14-H14)),0) -> 0.20977776 | J14: =IFERROR(MIN(Eingaben!$B$18,MAX(0,F14-I14)),0) -> 1.1855822 | K14: =H14+I14 -> 0.801 | L14: =MAX(0,D14-K14) -> 0 | M14: =MAX(0,F14-I14-J14) -> 0 | N14: =IF(Kalender!A14="",0,J13-H14) -> 0.01206576
A15: ="" | B15: =11 -> 11 | C15: =IF(Szenarien!$H$8="OK",(IFERROR(SUMIF(Nutzungsprofile!$B$6:$B$11,"Schulbetrieb",Nutzungsprofile!$G$6:$G$11)*Kalender!C15/SUM(Kalender!$C$5:$C$370),0)+IFERROR(SUMIF(Nutzungsprofile!$B$6:$B$11,"Halle",Nutzungsprofile!$G$6:$G$11)*Kalender!D15/SUM(Kalender!$D$5:$D$370),0)+IFERROR(SUMIF(Nutzungsprofile!$B$6:$B$11,"Individuell",Nutzungsprofile!$G$6:$G$11)*Kalender!E15/SUM(Kalender!$E$5:$E$370),0))*Szenarien!$E$8,0) -> 1.632 | D15: =IF(Szenarien!$H$8="OK",(IFERROR(SUMIF(Nutzungsprofile!$B$17:$B$22,"Schulbetrieb",Nutzungsprofile!$G$17:$G$22)*Kalender!C15/SUM(Kalender!$C$5:$C$370),0)+IFERROR(SUMIF(Nutzungsprofile!$B$17:$B$22,"Halle",Nutzungsprofile!$G$17:$G$22)*Kalender!D15/SUM(Kalender!$D$5:$D$370),0)+IFERROR(SUMIF(Nutzungsprofile!$B$17:$B$22,"Individuell",Nutzungsprofile!$G$17:$G$22)*Kalender!E15/SUM(Kalender!$E$5:$E$370),0))*Szenarien!$D$8,0) -> 0.801 | E15: =IFERROR(MIN(C15,Eingaben!$B$17)*Eingaben!$B$16,0) -> 1.5504 | F15: =IFERROR(E15*Eingaben!$B$15,0) -> 1.39536 | G15: =IFERROR(IF(Kalender!A15="",0,J14*(1-Eingaben!$B$20)),0) -> 1.1618706 | H15: =MIN(G15,D15) -> 0.801 | I15: =IFERROR(MIN(F15*Eingaben!$B$19,MAX(0,D15-H15)),0) -> 0 | J15: =IFERROR(MIN(Eingaben!$B$18,MAX(0,F15-I15)),0) -> 1.39536 | K15: =H15+I15 -> 0.801 | L15: =MAX(0,D15-K15) -> 0 | M15: =MAX(0,F15-I15-J15) -> 0 | N15: =IF(Kalender!A15="",0,J14-H15) -> 0.38458224
A16: ="" | B16: =12 -> 12 | C16: =IF(Szenarien!$H$8="OK",(IFERROR(SUMIF(Nutzungsprofile!$B$6:$B$11,"Schulbetrieb",Nutzungsprofile!$G$6:$G$11)*Kalender!C16/SUM(Kalender!$C$5:$C$370),0)+IFERROR(SUMIF(Nutzungsprofile!$B$6:$B$11,"Halle",Nutzungsprofile!$G$6:$G$11)*Kalender!D16/SUM(Kalender!$D$5:$D$370),0)+IFERROR(SUMIF(Nutzungsprofile!$B$6:$B$11,"Individuell",Nutzungsprofile!$G$6:$G$11)*Kalender!E16/SUM(Kalender!$E$5:$E$370),0))*Szenarien!$E$8,0) -> 2.352 | D16: =IF(Szenarien!$H$8="OK",(IFERROR(SUMIF(Nutzungsprofile!$B$17:$B$22,"Schulbetrieb",Nutzungsprofile!$G$17:$G$22)*Kalender!C16/SUM(Kalender!$C$5:$C$370),0)+IFERROR(SUMIF(Nutzungsprofile!$B$17:$B$22,"Halle",Nutzungsprofile!$G$17:$G$22)*Kalender!D16/SUM(Kalender!$D$5:$D$370),0)+IFERROR(SUMIF(Nutzungsprofile!$B$17:$B$22,"Individuell",Nutzungsprofile!$G$17:$G$22)*Kalender!E16/SUM(Kalender!$E$5:$E$370),0))*Szenarien!$D$8,0) -> 4.446 | E16: =IFERROR(MIN(C16,Eingaben!$B$17)*Eingaben!$B$16,0) -> 2.2344 | F16: =IFERROR(E16*Eingaben!$B$15,0) -> 2.01096 | G16: =IFERROR(IF(Kalender!A16="",0,J15*(1-Eingaben!$B$20)),0) -> 1.3674528 | H16: =MIN(G16,D16) -> 1.3674528 | I16: =IFERROR(MIN(F16*Eingaben!$B$19,MAX(0,D16-H16)),0) -> 1.407672 | J16: =IFERROR(MIN(Eingaben!$B$18,MAX(0,F16-I16)),0) -> 0.603288 | K16: =H16+I16 -> 2.7751248 | L16: =MAX(0,D16-K16) -> 1.6708752 | M16: =MAX(0,F16-I16-J16) -> 0 | N16: =IF(Kalender!A16="",0,J15-H16) -> 0.0279072
A17: ="" | B17: =13 -> 13 | C17: =IF(Szenarien!$H$8="OK",(IFERROR(SUMIF(Nutzungsprofile!$B$6:$B$11,"Schulbetrieb",Nutzungsprofile!$G$6:$G$11)*Kalender!C17/SUM(Kalender!$C$5:$C$370),0)+IFERROR(SUMIF(Nutzungsprofile!$B$6:$B$11,"Halle",Nutzungsprofile!$G$6:$G$11)*Kalender!D17/SUM(Kalender!$D$5:$D$370),0)+IFERROR(SUMIF(Nutzungsprofile!$B$6:$B$11,"Individuell",Nutzungsprofile!$G$6:$G$11)*Kalender!E17/SUM(Kalender!$E$5:$E$370),0))*Szenarien!$E$8,0) -> 2.352 | D17: =IF(Szenarien!$H$8="OK",(IFERROR(SUMIF(Nutzungsprofile!$B$17:$B$22,"Schulbetrieb",Nutzungsprofile!$G$17:$G$22)*Kalender!C17/SUM(Kalender!$C$5:$C$370),0)+IFERROR(SUMIF(Nutzungsprofile!$B$17:$B$22,"Halle",Nutzungsprofile!$G$17:$G$22)*Kalender!D17/SUM(Kalender!$D$5:$D$370),0)+IFERROR(SUMIF(Nutzungsprofile!$B$17:$B$22,"Individuell",Nutzungsprofile!$G$17:$G$22)*Kalender!E17/SUM(Kalender!$E$5:$E$370),0))*Szenarien!$D$8,0) -> 4.446 | E17: =IFERROR(MIN(C17,Eingaben!$B$17)*Eingaben!$B$16,0) -> 2.2344 | F17: =IFERROR(E17*Eingaben!$B$15,0) -> 2.01096 | G17: =IFERROR(IF(Kalender!A17="",0,J16*(1-Eingaben!$B$20)),0) -> 0.59122224 | H17: =MIN(G17,D17) -> 0.59122224 | I17: =IFERROR(MIN(F17*Eingaben!$B$19,MAX(0,D17-H17)),0) -> 1.407672 | J17: =IFERROR(MIN(Eingaben!$B$18,MAX(0,F17-I17)),0) -> 0.603288 | K17: =H17+I17 -> 1.9988942 | L17: =MAX(0,D17-K17) -> 2.4471058 | M17: =MAX(0,F17-I17-J17) -> 0 | N17: =IF(Kalender!A17="",0,J16-H17) -> 0.01206576
A18: ="" | B18: =14 -> 14 | C18: =IF(Szenarien!$H$8="OK",(IFERROR(SUMIF(Nutzungsprofile!$B$6:$B$11,"Schulbetrieb",Nutzungsprofile!$G$6:$G$11)*Kalender!C18/SUM(Kalender!$C$5:$C$370),0)+IFERROR(SUMIF(Nutzungsprofile!$B$6:$B$11,"Halle",Nutzungsprofile!$G$6:$G$11)*Kalender!D18/SUM(Kalender!$D$5:$D$370),0)+IFERROR(SUMIF(Nutzungsprofile!$B$6:$B$11,"Individuell",Nutzungsprofile!$G$6:$G$11)*Kalender!E18/SUM(Kalender!$E$5:$E$370),0))*Szenarien!$E$8,0) -> 2.352 | D18: =IF(Szenarien!$H$8="OK",(IFERROR(SUMIF(Nutzungsprofile!$B$17:$B$22,"Schulbetrieb",Nutzungsprofile!$G$17:$G$22)*Kalender!C18/SUM(Kalender!$C$5:$C$370),0)+IFERROR(SUMIF(Nutzungsprofile!$B$17:$B$22,"Halle",Nutzungsprofile!$G$17:$G$22)*Kalender!D18/SUM(Kalender!$D$5:$D$370),0)+IFERROR(SUMIF(Nutzungsprofile!$B$17:$B$22,"Individuell",Nutzungsprofile!$G$17:$G$22)*Kalender!E18/SUM(Kalender!$E$5:$E$370),0))*Szenarien!$D$8,0) -> 4.446 | E18: =IFERROR(MIN(C18,Eingaben!$B$17)*Eingaben!$B$16,0) -> 2.2344 | F18: =IFERROR(E18*Eingaben!$B$15,0) -> 2.01096 | G18: =IFERROR(IF(Kalender!A18="",0,J17*(1-Eingaben!$B$20)),0) -> 0.59122224 | H18: =MIN(G18,D18) -> 0.59122224 | I18: =IFERROR(MIN(F18*Eingaben!$B$19,MAX(0,D18-H18)),0) -> 1.407672 | J18: =IFERROR(MIN(Eingaben!$B$18,MAX(0,F18-I18)),0) -> 0.603288 | K18: =H18+I18 -> 1.9988942 | L18: =MAX(0,D18-K18) -> 2.4471058 | M18: =MAX(0,F18-I18-J18) -> 0 | N18: =IF(Kalender!A18="",0,J17-H18) -> 0.01206576
A19: ="" | B19: =15 -> 15 | C19: =IF(Szenarien!$H$8="OK",(IFERROR(SUMIF(Nutzungsprofile!$B$6:$B$11,"Schulbetrieb",Nutzungsprofile!$G$6:$G$11)*Kalender!C19/SUM(Kalender!$C$5:$C$370),0)+IFERROR(SUMIF(Nutzungsprofile!$B$6:$B$11,"Halle",Nutzungsprofile!$G$6:$G$11)*Kalender!D19/SUM(Kalender!$D$5:$D$370),0)+IFERROR(SUMIF(Nutzungsprofile!$B$6:$B$11,"Individuell",Nutzungsprofile!$G$6:$G$11)*Kalender!E19/SUM(Kalender!$E$5:$E$370),0))*Szenarien!$E$8,0) -> 2.352 | D19: =IF(Szenarien!$H$8="OK",(IFERROR(SUMIF(Nutzungsprofile!$B$17:$B$22,"Schulbetrieb",Nutzungsprofile!$G$17:$G$22)*Kalender!C19/SUM(Kalender!$C$5:$C$370),0)+IFERROR(SUMIF(Nutzungsprofile!$B$17:$B$22,"Halle",Nutzungsprofile!$G$17:$G$22)*Kalender!D19/SUM(Kalender!$D$5:$D$370),0)+IFERROR(SUMIF(Nutzungsprofile!$B$17:$B$22,"Individuell",Nutzungsprofile!$G$17:$G$22)*Kalender!E19/SUM(Kalender!$E$5:$E$370),0))*Szenarien!$D$8,0) -> 4.446 | E19: =IFERROR(MIN(C19,Eingaben!$B$17)*Eingaben!$B$16,0) -> 2.2344 | F19: =IFERROR(E19*Eingaben!$B$15,0) -> 2.01096 | G19: =IFERROR(IF(Kalender!A19="",0,J18*(1-Eingaben!$B$20)),0) -> 0.59122224 | H19: =MIN(G19,D19) -> 0.59122224 | I19: =IFERROR(MIN(F19*Eingaben!$B$19,MAX(0,D19-H19)),0) -> 1.407672 | J19: =IFERROR(MIN(Eingaben!$B$18,MAX(0,F19-I19)),0) -> 0.603288 | K19: =H19+I19 -> 1.9988942 | L19: =MAX(0,D19-K19) -> 2.4471058 | M19: =MAX(0,F19-I19-J19) -> 0 | N19: =IF(Kalender!A19="",0,J18-H19) -> 0.01206576
A20: ="" | B20: =16 -> 16 | C20: =IF(Szenarien!$H$8="OK",(IFERROR(SUMIF(Nutzungsprofile!$B$6:$B$11,"Schulbetrieb",Nutzungsprofile!$G$6:$G$11)*Kalender!C20/SUM(Kalender!$C$5:$C$370),0)+IFERROR(SUMIF(Nutzungsprofile!$B$6:$B$11,"Halle",Nutzungsprofile!$G$6:$G$11)*Kalender!D20/SUM(Kalender!$D$5:$D$370),0)+IFERROR(SUMIF(Nutzungsprofile!$B$6:$B$11,"Individuell",Nutzungsprofile!$G$6:$G$11)*Kalender!E20/SUM(Kalender!$E$5:$E$370),0))*Szenarien!$E$8,0) -> 2.352 | D20: =IF(Szenarien!$H$8="OK",(IFERROR(SUMIF(Nutzungsprofile!$B$17:$B$22,"Schulbetrieb",Nutzungsprofile!$G$17:$G$22)*Kalender!C20/SUM(Kalender!$C$5:$C$370),0)+IFERROR(SUMIF(Nutzungsprofile!$B$17:$B$22,"Halle",Nutzungsprofile!$G$17:$G$22)*Kalender!D20/SUM(Kalender!$D$5:$D$370),0)+IFERROR(SUMIF(Nutzungsprofile!$B$17:$B$22,"Individuell",Nutzungsprofile!$G$17:$G$22)*Kalender!E20/SUM(Kalender!$E$5:$E$370),0))*Szenarien!$D$8,0) -> 4.446 | E20: =IFERROR(MIN(C20,Eingaben!$B$17)*Eingaben!$B$16,0) -> 2.2344 | F20: =IFERROR(E20*Eingaben!$B$15,0) -> 2.01096 | G20: =IFERROR(IF(Kalender!A20="",0,J19*(1-Eingaben!$B$20)),0) -> 0.59122224 | H20: =MIN(G20,D20) -> 0.59122224 | I20: =IFERROR(MIN(F20*Eingaben!$B$19,MAX(0,D20-H20)),0) -> 1.407672 | J20: =IFERROR(MIN(Eingaben!$B$18,MAX(0,F20-I20)),0) -> 0.603288 | K20: =H20+I20 -> 1.9988942 | L20: =MAX(0,D20-K20) -> 2.4471058 | M20: =MAX(0,F20-I20-J20) -> 0 | N20: =IF(Kalender!A20="",0,J19-H20) -> 0.01206576
A21: ="" | B21: =17 -> 17 | C21: =IF(Szenarien!$H$8="OK",(IFERROR(SUMIF(Nutzungsprofile!$B$6:$B$11,"Schulbetrieb",Nutzungsprofile!$G$6:$G$11)*Kalender!C21/SUM(Kalender!$C$5:$C$370),0)+IFERROR(SUMIF(Nutzungsprofile!$B$6:$B$11,"Halle",Nutzungsprofile!$G$6:$G$11)*Kalender!D21/SUM(Kalender!$D$5:$D$370),0)+IFERROR(SUMIF(Nutzungsprofile!$B$6:$B$11,"Individuell",Nutzungsprofile!$G$6:$G$11)*Kalender!E21/SUM(Kalender!$E$5:$E$370),0))*Szenarien!$E$8,0) -> 1.632 | D21: =IF(Szenarien!$H$8="OK",(IFERROR(SUMIF(Nutzungsprofile!$B$17:$B$22,"Schulbetrieb",Nutzungsprofile!$G$17:$G$22)*Kalender!C21/SUM(Kalender!$C$5:$C$370),0)+IFERROR(SUMIF(Nutzungsprofile!$B$17:$B$22,"Halle",Nutzungsprofile!$G$17:$G$22)*Kalender!D21/SUM(Kalender!$D$5:$D$370),0)+IFERROR(SUMIF(Nutzungsprofile!$B$17:$B$22,"Individuell",Nutzungsprofile!$G$17:$G$22)*Kalender!E21/SUM(Kalender!$E$5:$E$370),0))*Szenarien!$D$8,0) -> 0.801 | E21: =IFERROR(MIN(C21,Eingaben!$B$17)*Eingaben!$B$16,0) -> 1.5504 | F21: =IFERROR(E21*Eingaben!$B$15,0) -> 1.39536 | G21: =IFERROR(IF(Kalender!A21="",0,J20*(1-Eingaben!$B$20)),0) -> 0.59122224 | H21: =MIN(G21,D21) -> 0.59122224 | I21: =IFERROR(MIN(F21*Eingaben!$B$19,MAX(0,D21-H21)),0) -> 0.20977776 | J21: =IFERROR(MIN(Eingaben!$B$18,MAX(0,F21-I21)),0) -> 1.1855822 | K21: =H21+I21 -> 0.801 | L21: =MAX(0,D21-K21) -> 0 | M21: =MAX(0,F21-I21-J21) -> 0 | N21: =IF(Kalender!A21="",0,J20-H21) -> 0.01206576
A22: ="" | B22: =18 -> 18 | C22: =IF(Szenarien!$H$8="OK",(IFERROR(SUMIF(Nutzungsprofile!$B$6:$B$11,"Schulbetrieb",Nutzungsprofile!$G$6:$G$11)*Kalender!C22/SUM(Kalender!$C$5:$C$370),0)+IFERROR(SUMIF(Nutzungsprofile!$B$6:$B$11,"Halle",Nutzungsprofile!$G$6:$G$11)*Kalender!D22/SUM(Kalender!$D$5:$D$370),0)+IFERROR(SUMIF(Nutzungsprofile!$B$6:$B$11,"Individuell",Nutzungsprofile!$G$6:$G$11)*Kalender!E22/SUM(Kalender!$E$5:$E$370),0))*Szenarien!$E$8,0) -> 1.632 | D22: =IF(Szenarien!$H$8="OK",(IFERROR(SUMIF(Nutzungsprofile!$B$17:$B$22,"Schulbetrieb",Nutzungsprofile!$G$17:$G$22)*Kalender!C22/SUM(Kalender!$C$5:$C$370),0)+IFERROR(SUMIF(Nutzungsprofile!$B$17:$B$22,"Halle",Nutzungsprofile!$G$17:$G$22)*Kalender!D22/SUM(Kalender!$D$5:$D$370),0)+IFERROR(SUMIF(Nutzungsprofile!$B$17:$B$22,"Individuell",Nutzungsprofile!$G$17:$G$22)*Kalender!E22/SUM(Kalender!$E$5:$E$370),0))*Szenarien!$D$8,0) -> 0.801 | E22: =IFERROR(MIN(C22,Eingaben!$B$17)*Eingaben!$B$16,0) -> 1.5504 | F22: =IFERROR(E22*Eingaben!$B$15,0) -> 1.39536 | G22: =IFERROR(IF(Kalender!A22="",0,J21*(1-Eingaben!$B$20)),0) -> 1.1618706 | H22: =MIN(G22,D22) -> 0.801 | I22: =IFERROR(MIN(F22*Eingaben!$B$19,MAX(0,D22-H22)),0) -> 0 | J22: =IFERROR(MIN(Eingaben!$B$18,MAX(0,F22-I22)),0) -> 1.39536 | K22: =H22+I22 -> 0.801 | L22: =MAX(0,D22-K22) -> 0 | M22: =MAX(0,F22-I22-J22) -> 0 | N22: =IF(Kalender!A22="",0,J21-H22) -> 0.38458224
A23: ="" | B23: =19 -> 19 | C23: =IF(Szenarien!$H$8="OK",(IFERROR(SUMIF(Nutzungsprofile!$B$6:$B$11,"Schulbetrieb",Nutzungsprofile!$G$6:$G$11)*Kalender!C23/SUM(Kalender!$C$5:$C$370),0)+IFERROR(SUMIF(Nutzungsprofile!$B$6:$B$11,"Halle",Nutzungsprofile!$G$6:$G$11)*Kalender!D23/SUM(Kalender!$D$5:$D$370),0)+IFERROR(SUMIF(Nutzungsprofile!$B$6:$B$11,"Individuell",Nutzungsprofile!$G$6:$G$11)*Kalender!E23/SUM(Kalender!$E$5:$E$370),0))*Szenarien!$E$8,0) -> 2.352 | D23: =IF(Szenarien!$H$8="OK",(IFERROR(SUMIF(Nutzungsprofile!$B$17:$B$22,"Schulbetrieb",Nutzungsprofile!$G$17:$G$22)*Kalender!C23/SUM(Kalender!$C$5:$C$370),0)+IFERROR(SUMIF(Nutzungsprofile!$B$17:$B$22,"Halle",Nutzungsprofile!$G$17:$G$22)*Kalender!D23/SUM(Kalender!$D$5:$D$370),0)+IFERROR(SUMIF(Nutzungsprofile!$B$17:$B$22,"Individuell",Nutzungsprofile!$G$17:$G$22)*Kalender!E23/SUM(Kalender!$E$5:$E$370),0))*Szenarien!$D$8,0) -> 4.446 | E23: =IFERROR(MIN(C23,Eingaben!$B$17)*Eingaben!$B$16,0) -> 2.2344 | F23: =IFERROR(E23*Eingaben!$B$15,0) -> 2.01096 | G23: =IFERROR(IF(Kalender!A23="",0,J22*(1-Eingaben!$B$20)),0) -> 1.3674528 | H23: =MIN(G23,D23) -> 1.3674528 | I23: =IFERROR(MIN(F23*Eingaben!$B$19,MAX(0,D23-H23)),0) -> 1.407672 | J23: =IFERROR(MIN(Eingaben!$B$18,MAX(0,F23-I23)),0) -> 0.603288 | K23: =H23+I23 -> 2.7751248 | L23: =MAX(0,D23-K23) -> 1.6708752 | M23: =MAX(0,F23-I23-J23) -> 0 | N23: =IF(Kalender!A23="",0,J22-H23) -> 0.0279072
A24: ="" | B24: =20 -> 20 | C24: =IF(Szenarien!$H$8="OK",(IFERROR(SUMIF(Nutzungsprofile!$B$6:$B$11,"Schulbetrieb",Nutzungsprofile!$G$6:$G$11)*Kalender!C24/SUM(Kalender!$C$5:$C$370),0)+IFERROR(SUMIF(Nutzungsprofile!$B$6:$B$11,"Halle",Nutzungsprofile!$G$6:$G$11)*Kalender!D24/SUM(Kalender!$D$5:$D$370),0)+IFERROR(SUMIF(Nutzungsprofile!$B$6:$B$11,"Individuell",Nutzungsprofile!$G$6:$G$11)*Kalender!E24/SUM(Kalender!$E$5:$E$370),0))*Szenarien!$E$8,0) -> 2.352 | D24: =IF(Szenarien!$H$8="OK",(IFERROR(SUMIF(Nutzungsprofile!$B$17:$B$22,"Schulbetrieb",Nutzungsprofile!$G$17:$G$22)*Kalender!C24/SUM(Kalender!$C$5:$C$370),0)+IFERROR(SUMIF(Nutzungsprofile!$B$17:$B$22,"Halle",Nutzungsprofile!$G$17:$G$22)*Kalender!D24/SUM(Kalender!$D$5:$D$370),0)+IFERROR(SUMIF(Nutzungsprofile!$B$17:$B$22,"Individuell",Nutzungsprofile!$G$17:$G$22)*Kalender!E24/SUM(Kalender!$E$5:$E$370),0))*Szenarien!$D$8,0) -> 4.446 | E24: =IFERROR(MIN(C24,Eingaben!$B$17)*Eingaben!$B$16,0) -> 2.2344 | F24: =IFERROR(E24*Eingaben!$B$15,0) -> 2.01096 | G24: =IFERROR(IF(Kalender!A24="",0,J23*(1-Eingaben!$B$20)),0) -> 0.59122224 | H24: =MIN(G24,D24) -> 0.59122224 | I24: =IFERROR(MIN(F24*Eingaben!$B$19,MAX(0,D24-H24)),0) -> 1.407672 | J24: =IFERROR(MIN(Eingaben!$B$18,MAX(0,F24-I24)),0) -> 0.603288 | K24: =H24+I24 -> 1.9988942 | L24: =MAX(0,D24-K24) -> 2.4471058 | M24: =MAX(0,F24-I24-J24) -> 0 | N24: =IF(Kalender!A24="",0,J23-H24) -> 0.01206576
A25: ="" | B25: =21 -> 21 | C25: =IF(Szenarien!$H$8="OK",(IFERROR(SUMIF(Nutzungsprofile!$B$6:$B$11,"Schulbetrieb",Nutzungsprofile!$G$6:$G$11)*Kalender!C25/SUM(Kalender!$C$5:$C$370),0)+IFERROR(SUMIF(Nutzungsprofile!$B$6:$B$11,"Halle",Nutzungsprofile!$G$6:$G$11)*Kalender!D25/SUM(Kalender!$D$5:$D$370),0)+IFERROR(SUMIF(Nutzungsprofile!$B$6:$B$11,"Individuell",Nutzungsprofile!$G$6:$G$11)*Kalender!E25/SUM(Kalender!$E$5:$E$370),0))*Szenarien!$E$8,0) -> 2.352 | D25: =IF(Szenarien!$H$8="OK",(IFERROR(SUMIF(Nutzungsprofile!$B$17:$B$22,"Schulbetrieb",Nutzungsprofile!$G$17:$G$22)*Kalender!C25/SUM(Kalender!$C$5:$C$370),0)+IFERROR(SUMIF(Nutzungsprofile!$B$17:$B$22,"Halle",Nutzungsprofile!$G$17:$G$22)*Kalender!D25/SUM(Kalender!$D$5:$D$370),0)+IFERROR(SUMIF(Nutzungsprofile!$B$17:$B$22,"Individuell",Nutzungsprofile!$G$17:$G$22)*Kalender!E25/SUM(Kalender!$E$5:$E$370),0))*Szenarien!$D$8,0) -> 4.446 | E25: =IFERROR(MIN(C25,Eingaben!$B$17)*Eingaben!$B$16,0) -> 2.2344 | F25: =IFERROR(E25*Eingaben!$B$15,0) -> 2.01096 | G25: =IFERROR(IF(Kalender!A25="",0,J24*(1-Eingaben!$B$20)),0) -> 0.59122224 | H25: =MIN(G25,D25) -> 0.59122224 | I25: =IFERROR(MIN(F25*Eingaben!$B$19,MAX(0,D25-H25)),0) -> 1.407672 | J25: =IFERROR(MIN(Eingaben!$B$18,MAX(0,F25-I25)),0) -> 0.603288 | K25: =H25+I25 -> 1.9988942 | L25: =MAX(0,D25-K25) -> 2.4471058 | M25: =MAX(0,F25-I25-J25) -> 0 | N25: =IF(Kalender!A25="",0,J24-H25) -> 0.01206576
A26: ="" | B26: =22 -> 22 | C26: =IF(Szenarien!$H$8="OK",(IFERROR(SUMIF(Nutzungsprofile!$B$6:$B$11,"Schulbetrieb",Nutzungsprofile!$G$6:$G$11)*Kalender!C26/SUM(Kalender!$C$5:$C$370),0)+IFERROR(SUMIF(Nutzungsprofile!$B$6:$B$11,"Halle",Nutzungsprofile!$G$6:$G$11)*Kalender!D26/SUM(Kalender!$D$5:$D$370),0)+IFERROR(SUMIF(Nutzungsprofile!$B$6:$B$11,"Individuell",Nutzungsprofile!$G$6:$G$11)*Kalender!E26/SUM(Kalender!$E$5:$E$370),0))*Szenarien!$E$8,0) -> 2.352 | D26: =IF(Szenarien!$H$8="OK",(IFERROR(SUMIF(Nutzungsprofile!$B$17:$B$22,"Schulbetrieb",Nutzungsprofile!$G$17:$G$22)*Kalender!C26/SUM(Kalender!$C$5:$C$370),0)+IFERROR(SUMIF(Nutzungsprofile!$B$17:$B$22,"Halle",Nutzungsprofile!$G$17:$G$22)*Kalender!D26/SUM(Kalender!$D$5:$D$370),0)+IFERROR(SUMIF(Nutzungsprofile!$B$17:$B$22,"Individuell",Nutzungsprofile!$G$17:$G$22)*Kalender!E26/SUM(Kalender!$E$5:$E$370),0))*Szenarien!$D$8,0) -> 4.446 | E26: =IFERROR(MIN(C26,Eingaben!$B$17)*Eingaben!$B$16,0) -> 2.2344 | F26: =IFERROR(E26*Eingaben!$B$15,0) -> 2.01096 | G26: =IFERROR(IF(Kalender!A26="",0,J25*(1-Eingaben!$B$20)),0) -> 0.59122224 | H26: =MIN(G26,D26) -> 0.59122224 | I26: =IFERROR(MIN(F26*Eingaben!$B$19,MAX(0,D26-H26)),0) -> 1.407672 | J26: =IFERROR(MIN(Eingaben!$B$18,MAX(0,F26-I26)),0) -> 0.603288 | K26: =H26+I26 -> 1.9988942 | L26: =MAX(0,D26-K26) -> 2.4471058 | M26: =MAX(0,F26-I26-J26) -> 0 | N26: =IF(Kalender!A26="",0,J25-H26) -> 0.01206576
A27: ="" | B27: =23 -> 23 | C27: =IF(Szenarien!$H$8="OK",(IFERROR(SUMIF(Nutzungsprofile!$B$6:$B$11,"Schulbetrieb",Nutzungsprofile!$G$6:$G$11)*Kalender!C27/SUM(Kalender!$C$5:$C$370),0)+IFERROR(SUMIF(Nutzungsprofile!$B$6:$B$11,"Halle",Nutzungsprofile!$G$6:$G$11)*Kalender!D27/SUM(Kalender!$D$5:$D$370),0)+IFERROR(SUMIF(Nutzungsprofile!$B$6:$B$11,"Individuell",Nutzungsprofile!$G$6:$G$11)*Kalender!E27/SUM(Kalender!$E$5:$E$370),0))*Szenarien!$E$8,0) -> 2.352 | D27: =IF(Szenarien!$H$8="OK",(IFERROR(SUMIF(Nutzungsprofile!$B$17:$B$22,"Schulbetrieb",Nutzungsprofile!$G$17:$G$22)*Kalender!C27/SUM(Kalender!$C$5:$C$370),0)+IFERROR(SUMIF(Nutzungsprofile!$B$17:$B$22,"Halle",Nutzungsprofile!$G$17:$G$22)*Kalender!D27/SUM(Kalender!$D$5:$D$370),0)+IFERROR(SUMIF(Nutzungsprofile!$B$17:$B$22,"Individuell",Nutzungsprofile!$G$17:$G$22)*Kalender!E27/SUM(Kalender!$E$5:$E$370),0))*Szenarien!$D$8,0) -> 4.446 | E27: =IFERROR(MIN(C27,Eingaben!$B$17)*Eingaben!$B$16,0) -> 2.2344 | F27: =IFERROR(E27*Eingaben!$B$15,0) -> 2.01096 | G27: =IFERROR(IF(Kalender!A27="",0,J26*(1-Eingaben!$B$20)),0) -> 0.59122224 | H27: =MIN(G27,D27) -> 0.59122224 | I27: =IFERROR(MIN(F27*Eingaben!$B$19,MAX(0,D27-H27)),0) -> 1.407672 | J27: =IFERROR(MIN(Eingaben!$B$18,MAX(0,F27-I27)),0) -> 0.603288 | K27: =H27+I27 -> 1.9988942 | L27: =MAX(0,D27-K27) -> 2.4471058 | M27: =MAX(0,F27-I27-J27) -> 0 | N27: =IF(Kalender!A27="",0,J26-H27) -> 0.01206576
A28: ="" | B28: =24 -> 24 | C28: =IF(Szenarien!$H$8="OK",(IFERROR(SUMIF(Nutzungsprofile!$B$6:$B$11,"Schulbetrieb",Nutzungsprofile!$G$6:$G$11)*Kalender!C28/SUM(Kalender!$C$5:$C$370),0)+IFERROR(SUMIF(Nutzungsprofile!$B$6:$B$11,"Halle",Nutzungsprofile!$G$6:$G$11)*Kalender!D28/SUM(Kalender!$D$5:$D$370),0)+IFERROR(SUMIF(Nutzungsprofile!$B$6:$B$11,"Individuell",Nutzungsprofile!$G$6:$G$11)*Kalender!E28/SUM(Kalender!$E$5:$E$370),0))*Szenarien!$E$8,0) -> 1.632 | D28: =IF(Szenarien!$H$8="OK",(IFERROR(SUMIF(Nutzungsprofile!$B$17:$B$22,"Schulbetrieb",Nutzungsprofile!$G$17:$G$22)*Kalender!C28/SUM(Kalender!$C$5:$C$370),0)+IFERROR(SUMIF(Nutzungsprofile!$B$17:$B$22,"Halle",Nutzungsprofile!$G$17:$G$22)*Kalender!D28/SUM(Kalender!$D$5:$D$370),0)+IFERROR(SUMIF(Nutzungsprofile!$B$17:$B$22,"Individuell",Nutzungsprofile!$G$17:$G$22)*Kalender!E28/SUM(Kalender!$E$5:$E$370),0))*Szenarien!$D$8,0) -> 0.801 | E28: =IFERROR(MIN(C28,Eingaben!$B$17)*Eingaben!$B$16,0) -> 1.5504 | F28: =IFERROR(E28*Eingaben!$B$15,0) -> 1.39536 | G28: =IFERROR(IF(Kalender!A28="",0,J27*(1-Eingaben!$B$20)),0) -> 0.59122224 | H28: =MIN(G28,D28) -> 0.59122224 | I28: =IFERROR(MIN(F28*Eingaben!$B$19,MAX(0,D28-H28)),0) -> 0.20977776 | J28: =IFERROR(MIN(Eingaben!$B$18,MAX(0,F28-I28)),0) -> 1.1855822 | K28: =H28+I28 -> 0.801 | L28: =MAX(0,D28-K28) -> 0 | M28: =MAX(0,F28-I28-J28) -> 0 | N28: =IF(Kalender!A28="",0,J27-H28) -> 0.01206576
A29: ="" | B29: =25 -> 25 | C29: =IF(Szenarien!$H$8="OK",(IFERROR(SUMIF(Nutzungsprofile!$B$6:$B$11,"Schulbetrieb",Nutzungsprofile!$G$6:$G$11)*Kalender!C29/SUM(Kalender!$C$5:$C$370),0)+IFERROR(SUMIF(Nutzungsprofile!$B$6:$B$11,"Halle",Nutzungsprofile!$G$6:$G$11)*Kalender!D29/SUM(Kalender!$D$5:$D$370),0)+IFERROR(SUMIF(Nutzungsprofile!$B$6:$B$11,"Individuell",Nutzungsprofile!$G$6:$G$11)*Kalender!E29/SUM(Kalender!$E$5:$E$370),0))*Szenarien!$E$8,0) -> 1.632 | D29: =IF(Szenarien!$H$8="OK",(IFERROR(SUMIF(Nutzungsprofile!$B$17:$B$22,"Schulbetrieb",Nutzungsprofile!$G$17:$G$22)*Kalender!C29/SUM(Kalender!$C$5:$C$370),0)+IFERROR(SUMIF(Nutzungsprofile!$B$17:$B$22,"Halle",Nutzungsprofile!$G$17:$G$22)*Kalender!D29/SUM(Kalender!$D$5:$D$370),0)+IFERROR(SUMIF(Nutzungsprofile!$B$17:$B$22,"Individuell",Nutzungsprofile!$G$17:$G$22)*Kalender!E29/SUM(Kalender!$E$5:$E$370),0))*Szenarien!$D$8,0) -> 0.801 | E29: =IFERROR(MIN(C29,Eingaben!$B$17)*Eingaben!$B$16,0) -> 1.5504 | F29: =IFERROR(E29*Eingaben!$B$15,0) -> 1.39536 | G29: =IFERROR(IF(Kalender!A29="",0,J28*(1-Eingaben!$B$20)),0) -> 1.1618706 | H29: =MIN(G29,D29) -> 0.801 | I29: =IFERROR(MIN(F29*Eingaben!$B$19,MAX(0,D29-H29)),0) -> 0 | J29: =IFERROR(MIN(Eingaben!$B$18,MAX(0,F29-I29)),0) -> 1.39536 | K29: =H29+I29 -> 0.801 | L29: =MAX(0,D29-K29) -> 0 | M29: =MAX(0,F29-I29-J29) -> 0 | N29: =IF(Kalender!A29="",0,J28-H29) -> 0.38458224
A30: ="" | B30: =26 -> 26 | C30: =IF(Szenarien!$H$8="OK",(IFERROR(SUMIF(Nutzungsprofile!$B$6:$B$11,"Schulbetrieb",Nutzungsprofile!$G$6:$G$11)*Kalender!C30/SUM(Kalender!$C$5:$C$370),0)+IFERROR(SUMIF(Nutzungsprofile!$B$6:$B$11,"Halle",Nutzungsprofile!$G$6:$G$11)*Kalender!D30/SUM(Kalender!$D$5:$D$370),0)+IFERROR(SUMIF(Nutzungsprofile!$B$6:$B$11,"Individuell",Nutzungsprofile!$G$6:$G$11)*Kalender!E30/SUM(Kalender!$E$5:$E$370),0))*Szenarien!$E$8,0) -> 2.352 | D30: =IF(Szenarien!$H$8="OK",(IFERROR(SUMIF(Nutzungsprofile!$B$17:$B$22,"Schulbetrieb",Nutzungsprofile!$G$17:$G$22)*Kalender!C30/SUM(Kalender!$C$5:$C$370),0)+IFERROR(SUMIF(Nutzungsprofile!$B$17:$B$22,"Halle",Nutzungsprofile!$G$17:$G$22)*Kalender!D30/SUM(Kalender!$D$5:$D$370),0)+IFERROR(SUMIF(Nutzungsprofile!$B$17:$B$22,"Individuell",Nutzungsprofile!$G$17:$G$22)*Kalender!E30/SUM(Kalender!$E$5:$E$370),0))*Szenarien!$D$8,0) -> 4.446 | E30: =IFERROR(MIN(C30,Eingaben!$B$17)*Eingaben!$B$16,0) -> 2.2344 | F30: =IFERROR(E30*Eingaben!$B$15,0) -> 2.01096 | G30: =IFERROR(IF(Kalender!A30="",0,J29*(1-Eingaben!$B$20)),0) -> 1.3674528 | H30: =MIN(G30,D30) -> 1.3674528 | I30: =IFERROR(MIN(F30*Eingaben!$B$19,MAX(0,D30-H30)),0) -> 1.407672 | J30: =IFERROR(MIN(Eingaben!$B$18,MAX(0,F30-I30)),0) -> 0.603288 | K30: =H30+I30 -> 2.7751248 | L30: =MAX(0,D30-K30) -> 1.6708752 | M30: =MAX(0,F30-I30-J30) -> 0 | N30: =IF(Kalender!A30="",0,J29-H30) -> 0.0279072
A31: ="" | B31: =27 -> 27 | C31: =IF(Szenarien!$H$8="OK",(IFERROR(SUMIF(Nutzungsprofile!$B$6:$B$11,"Schulbetrieb",Nutzungsprofile!$G$6:$G$11)*Kalender!C31/SUM(Kalender!$C$5:$C$370),0)+IFERROR(SUMIF(Nutzungsprofile!$B$6:$B$11,"Halle",Nutzungsprofile!$G$6:$G$11)*Kalender!D31/SUM(Kalender!$D$5:$D$370),0)+IFERROR(SUMIF(Nutzungsprofile!$B$6:$B$11,"Individuell",Nutzungsprofile!$G$6:$G$11)*Kalender!E31/SUM(Kalender!$E$5:$E$370),0))*Szenarien!$E$8,0) -> 2.352 | D31: =IF(Szenarien!$H$8="OK",(IFERROR(SUMIF(Nutzungsprofile!$B$17:$B$22,"Schulbetrieb",Nutzungsprofile!$G$17:$G$22)*Kalender!C31/SUM(Kalender!$C$5:$C$370),0)+IFERROR(SUMIF(Nutzungsprofile!$B$17:$B$22,"Halle",Nutzungsprofile!$G$17:$G$22)*Kalender!D31/SUM(Kalender!$D$5:$D$370),0)+IFERROR(SUMIF(Nutzungsprofile!$B$17:$B$22,"Individuell",Nutzungsprofile!$G$17:$G$22)*Kalender!E31/SUM(Kalender!$E$5:$E$370),0))*Szenarien!$D$8,0) -> 4.446 | E31: =IFERROR(MIN(C31,Eingaben!$B$17)*Eingaben!$B$16,0) -> 2.2344 | F31: =IFERROR(E31*Eingaben!$B$15,0) -> 2.01096 | G31: =IFERROR(IF(Kalender!A31="",0,J30*(1-Eingaben!$B$20)),0) -> 0.59122224 | H31: =MIN(G31,D31) -> 0.59122224 | I31: =IFERROR(MIN(F31*Eingaben!$B$19,MAX(0,D31-H31)),0) -> 1.407672 | J31: =IFERROR(MIN(Eingaben!$B$18,MAX(0,F31-I31)),0) -> 0.603288 | K31: =H31+I31 -> 1.9988942 | L31: =MAX(0,D31-K31) -> 2.4471058 | M31: =MAX(0,F31-I31-J31) -> 0 | N31: =IF(Kalender!A31="",0,J30-H31) -> 0.01206576
A32: ="" | B32: =28 -> 28 | C32: =IF(Szenarien!$H$8="OK",(IFERROR(SUMIF(Nutzungsprofile!$B$6:$B$11,"Schulbetrieb",Nutzungsprofile!$G$6:$G$11)*Kalender!C32/SUM(Kalender!$C$5:$C$370),0)+IFERROR(SUMIF(Nutzungsprofile!$B$6:$B$11,"Halle",Nutzungsprofile!$G$6:$G$11)*Kalender!D32/SUM(Kalender!$D$5:$D$370),0)+IFERROR(SUMIF(Nutzungsprofile!$B$6:$B$11,"Individuell",Nutzungsprofile!$G$6:$G$11)*Kalender!E32/SUM(Kalender!$E$5:$E$370),0))*Szenarien!$E$8,0) -> 2.352 | D32: =IF(Szenarien!$H$8="OK",(IFERROR(SUMIF(Nutzungsprofile!$B$17:$B$22,"Schulbetrieb",Nutzungsprofile!$G$17:$G$22)*Kalender!C32/SUM(Kalender!$C$5:$C$370),0)+IFERROR(SUMIF(Nutzungsprofile!$B$17:$B$22,"Halle",Nutzungsprofile!$G$17:$G$22)*Kalender!D32/SUM(Kalender!$D$5:$D$370),0)+IFERROR(SUMIF(Nutzungsprofile!$B$17:$B$22,"Individuell",Nutzungsprofile!$G$17:$G$22)*Kalender!E32/SUM(Kalender!$E$5:$E$370),0))*Szenarien!$D$8,0) -> 4.446 | E32: =IFERROR(MIN(C32,Eingaben!$B$17)*Eingaben!$B$16,0) -> 2.2344 | F32: =IFERROR(E32*Eingaben!$B$15,0) -> 2.01096 | G32: =IFERROR(IF(Kalender!A32="",0,J31*(1-Eingaben!$B$20)),0) -> 0.59122224 | H32: =MIN(G32,D32) -> 0.59122224 | I32: =IFERROR(MIN(F32*Eingaben!$B$19,MAX(0,D32-H32)),0) -> 1.407672 | J32: =IFERROR(MIN(Eingaben!$B$18,MAX(0,F32-I32)),0) -> 0.603288 | K32: =H32+I32 -> 1.9988942 | L32: =MAX(0,D32-K32) -> 2.4471058 | M32: =MAX(0,F32-I32-J32) -> 0 | N32: =IF(Kalender!A32="",0,J31-H32) -> 0.01206576
A33: ="" | B33: =29 -> 29 | C33: =IF(Szenarien!$H$8="OK",(IFERROR(SUMIF(Nutzungsprofile!$B$6:$B$11,"Schulbetrieb",Nutzungsprofile!$G$6:$G$11)*Kalender!C33/SUM(Kalender!$C$5:$C$370),0)+IFERROR(SUMIF(Nutzungsprofile!$B$6:$B$11,"Halle",Nutzungsprofile!$G$6:$G$11)*Kalender!D33/SUM(Kalender!$D$5:$D$370),0)+IFERROR(SUMIF(Nutzungsprofile!$B$6:$B$11,"Individuell",Nutzungsprofile!$G$6:$G$11)*Kalender!E33/SUM(Kalender!$E$5:$E$370),0))*Szenarien!$E$8,0) -> 2.352 | D33: =IF(Szenarien!$H$8="OK",(IFERROR(SUMIF(Nutzungsprofile!$B$17:$B$22,"Schulbetrieb",Nutzungsprofile!$G$17:$G$22)*Kalender!C33/SUM(Kalender!$C$5:$C$370),0)+IFERROR(SUMIF(Nutzungsprofile!$B$17:$B$22,"Halle",Nutzungsprofile!$G$17:$G$22)*Kalender!D33/SUM(Kalender!$D$5:$D$370),0)+IFERROR(SUMIF(Nutzungsprofile!$B$17:$B$22,"Individuell",Nutzungsprofile!$G$17:$G$22)*Kalender!E33/SUM(Kalender!$E$5:$E$370),0))*Szenarien!$D$8,0) -> 4.446 | E33: =IFERROR(MIN(C33,Eingaben!$B$17)*Eingaben!$B$16,0) -> 2.2344 | F33: =IFERROR(E33*Eingaben!$B$15,0) -> 2.01096 | G33: =IFERROR(IF(Kalender!A33="",0,J32*(1-Eingaben!$B$20)),0) -> 0.59122224 | H33: =MIN(G33,D33) -> 0.59122224 | I33: =IFERROR(MIN(F33*Eingaben!$B$19,MAX(0,D33-H33)),0) -> 1.407672 | J33: =IFERROR(MIN(Eingaben!$B$18,MAX(0,F33-I33)),0) -> 0.603288 | K33: =H33+I33 -> 1.9988942 | L33: =MAX(0,D33-K33) -> 2.4471058 | M33: =MAX(0,F33-I33-J33) -> 0 | N33: =IF(Kalender!A33="",0,J32-H33) -> 0.01206576
A34: ="" | B34: =30 -> 30 | C34: =IF(Szenarien!$H$8="OK",(IFERROR(SUMIF(Nutzungsprofile!$B$6:$B$11,"Schulbetrieb",Nutzungsprofile!$G$6:$G$11)*Kalender!C34/SUM(Kalender!$C$5:$C$370),0)+IFERROR(SUMIF(Nutzungsprofile!$B$6:$B$11,"Halle",Nutzungsprofile!$G$6:$G$11)*Kalender!D34/SUM(Kalender!$D$5:$D$370),0)+IFERROR(SUMIF(Nutzungsprofile!$B$6:$B$11,"Individuell",Nutzungsprofile!$G$6:$G$11)*Kalender!E34/SUM(Kalender!$E$5:$E$370),0))*Szenarien!$E$8,0) -> 2.352 | D34: =IF(Szenarien!$H$8="OK",(IFERROR(SUMIF(Nutzungsprofile!$B$17:$B$22,"Schulbetrieb",Nutzungsprofile!$G$17:$G$22)*Kalender!C34/SUM(Kalender!$C$5:$C$370),0)+IFERROR(SUMIF(Nutzungsprofile!$B$17:$B$22,"Halle",Nutzungsprofile!$G$17:$G$22)*Kalender!D34/SUM(Kalender!$D$5:$D$370),0)+IFERROR(SUMIF(Nutzungsprofile!$B$17:$B$22,"Individuell",Nutzungsprofile!$G$17:$G$22)*Kalender!E34/SUM(Kalender!$E$5:$E$370),0))*Szenarien!$D$8,0) -> 4.446 | E34: =IFERROR(MIN(C34,Eingaben!$B$17)*Eingaben!$B$16,0) -> 2.2344 | F34: =IFERROR(E34*Eingaben!$B$15,0) -> 2.01096 | G34: =IFERROR(IF(Kalender!A34="",0,J33*(1-Eingaben!$B$20)),0) -> 0.59122224 | H34: =MIN(G34,D34) -> 0.59122224 | I34: =IFERROR(MIN(F34*Eingaben!$B$19,MAX(0,D34-H34)),0) -> 1.407672 | J34: =IFERROR(MIN(Eingaben!$B$18,MAX(0,F34-I34)),0) -> 0.603288 | K34: =H34+I34 -> 1.9988942 | L34: =MAX(0,D34-K34) -> 2.4471058 | M34: =MAX(0,F34-I34-J34) -> 0 | N34: =IF(Kalender!A34="",0,J33-H34) -> 0.01206576
A35: ="" | B35: =31 -> 31 | C35: =IF(Szenarien!$H$8="OK",(IFERROR(SUMIF(Nutzungsprofile!$B$6:$B$11,"Schulbetrieb",Nutzungsprofile!$G$6:$G$11)*Kalender!C35/SUM(Kalender!$C$5:$C$370),0)+IFERROR(SUMIF(Nutzungsprofile!$B$6:$B$11,"Halle",Nutzungsprofile!$G$6:$G$11)*Kalender!D35/SUM(Kalender!$D$5:$D$370),0)+IFERROR(SUMIF(Nutzungsprofile!$B$6:$B$11,"Individuell",Nutzungsprofile!$G$6:$G$11)*Kalender!E35/SUM(Kalender!$E$5:$E$370),0))*Szenarien!$E$8,0) -> 1.632 | D35: =IF(Szenarien!$H$8="OK",(IFERROR(SUMIF(Nutzungsprofile!$B$17:$B$22,"Schulbetrieb",Nutzungsprofile!$G$17:$G$22)*Kalender!C35/SUM(Kalender!$C$5:$C$370),0)+IFERROR(SUMIF(Nutzungsprofile!$B$17:$B$22,"Halle",Nutzungsprofile!$G$17:$G$22)*Kalender!D35/SUM(Kalender!$D$5:$D$370),0)+IFERROR(SUMIF(Nutzungsprofile!$B$17:$B$22,"Individuell",Nutzungsprofile!$G$17:$G$22)*Kalender!E35/SUM(Kalender!$E$5:$E$370),0))*Szenarien!$D$8,0) -> 0.801 | E35: =IFERROR(MIN(C35,Eingaben!$B$17)*Eingaben!$B$16,0) -> 1.5504 | F35: =IFERROR(E35*Eingaben!$B$15,0) -> 1.39536 | G35: =IFERROR(IF(Kalender!A35="",0,J34*(1-Eingaben!$B$20)),0) -> 0.59122224 | H35: =MIN(G35,D35) -> 0.59122224 | I35: =IFERROR(MIN(F35*Eingaben!$B$19,MAX(0,D35-H35)),0) -> 0.20977776 | J35: =IFERROR(MIN(Eingaben!$B$18,MAX(0,F35-I35)),0) -> 1.1855822 | K35: =H35+I35 -> 0.801 | L35: =MAX(0,D35-K35) -> 0 | M35: =MAX(0,F35-I35-J35) -> 0 | N35: =IF(Kalender!A35="",0,J34-H35) -> 0.01206576
A36: ="" | B36: =32 -> 32 | C36: =IF(Szenarien!$H$8="OK",(IFERROR(SUMIF(Nutzungsprofile!$B$6:$B$11,"Schulbetrieb",Nutzungsprofile!$G$6:$G$11)*Kalender!C36/SUM(Kalender!$C$5:$C$370),0)+IFERROR(SUMIF(Nutzungsprofile!$B$6:$B$11,"Halle",Nutzungsprofile!$G$6:$G$11)*Kalender!D36/SUM(Kalender!$D$5:$D$370),0)+IFERROR(SUMIF(Nutzungsprofile!$B$6:$B$11,"Individuell",Nutzungsprofile!$G$6:$G$11)*Kalender!E36/SUM(Kalender!$E$5:$E$370),0))*Szenarien!$E$8,0) -> 1.632 | D36: =IF(Szenarien!$H$8="OK",(IFERROR(SUMIF(Nutzungsprofile!$B$17:$B$22,"Schulbetrieb",Nutzungsprofile!$G$17:$G$22)*Kalender!C36/SUM(Kalender!$C$5:$C$370),0)+IFERROR(SUMIF(Nutzungsprofile!$B$17:$B$22,"Halle",Nutzungsprofile!$G$17:$G$22)*Kalender!D36/SUM(Kalender!$D$5:$D$370),0)+IFERROR(SUMIF(Nutzungsprofile!$B$17:$B$22,"Individuell",Nutzungsprofile!$G$17:$G$22)*Kalender!E36/SUM(Kalender!$E$5:$E$370),0))*Szenarien!$D$8,0) -> 0.801 | E36: =IFERROR(MIN(C36,Eingaben!$B$17)*Eingaben!$B$16,0) -> 1.5504 | F36: =IFERROR(E36*Eingaben!$B$15,0) -> 1.39536 | G36: =IFERROR(IF(Kalender!A36="",0,J35*(1-Eingaben!$B$20)),0) -> 1.1618706 | H36: =MIN(G36,D36) -> 0.801 | I36: =IFERROR(MIN(F36*Eingaben!$B$19,MAX(0,D36-H36)),0) -> 0 | J36: =IFERROR(MIN(Eingaben!$B$18,MAX(0,F36-I36)),0) -> 1.39536 | K36: =H36+I36 -> 0.801 | L36: =MAX(0,D36-K36) -> 0 | M36: =MAX(0,F36-I36-J36) -> 0 | N36: =IF(Kalender!A36="",0,J35-H36) -> 0.38458224
A37: ="" | B37: =33 -> 33 | C37: =IF(Szenarien!$H$8="OK",(IFERROR(SUMIF(Nutzungsprofile!$B$6:$B$11,"Schulbetrieb",Nutzungsprofile!$G$6:$G$11)*Kalender!C37/SUM(Kalender!$C$5:$C$370),0)+IFERROR(SUMIF(Nutzungsprofile!$B$6:$B$11,"Halle",Nutzungsprofile!$G$6:$G$11)*Kalender!D37/SUM(Kalender!$D$5:$D$370),0)+IFERROR(SUMIF(Nutzungsprofile!$B$6:$B$11,"Individuell",Nutzungsprofile!$G$6:$G$11)*Kalender!E37/SUM(Kalender!$E$5:$E$370),0))*Szenarien!$E$8,0) -> 2.352 | D37: =IF(Szenarien!$H$8="OK",(IFERROR(SUMIF(Nutzungsprofile!$B$17:$B$22,"Schulbetrieb",Nutzungsprofile!$G$17:$G$22)*Kalender!C37/SUM(Kalender!$C$5:$C$370),0)+IFERROR(SUMIF(Nutzungsprofile!$B$17:$B$22,"Halle",Nutzungsprofile!$G$17:$G$22)*Kalender!D37/SUM(Kalender!$D$5:$D$370),0)+IFERROR(SUMIF(Nutzungsprofile!$B$17:$B$22,"Individuell",Nutzungsprofile!$G$17:$G$22)*Kalender!E37/SUM(Kalender!$E$5:$E$370),0))*Szenarien!$D$8,0) -> 4.446 | E37: =IFERROR(MIN(C37,Eingaben!$B$17)*Eingaben!$B$16,0) -> 2.2344 | F37: =IFERROR(E37*Eingaben!$B$15,0) -> 2.01096 | G37: =IFERROR(IF(Kalender!A37="",0,J36*(1-Eingaben!$B$20)),0) -> 1.3674528 | H37: =MIN(G37,D37) -> 1.3674528 | I37: =IFERROR(MIN(F37*Eingaben!$B$19,MAX(0,D37-H37)),0) -> 1.407672 | J37: =IFERROR(MIN(Eingaben!$B$18,MAX(0,F37-I37)),0) -> 0.603288 | K37: =H37+I37 -> 2.7751248 | L37: =MAX(0,D37-K37) -> 1.6708752 | M37: =MAX(0,F37-I37-J37) -> 0 | N37: =IF(Kalender!A37="",0,J36-H37) -> 0.0279072
A38: ="" | B38: =34 -> 34 | C38: =IF(Szenarien!$H$8="OK",(IFERROR(SUMIF(Nutzungsprofile!$B$6:$B$11,"Schulbetrieb",Nutzungsprofile!$G$6:$G$11)*Kalender!C38/SUM(Kalender!$C$5:$C$370),0)+IFERROR(SUMIF(Nutzungsprofile!$B$6:$B$11,"Halle",Nutzungsprofile!$G$6:$G$11)*Kalender!D38/SUM(Kalender!$D$5:$D$370),0)+IFERROR(SUMIF(Nutzungsprofile!$B$6:$B$11,"Individuell",Nutzungsprofile!$G$6:$G$11)*Kalender!E38/SUM(Kalender!$E$5:$E$370),0))*Szenarien!$E$8,0) -> 2.352 | D38: =IF(Szenarien!$H$8="OK",(IFERROR(SUMIF(Nutzungsprofile!$B$17:$B$22,"Schulbetrieb",Nutzungsprofile!$G$17:$G$22)*Kalender!C38/SUM(Kalender!$C$5:$C$370),0)+IFERROR(SUMIF(Nutzungsprofile!$B$17:$B$22,"Halle",Nutzungsprofile!$G$17:$G$22)*Kalender!D38/SUM(Kalender!$D$5:$D$370),0)+IFERROR(SUMIF(Nutzungsprofile!$B$17:$B$22,"Individuell",Nutzungsprofile!$G$17:$G$22)*Kalender!E38/SUM(Kalender!$E$5:$E$370),0))*Szenarien!$D$8,0) -> 4.446 | E38: =IFERROR(MIN(C38,Eingaben!$B$17)*Eingaben!$B$16,0) -> 2.2344 | F38: =IFERROR(E38*Eingaben!$B$15,0) -> 2.01096 | G38: =IFERROR(IF(Kalender!A38="",0,J37*(1-Eingaben!$B$20)),0) -> 0.59122224 | H38: =MIN(G38,D38) -> 0.59122224 | I38: =IFERROR(MIN(F38*Eingaben!$B$19,MAX(0,D38-H38)),0) -> 1.407672 | J38: =IFERROR(MIN(Eingaben!$B$18,MAX(0,F38-I38)),0) -> 0.603288 | K38: =H38+I38 -> 1.9988942 | L38: =MAX(0,D38-K38) -> 2.4471058 | M38: =MAX(0,F38-I38-J38) -> 0 | N38: =IF(Kalender!A38="",0,J37-H38) -> 0.01206576
A39: ="" | B39: =35 -> 35 | C39: =IF(Szenarien!$H$8="OK",(IFERROR(SUMIF(Nutzungsprofile!$B$6:$B$11,"Schulbetrieb",Nutzungsprofile!$G$6:$G$11)*Kalender!C39/SUM(Kalender!$C$5:$C$370),0)+IFERROR(SUMIF(Nutzungsprofile!$B$6:$B$11,"Halle",Nutzungsprofile!$G$6:$G$11)*Kalender!D39/SUM(Kalender!$D$5:$D$370),0)+IFERROR(SUMIF(Nutzungsprofile!$B$6:$B$11,"Individuell",Nutzungsprofile!$G$6:$G$11)*Kalender!E39/SUM(Kalender!$E$5:$E$370),0))*Szenarien!$E$8,0) -> 2.352 | D39: =IF(Szenarien!$H$8="OK",(IFERROR(SUMIF(Nutzungsprofile!$B$17:$B$22,"Schulbetrieb",Nutzungsprofile!$G$17:$G$22)*Kalender!C39/SUM(Kalender!$C$5:$C$370),0)+IFERROR(SUMIF(Nutzungsprofile!$B$17:$B$22,"Halle",Nutzungsprofile!$G$17:$G$22)*Kalender!D39/SUM(Kalender!$D$5:$D$370),0)+IFERROR(SUMIF(Nutzungsprofile!$B$17:$B$22,"Individuell",Nutzungsprofile!$G$17:$G$22)*Kalender!E39/SUM(Kalender!$E$5:$E$370),0))*Szenarien!$D$8,0) -> 4.446 | E39: =IFERROR(MIN(C39,Eingaben!$B$17)*Eingaben!$B$16,0) -> 2.2344 | F39: =IFERROR(E39*Eingaben!$B$15,0) -> 2.01096 | G39: =IFERROR(IF(Kalender!A39="",0,J38*(1-Eingaben!$B$20)),0) -> 0.59122224 | H39: =MIN(G39,D39) -> 0.59122224 | I39: =IFERROR(MIN(F39*Eingaben!$B$19,MAX(0,D39-H39)),0) -> 1.407672 | J39: =IFERROR(MIN(Eingaben!$B$18,MAX(0,F39-I39)),0) -> 0.603288 | K39: =H39+I39 -> 1.9988942 | L39: =MAX(0,D39-K39) -> 2.4471058 | M39: =MAX(0,F39-I39-J39) -> 0 | N39: =IF(Kalender!A39="",0,J38-H39) -> 0.01206576
A40: ="" | B40: =36 -> 36 | C40: =IF(Szenarien!$H$8="OK",(IFERROR(SUMIF(Nutzungsprofile!$B$6:$B$11,"Schulbetrieb",Nutzungsprofile!$G$6:$G$11)*Kalender!C40/SUM(Kalender!$C$5:$C$370),0)+IFERROR(SUMIF(Nutzungsprofile!$B$6:$B$11,"Halle",Nutzungsprofile!$G$6:$G$11)*Kalender!D40/SUM(Kalender!$D$5:$D$370),0)+IFERROR(SUMIF(Nutzungsprofile!$B$6:$B$11,"Individuell",Nutzungsprofile!$G$6:$G$11)*Kalender!E40/SUM(Kalender!$E$5:$E$370),0))*Szenarien!$E$8,0) -> 2.352 | D40: =IF(Szenarien!$H$8="OK",(IFERROR(SUMIF(Nutzungsprofile!$B$17:$B$22,"Schulbetrieb",Nutzungsprofile!$G$17:$G$22)*Kalender!C40/SUM(Kalender!$C$5:$C$370),0)+IFERROR(SUMIF(Nutzungsprofile!$B$17:$B$22,"Halle",Nutzungsprofile!$G$17:$G$22)*Kalender!D40/SUM(Kalender!$D$5:$D$370),0)+IFERROR(SUMIF(Nutzungsprofile!$B$17:$B$22,"Individuell",Nutzungsprofile!$G$17:$G$22)*Kalender!E40/SUM(Kalender!$E$5:$E$370),0))*Szenarien!$D$8,0) -> 4.446 | E40: =IFERROR(MIN(C40,Eingaben!$B$17)*Eingaben!$B$16,0) -> 2.2344 | F40: =IFERROR(E40*Eingaben!$B$15,0) -> 2.01096 | G40: =IFERROR(IF(Kalender!A40="",0,J39*(1-Eingaben!$B$20)),0) -> 0.59122224 | H40: =MIN(G40,D40) -> 0.59122224 | I40: =IFERROR(MIN(F40*Eingaben!$B$19,MAX(0,D40-H40)),0) -> 1.407672 | J40: =IFERROR(MIN(Eingaben!$B$18,MAX(0,F40-I40)),0) -> 0.603288 | K40: =H40+I40 -> 1.9988942 | L40: =MAX(0,D40-K40) -> 2.4471058 | M40: =MAX(0,F40-I40-J40) -> 0 | N40: =IF(Kalender!A40="",0,J39-H40) -> 0.01206576
A41: ="" | B41: =37 -> 37 | C41: =IF(Szenarien!$H$8="OK",(IFERROR(SUMIF(Nutzungsprofile!$B$6:$B$11,"Schulbetrieb",Nutzungsprofile!$G$6:$G$11)*Kalender!C41/SUM(Kalender!$C$5:$C$370),0)+IFERROR(SUMIF(Nutzungsprofile!$B$6:$B$11,"Halle",Nutzungsprofile!$G$6:$G$11)*Kalender!D41/SUM(Kalender!$D$5:$D$370),0)+IFERROR(SUMIF(Nutzungsprofile!$B$6:$B$11,"Individuell",Nutzungsprofile!$G$6:$G$11)*Kalender!E41/SUM(Kalender!$E$5:$E$370),0))*Szenarien!$E$8,0) -> 2.352 | D41: =IF(Szenarien!$H$8="OK",(IFERROR(SUMIF(Nutzungsprofile!$B$17:$B$22,"Schulbetrieb",Nutzungsprofile!$G$17:$G$22)*Kalender!C41/SUM(Kalender!$C$5:$C$370),0)+IFERROR(SUMIF(Nutzungsprofile!$B$17:$B$22,"Halle",Nutzungsprofile!$G$17:$G$22)*Kalender!D41/SUM(Kalender!$D$5:$D$370),0)+IFERROR(SUMIF(Nutzungsprofile!$B$17:$B$22,"Individuell",Nutzungsprofile!$G$17:$G$22)*Kalender!E41/SUM(Kalender!$E$5:$E$370),0))*Szenarien!$D$8,0) -> 4.446 | E41: =IFERROR(MIN(C41,Eingaben!$B$17)*Eingaben!$B$16,0) -> 2.2344 | F41: =IFERROR(E41*Eingaben!$B$15,0) -> 2.01096 | G41: =IFERROR(IF(Kalender!A41="",0,J40*(1-Eingaben!$B$20)),0) -> 0.59122224 | H41: =MIN(G41,D41) -> 0.59122224 | I41: =IFERROR(MIN(F41*Eingaben!$B$19,MAX(0,D41-H41)),0) -> 1.407672 | J41: =IFERROR(MIN(Eingaben!$B$18,MAX(0,F41-I41)),0) -> 0.603288 | K41: =H41+I41 -> 1.9988942 | L41: =MAX(0,D41-K41) -> 2.4471058 | M41: =MAX(0,F41-I41-J41) -> 0 | N41: =IF(Kalender!A41="",0,J40-H41) -> 0.01206576
A42: ="" | B42: =38 -> 38 | C42: =IF(Szenarien!$H$8="OK",(IFERROR(SUMIF(Nutzungsprofile!$B$6:$B$11,"Schulbetrieb",Nutzungsprofile!$G$6:$G$11)*Kalender!C42/SUM(Kalender!$C$5:$C$370),0)+IFERROR(SUMIF(Nutzungsprofile!$B$6:$B$11,"Halle",Nutzungsprofile!$G$6:$G$11)*Kalender!D42/SUM(Kalender!$D$5:$D$370),0)+IFERROR(SUMIF(Nutzungsprofile!$B$6:$B$11,"Individuell",Nutzungsprofile!$G$6:$G$11)*Kalender!E42/SUM(Kalender!$E$5:$E$370),0))*Szenarien!$E$8,0) -> 1.632 | D42: =IF(Szenarien!$H$8="OK",(IFERROR(SUMIF(Nutzungsprofile!$B$17:$B$22,"Schulbetrieb",Nutzungsprofile!$G$17:$G$22)*Kalender!C42/SUM(Kalender!$C$5:$C$370),0)+IFERROR(SUMIF(Nutzungsprofile!$B$17:$B$22,"Halle",Nutzungsprofile!$G$17:$G$22)*Kalender!D42/SUM(Kalender!$D$5:$D$370),0)+IFERROR(SUMIF(Nutzungsprofile!$B$17:$B$22,"Individuell",Nutzungsprofile!$G$17:$G$22)*Kalender!E42/SUM(Kalender!$E$5:$E$370),0))*Szenarien!$D$8,0) -> 0.801 | E42: =IFERROR(MIN(C42,Eingaben!$B$17)*Eingaben!$B$16,0) -> 1.5504 | F42: =IFERROR(E42*Eingaben!$B$15,0) -> 1.39536 | G42: =IFERROR(IF(Kalender!A42="",0,J41*(1-Eingaben!$B$20)),0) -> 0.59122224 | H42: =MIN(G42,D42) -> 0.59122224 | I42: =IFERROR(MIN(F42*Eingaben!$B$19,MAX(0,D42-H42)),0) -> 0.20977776 | J42: =IFERROR(MIN(Eingaben!$B$18,MAX(0,F42-I42)),0) -> 1.1855822 | K42: =H42+I42 -> 0.801 | L42: =MAX(0,D42-K42) -> 0 | M42: =MAX(0,F42-I42-J42) -> 0 | N42: =IF(Kalender!A42="",0,J41-H42) -> 0.01206576
A43: ="" | B43: =39 -> 39 | C43: =IF(Szenarien!$H$8="OK",(IFERROR(SUMIF(Nutzungsprofile!$B$6:$B$11,"Schulbetrieb",Nutzungsprofile!$G$6:$G$11)*Kalender!C43/SUM(Kalender!$C$5:$C$370),0)+IFERROR(SUMIF(Nutzungsprofile!$B$6:$B$11,"Halle",Nutzungsprofile!$G$6:$G$11)*Kalender!D43/SUM(Kalender!$D$5:$D$370),0)+IFERROR(SUMIF(Nutzungsprofile!$B$6:$B$11,"Individuell",Nutzungsprofile!$G$6:$G$11)*Kalender!E43/SUM(Kalender!$E$5:$E$370),0))*Szenarien!$E$8,0) -> 1.632 | D43: =IF(Szenarien!$H$8="OK",(IFERROR(SUMIF(Nutzungsprofile!$B$17:$B$22,"Schulbetrieb",Nutzungsprofile!$G$17:$G$22)*Kalender!C43/SUM(Kalender!$C$5:$C$370),0)+IFERROR(SUMIF(Nutzungsprofile!$B$17:$B$22,"Halle",Nutzungsprofile!$G$17:$G$22)*Kalender!D43/SUM(Kalender!$D$5:$D$370),0)+IFERROR(SUMIF(Nutzungsprofile!$B$17:$B$22,"Individuell",Nutzungsprofile!$G$17:$G$22)*Kalender!E43/SUM(Kalender!$E$5:$E$370),0))*Szenarien!$D$8,0) -> 0.801 | E43: =IFERROR(MIN(C43,Eingaben!$B$17)*Eingaben!$B$16,0) -> 1.5504 | F43: =IFERROR(E43*Eingaben!$B$15,0) -> 1.39536 | G43: =IFERROR(IF(Kalender!A43="",0,J42*(1-Eingaben!$B$20)),0) -> 1.1618706 | H43: =MIN(G43,D43) -> 0.801 | I43: =IFERROR(MIN(F43*Eingaben!$B$19,MAX(0,D43-H43)),0) -> 0 | J43: =IFERROR(MIN(Eingaben!$B$18,MAX(0,F43-I43)),0) -> 1.39536 | K43: =H43+I43 -> 0.801 | L43: =MAX(0,D43-K43) -> 0 | M43: =MAX(0,F43-I43-J43) -> 0 | N43: =IF(Kalender!A43="",0,J42-H43) -> 0.38458224
A44: ="" | B44: =40 -> 40 | C44: =IF(Szenarien!$H$8="OK",(IFERROR(SUMIF(Nutzungsprofile!$B$6:$B$11,"Schulbetrieb",Nutzungsprofile!$G$6:$G$11)*Kalender!C44/SUM(Kalender!$C$5:$C$370),0)+IFERROR(SUMIF(Nutzungsprofile!$B$6:$B$11,"Halle",Nutzungsprofile!$G$6:$G$11)*Kalender!D44/SUM(Kalender!$D$5:$D$370),0)+IFERROR(SUMIF(Nutzungsprofile!$B$6:$B$11,"Individuell",Nutzungsprofile!$G$6:$G$11)*Kalender!E44/SUM(Kalender!$E$5:$E$370),0))*Szenarien!$E$8,0) -> 2.352 | D44: =IF(Szenarien!$H$8="OK",(IFERROR(SUMIF(Nutzungsprofile!$B$17:$B$22,"Schulbetrieb",Nutzungsprofile!$G$17:$G$22)*Kalender!C44/SUM(Kalender!$C$5:$C$370),0)+IFERROR(SUMIF(Nutzungsprofile!$B$17:$B$22,"Halle",Nutzungsprofile!$G$17:$G$22)*Kalender!D44/SUM(Kalender!$D$5:$D$370),0)+IFERROR(SUMIF(Nutzungsprofile!$B$17:$B$22,"Individuell",Nutzungsprofile!$G$17:$G$22)*Kalender!E44/SUM(Kalender!$E$5:$E$370),0))*Szenarien!$D$8,0) -> 4.446 | E44: =IFERROR(MIN(C44,Eingaben!$B$17)*Eingaben!$B$16,0) -> 2.2344 | F44: =IFERROR(E44*Eingaben!$B$15,0) -> 2.01096 | G44: =IFERROR(IF(Kalender!A44="",0,J43*(1-Eingaben!$B$20)),0) -> 1.3674528 | H44: =MIN(G44,D44) -> 1.3674528 | I44: =IFERROR(MIN(F44*Eingaben!$B$19,MAX(0,D44-H44)),0) -> 1.407672 | J44: =IFERROR(MIN(Eingaben!$B$18,MAX(0,F44-I44)),0) -> 0.603288 | K44: =H44+I44 -> 2.7751248 | L44: =MAX(0,D44-K44) -> 1.6708752 | M44: =MAX(0,F44-I44-J44) -> 0 | N44: =IF(Kalender!A44="",0,J43-H44) -> 0.0279072
A45: ="" | B45: =41 -> 41 | C45: =IF(Szenarien!$H$8="OK",(IFERROR(SUMIF(Nutzungsprofile!$B$6:$B$11,"Schulbetrieb",Nutzungsprofile!$G$6:$G$11)*Kalender!C45/SUM(Kalender!$C$5:$C$370),0)+IFERROR(SUMIF(Nutzungsprofile!$B$6:$B$11,"Halle",Nutzungsprofile!$G$6:$G$11)*Kalender!D45/SUM(Kalender!$D$5:$D$370),0)+IFERROR(SUMIF(Nutzungsprofile!$B$6:$B$11,"Individuell",Nutzungsprofile!$G$6:$G$11)*Kalender!E45/SUM(Kalender!$E$5:$E$370),0))*Szenarien!$E$8,0) -> 2.352 | D45: =IF(Szenarien!$H$8="OK",(IFERROR(SUMIF(Nutzungsprofile!$B$17:$B$22,"Schulbetrieb",Nutzungsprofile!$G$17:$G$22)*Kalender!C45/SUM(Kalender!$C$5:$C$370),0)+IFERROR(SUMIF(Nutzungsprofile!$B$17:$B$22,"Halle",Nutzungsprofile!$G$17:$G$22)*Kalender!D45/SUM(Kalender!$D$5:$D$370),0)+IFERROR(SUMIF(Nutzungsprofile!$B$17:$B$22,"Individuell",Nutzungsprofile!$G$17:$G$22)*Kalender!E45/SUM(Kalender!$E$5:$E$370),0))*Szenarien!$D$8,0) -> 4.446 | E45: =IFERROR(MIN(C45,Eingaben!$B$17)*Eingaben!$B$16,0) -> 2.2344 | F45: =IFERROR(E45*Eingaben!$B$15,0) -> 2.01096 | G45: =IFERROR(IF(Kalender!A45="",0,J44*(1-Eingaben!$B$20)),0) -> 0.59122224 | H45: =MIN(G45,D45) -> 0.59122224 | I45: =IFERROR(MIN(F45*Eingaben!$B$19,MAX(0,D45-H45)),0) -> 1.407672 | J45: =IFERROR(MIN(Eingaben!$B$18,MAX(0,F45-I45)),0) -> 0.603288 | K45: =H45+I45 -> 1.9988942 | L45: =MAX(0,D45-K45) -> 2.4471058 | M45: =MAX(0,F45-I45-J45) -> 0 | N45: =IF(Kalender!A45="",0,J44-H45) -> 0.01206576
A46: ="" | B46: =42 -> 42 | C46: =IF(Szenarien!$H$8="OK",(IFERROR(SUMIF(Nutzungsprofile!$B$6:$B$11,"Schulbetrieb",Nutzungsprofile!$G$6:$G$11)*Kalender!C46/SUM(Kalender!$C$5:$C$370),0)+IFERROR(SUMIF(Nutzungsprofile!$B$6:$B$11,"Halle",Nutzungsprofile!$G$6:$G$11)*Kalender!D46/SUM(Kalender!$D$5:$D$370),0)+IFERROR(SUMIF(Nutzungsprofile!$B$6:$B$11,"Individuell",Nutzungsprofile!$G$6:$G$11)*Kalender!E46/SUM(Kalender!$E$5:$E$370),0))*Szenarien!$E$8,0) -> 2.352 | D46: =IF(Szenarien!$H$8="OK",(IFERROR(SUMIF(Nutzungsprofile!$B$17:$B$22,"Schulbetrieb",Nutzungsprofile!$G$17:$G$22)*Kalender!C46/SUM(Kalender!$C$5:$C$370),0)+IFERROR(SUMIF(Nutzungsprofile!$B$17:$B$22,"Halle",Nutzungsprofile!$G$17:$G$22)*Kalender!D46/SUM(Kalender!$D$5:$D$370),0)+IFERROR(SUMIF(Nutzungsprofile!$B$17:$B$22,"Individuell",Nutzungsprofile!$G$17:$G$22)*Kalender!E46/SUM(Kalender!$E$5:$E$370),0))*Szenarien!$D$8,0) -> 4.446 | E46: =IFERROR(MIN(C46,Eingaben!$B$17)*Eingaben!$B$16,0) -> 2.2344 | F46: =IFERROR(E46*Eingaben!$B$15,0) -> 2.01096 | G46: =IFERROR(IF(Kalender!A46="",0,J45*(1-Eingaben!$B$20)),0) -> 0.59122224 | H46: =MIN(G46,D46) -> 0.59122224 | I46: =IFERROR(MIN(F46*Eingaben!$B$19,MAX(0,D46-H46)),0) -> 1.407672 | J46: =IFERROR(MIN(Eingaben!$B$18,MAX(0,F46-I46)),0) -> 0.603288 | K46: =H46+I46 -> 1.9988942 | L46: =MAX(0,D46-K46) -> 2.4471058 | M46: =MAX(0,F46-I46-J46) -> 0 | N46: =IF(Kalender!A46="",0,J45-H46) -> 0.01206576
A47: ="" | B47: =43 -> 43 | C47: =IF(Szenarien!$H$8="OK",(IFERROR(SUMIF(Nutzungsprofile!$B$6:$B$11,"Schulbetrieb",Nutzungsprofile!$G$6:$G$11)*Kalender!C47/SUM(Kalender!$C$5:$C$370),0)+IFERROR(SUMIF(Nutzungsprofile!$B$6:$B$11,"Halle",Nutzungsprofile!$G$6:$G$11)*Kalender!D47/SUM(Kalender!$D$5:$D$370),0)+IFERROR(SUMIF(Nutzungsprofile!$B$6:$B$11,"Individuell",Nutzungsprofile!$G$6:$G$11)*Kalender!E47/SUM(Kalender!$E$5:$E$370),0))*Szenarien!$E$8,0) -> 2.352 | D47: =IF(Szenarien!$H$8="OK",(IFERROR(SUMIF(Nutzungsprofile!$B$17:$B$22,"Schulbetrieb",Nutzungsprofile!$G$17:$G$22)*Kalender!C47/SUM(Kalender!$C$5:$C$370),0)+IFERROR(SUMIF(Nutzungsprofile!$B$17:$B$22,"Halle",Nutzungsprofile!$G$17:$G$22)*Kalender!D47/SUM(Kalender!$D$5:$D$370),0)+IFERROR(SUMIF(Nutzungsprofile!$B$17:$B$22,"Individuell",Nutzungsprofile!$G$17:$G$22)*Kalender!E47/SUM(Kalender!$E$5:$E$370),0))*Szenarien!$D$8,0) -> 4.446 | E47: =IFERROR(MIN(C47,Eingaben!$B$17)*Eingaben!$B$16,0) -> 2.2344 | F47: =IFERROR(E47*Eingaben!$B$15,0) -> 2.01096 | G47: =IFERROR(IF(Kalender!A47="",0,J46*(1-Eingaben!$B$20)),0) -> 0.59122224 | H47: =MIN(G47,D47) -> 0.59122224 | I47: =IFERROR(MIN(F47*Eingaben!$B$19,MAX(0,D47-H47)),0) -> 1.407672 | J47: =IFERROR(MIN(Eingaben!$B$18,MAX(0,F47-I47)),0) -> 0.603288 | K47: =H47+I47 -> 1.9988942 | L47: =MAX(0,D47-K47) -> 2.4471058 | M47: =MAX(0,F47-I47-J47) -> 0 | N47: =IF(Kalender!A47="",0,J46-H47) -> 0.01206576
A48: ="" | B48: =44 -> 44 | C48: =IF(Szenarien!$H$8="OK",(IFERROR(SUMIF(Nutzungsprofile!$B$6:$B$11,"Schulbetrieb",Nutzungsprofile!$G$6:$G$11)*Kalender!C48/SUM(Kalender!$C$5:$C$370),0)+IFERROR(SUMIF(Nutzungsprofile!$B$6:$B$11,"Halle",Nutzungsprofile!$G$6:$G$11)*Kalender!D48/SUM(Kalender!$D$5:$D$370),0)+IFERROR(SUMIF(Nutzungsprofile!$B$6:$B$11,"Individuell",Nutzungsprofile!$G$6:$G$11)*Kalender!E48/SUM(Kalender!$E$5:$E$370),0))*Szenarien!$E$8,0) -> 2.352 | D48: =IF(Szenarien!$H$8="OK",(IFERROR(SUMIF(Nutzungsprofile!$B$17:$B$22,"Schulbetrieb",Nutzungsprofile!$G$17:$G$22)*Kalender!C48/SUM(Kalender!$C$5:$C$370),0)+IFERROR(SUMIF(Nutzungsprofile!$B$17:$B$22,"Halle",Nutzungsprofile!$G$17:$G$22)*Kalender!D48/SUM(Kalender!$D$5:$D$370),0)+IFERROR(SUMIF(Nutzungsprofile!$B$17:$B$22,"Individuell",Nutzungsprofile!$G$17:$G$22)*Kalender!E48/SUM(Kalender!$E$5:$E$370),0))*Szenarien!$D$8,0) -> 4.446 | E48: =IFERROR(MIN(C48,Eingaben!$B$17)*Eingaben!$B$16,0) -> 2.2344 | F48: =IFERROR(E48*Eingaben!$B$15,0) -> 2.01096 | G48: =IFERROR(IF(Kalender!A48="",0,J47*(1-Eingaben!$B$20)),0) -> 0.59122224 | H48: =MIN(G48,D48) -> 0.59122224 | I48: =IFERROR(MIN(F48*Eingaben!$B$19,MAX(0,D48-H48)),0) -> 1.407672 | J48: =IFERROR(MIN(Eingaben!$B$18,MAX(0,F48-I48)),0) -> 0.603288 | K48: =H48+I48 -> 1.9988942 | L48: =MAX(0,D48-K48) -> 2.4471058 | M48: =MAX(0,F48-I48-J48) -> 0 | N48: =IF(Kalender!A48="",0,J47-H48) -> 0.01206576
A49: ="" | B49: =45 -> 45 | C49: =IF(Szenarien!$H$8="OK",(IFERROR(SUMIF(Nutzungsprofile!$B$6:$B$11,"Schulbetrieb",Nutzungsprofile!$G$6:$G$11)*Kalender!C49/SUM(Kalender!$C$5:$C$370),0)+IFERROR(SUMIF(Nutzungsprofile!$B$6:$B$11,"Halle",Nutzungsprofile!$G$6:$G$11)*Kalender!D49/SUM(Kalender!$D$5:$D$370),0)+IFERROR(SUMIF(Nutzungsprofile!$B$6:$B$11,"Individuell",Nutzungsprofile!$G$6:$G$11)*Kalender!E49/SUM(Kalender!$E$5:$E$370),0))*Szenarien!$E$8,0) -> 1.632 | D49: =IF(Szenarien!$H$8="OK",(IFERROR(SUMIF(Nutzungsprofile!$B$17:$B$22,"Schulbetrieb",Nutzungsprofile!$G$17:$G$22)*Kalender!C49/SUM(Kalender!$C$5:$C$370),0)+IFERROR(SUMIF(Nutzungsprofile!$B$17:$B$22,"Halle",Nutzungsprofile!$G$17:$G$22)*Kalender!D49/SUM(Kalender!$D$5:$D$370),0)+IFERROR(SUMIF(Nutzungsprofile!$B$17:$B$22,"Individuell",Nutzungsprofile!$G$17:$G$22)*Kalender!E49/SUM(Kalender!$E$5:$E$370),0))*Szenarien!$D$8,0) -> 0.801 | E49: =IFERROR(MIN(C49,Eingaben!$B$17)*Eingaben!$B$16,0) -> 1.5504 | F49: =IFERROR(E49*Eingaben!$B$15,0) -> 1.39536 | G49: =IFERROR(IF(Kalender!A49="",0,J48*(1-Eingaben!$B$20)),0) -> 0.59122224 | H49: =MIN(G49,D49) -> 0.59122224 | I49: =IFERROR(MIN(F49*Eingaben!$B$19,MAX(0,D49-H49)),0) -> 0.20977776 | J49: =IFERROR(MIN(Eingaben!$B$18,MAX(0,F49-I49)),0) -> 1.1855822 | K49: =H49+I49 -> 0.801 | L49: =MAX(0,D49-K49) -> 0 | M49: =MAX(0,F49-I49-J49) -> 0 | N49: =IF(Kalender!A49="",0,J48-H49) -> 0.01206576
